Workbook

Sheet Start here
A1: Minimum payment payoff planner
A3: How to use it
A4: 1. Type your balance, the APR and how your card works out its minimum (look in your cardholder agreement).
A5: 2. Type an extra amount you could add on top of your first minimum.
A6: 3. The Compare tab shows three paths: minimum only, freezing your first minimum, and the frozen payment plus extra.
A7: 4. The Months tab shows every month for all three paths.
A9: Assumes no new spending on the card and simple monthly interest. Your issuer's numbers will differ slightly.
A11: Yellow cells are for you to type in. White cells calculate automatically, so leave them alone.
A12: The example numbers only show the format. Replace them with your own.
A14: Step-by-step guide: https://guidelark.com/blog/minimum-payment-trap/
A15: Free to use and share. General information, not financial advice.

Sheet Compare
A1: What paying the minimum really costs
A3: Balance | B3: 3000
A4: APR | B4: 0.22
A5: Minimum: % of balance | B5: 0.01
A6: Minimum adds that month's interest? | B6: Yes | C6: Large issuers usually use 1% plus interest. Some use a flat 2% to 3%.
A7: Minimum floor | B7: 25
A8: Extra on top of the first minimum | B8: 25
A9: Your first minimum | B9: =MIN(B3*(1+B4/12),MAX(B7,B3*B5+IF(B6="Yes",B3*B4/12,0))) -> 85
A11: Path | B11: Monthly payment | C11: Months to clear | D11: Years | E11: Interest paid | F11: Total paid
A12: Minimum only | B12: ="Falls each month" -> Falls each month | C12: =IF(COUNTIF(Months!B4:B603,">0.005")>=600,"Over 50 years",COUNTIF(Months!B4:B603,">0.005")+1) -> 180 | D12: =IF(ISNUMBER(C12),INT(C12/12)&" yr "&MOD(C12,12)&" mo","") -> 15 yr 0 mo | E12: =SUM(Months!C4:C603) -> 4433.1203 | F12: =$B$3+E12 -> 7433.1203
A13: Freeze your first minimum | B13: =B9 -> 85 | C13: =IF(COUNTIF(Months!E4:E603,">0.005")>=600,"Over 50 years",COUNTIF(Months!E4:E603,">0.005")+1) -> 58 | D13: =IF(ISNUMBER(C13),INT(C13/12)&" yr "&MOD(C13,12)&" mo","") -> 4 yr 10 mo | E13: =SUM(Months!F4:F603) -> 1872.8564 | F13: =$B$3+E13 -> 4872.8564
A14: Frozen plus extra | B14: =B9+B8 -> 110 | C14: =IF(COUNTIF(Months!H4:H603,">0.005")>=600,"Over 50 years",COUNTIF(Months!H4:H603,">0.005")+1) -> 39 | D14: =IF(ISNUMBER(C14),INT(C14/12)&" yr "&MOD(C14,12)&" mo","") -> 3 yr 3 mo | E14: =SUM(Months!I4:I603) -> 1197.0209 | F14: =$B$3+E14 -> 4197.0209
A16: Freezing the payment means you keep paying your first minimum even as the required minimum falls.

Sheet Months
A1: Month by month (calculated)
A3: Month | B3: Min only: end balance | C3: Min only: interest | D3: Min only: paid | E3: Frozen: end balance | F3: Frozen: interest | G3: Frozen: paid | H3: Plus extra: end balance | I3: Plus extra: interest | J3: Plus extra: paid
A4: 1 | B4: =MAX(0,Compare!$B$3+C4-D4) -> 2970 | C4: =IF(Compare!$B$3<=0.005,0,Compare!$B$3*Compare!$B$4/12) -> 55 | D4: =IF(Compare!$B$3<=0.005,0,MIN(Compare!$B$3+C4,MAX(Compare!$B$7,Compare!$B$3*Compare!$B$5+IF(Compare!$B$6="Yes",C4,0)))) -> 85 | E4: =MAX(0,Compare!$B$3+F4-G4) -> 2970 | F4: =IF(Compare!$B$3<=0.005,0,Compare!$B$3*Compare!$B$4/12) -> 55 | G4: =IF(Compare!$B$3<=0.005,0,MIN(Compare!$B$3+F4,Compare!$B$9)) -> 85 | H4: =MAX(0,Compare!$B$3+I4-J4) -> 2945 | I4: =IF(Compare!$B$3<=0.005,0,Compare!$B$3*Compare!$B$4/12) -> 55 | J4: =IF(Compare!$B$3<=0.005,0,MIN(Compare!$B$3+I4,Compare!$B$9+Compare!$B$8)) -> 110
A5: 2 | B5: =MAX(0,B4+C5-D5) -> 2940.3 | C5: =IF(B4<=0.005,0,B4*Compare!$B$4/12) -> 54.45 | D5: =IF(B4<=0.005,0,MIN(B4+C5,MAX(Compare!$B$7,B4*Compare!$B$5+IF(Compare!$B$6="Yes",C5,0)))) -> 84.15 | E5: =MAX(0,E4+F5-G5) -> 2939.45 | F5: =IF(E4<=0.005,0,E4*Compare!$B$4/12) -> 54.45 | G5: =IF(E4<=0.005,0,MIN(E4+F5,Compare!$B$9)) -> 85 | H5: =MAX(0,H4+I5-J5) -> 2888.9917 | I5: =IF(H4<=0.005,0,H4*Compare!$B$4/12) -> 53.991667 | J5: =IF(H4<=0.005,0,MIN(H4+I5,Compare!$B$9+Compare!$B$8)) -> 110
A6: 3 | B6: =MAX(0,B5+C6-D6) -> 2910.897 | C6: =IF(B5<=0.005,0,B5*Compare!$B$4/12) -> 53.9055 | D6: =IF(B5<=0.005,0,MIN(B5+C6,MAX(Compare!$B$7,B5*Compare!$B$5+IF(Compare!$B$6="Yes",C6,0)))) -> 83.3085 | E6: =MAX(0,E5+F6-G6) -> 2908.3399 | F6: =IF(E5<=0.005,0,E5*Compare!$B$4/12) -> 53.889917 | G6: =IF(E5<=0.005,0,MIN(E5+F6,Compare!$B$9)) -> 85 | H6: =MAX(0,H5+I6-J6) -> 2831.9565 | I6: =IF(H5<=0.005,0,H5*Compare!$B$4/12) -> 52.964847 | J6: =IF(H5<=0.005,0,MIN(H5+I6,Compare!$B$9+Compare!$B$8)) -> 110
A7: 4 | B7: =MAX(0,B6+C7-D7) -> 2881.788 | C7: =IF(B6<=0.005,0,B6*Compare!$B$4/12) -> 53.366445 | D7: =IF(B6<=0.005,0,MIN(B6+C7,MAX(Compare!$B$7,B6*Compare!$B$5+IF(Compare!$B$6="Yes",C7,0)))) -> 82.475415 | E7: =MAX(0,E6+F7-G7) -> 2876.6595 | F7: =IF(E6<=0.005,0,E6*Compare!$B$4/12) -> 53.319565 | G7: =IF(E6<=0.005,0,MIN(E6+F7,Compare!$B$9)) -> 85 | H7: =MAX(0,H6+I7-J7) -> 2773.8757 | I7: =IF(H6<=0.005,0,H6*Compare!$B$4/12) -> 51.919203 | J7: =IF(H6<=0.005,0,MIN(H6+I7,Compare!$B$9+Compare!$B$8)) -> 110
A8: 5 | B8: =MAX(0,B7+C8-D8) -> 2852.9701 | C8: =IF(B7<=0.005,0,B7*Compare!$B$4/12) -> 52.832781 | D8: =IF(B7<=0.005,0,MIN(B7+C8,MAX(Compare!$B$7,B7*Compare!$B$5+IF(Compare!$B$6="Yes",C8,0)))) -> 81.650661 | E8: =MAX(0,E7+F8-G8) -> 2844.3982 | F8: =IF(E7<=0.005,0,E7*Compare!$B$4/12) -> 52.738757 | G8: =IF(E7<=0.005,0,MIN(E7+F8,Compare!$B$9)) -> 85 | H8: =MAX(0,H7+I8-J8) -> 2714.7301 | I8: =IF(H7<=0.005,0,H7*Compare!$B$4/12) -> 50.854388 | J8: =IF(H7<=0.005,0,MIN(H7+I8,Compare!$B$9+Compare!$B$8)) -> 110
A9: 6 | B9: =MAX(0,B8+C9-D9) -> 2824.4404 | C9: =IF(B8<=0.005,0,B8*Compare!$B$4/12) -> 52.304453 | D9: =IF(B8<=0.005,0,MIN(B8+C9,MAX(Compare!$B$7,B8*Compare!$B$5+IF(Compare!$B$6="Yes",C9,0)))) -> 80.834154 | E9: =MAX(0,E8+F9-G9) -> 2811.5455 | F9: =IF(E8<=0.005,0,E8*Compare!$B$4/12) -> 52.147301 | G9: =IF(E8<=0.005,0,MIN(E8+F9,Compare!$B$9)) -> 85 | H9: =MAX(0,H8+I9-J9) -> 2654.5002 | I9: =IF(H8<=0.005,0,H8*Compare!$B$4/12) -> 49.770052 | J9: =IF(H8<=0.005,0,MIN(H8+I9,Compare!$B$9+Compare!$B$8)) -> 110
A10: 7 | B10: =MAX(0,B9+C10-D10) -> 2796.196 | C10: =IF(B9<=0.005,0,B9*Compare!$B$4/12) -> 51.781408 | D10: =IF(B9<=0.005,0,MIN(B9+C10,MAX(Compare!$B$7,B9*Compare!$B$5+IF(Compare!$B$6="Yes",C10,0)))) -> 80.025813 | E10: =MAX(0,E9+F10-G10) -> 2778.0905 | F10: =IF(E9<=0.005,0,E9*Compare!$B$4/12) -> 51.545002 | G10: =IF(E9<=0.005,0,MIN(E9+F10,Compare!$B$9)) -> 85 | H10: =MAX(0,H9+I10-J10) -> 2593.166 | I10: =IF(H9<=0.005,0,H9*Compare!$B$4/12) -> 48.665836 | J10: =IF(H9<=0.005,0,MIN(H9+I10,Compare!$B$9+Compare!$B$8)) -> 110
A11: 8 | B11: =MAX(0,B10+C11-D11) -> 2768.2341 | C11: =IF(B10<=0.005,0,B10*Compare!$B$4/12) -> 51.263594 | D11: =IF(B10<=0.005,0,MIN(B10+C11,MAX(Compare!$B$7,B10*Compare!$B$5+IF(Compare!$B$6="Yes",C11,0)))) -> 79.225555 | E11: =MAX(0,E10+F11-G11) -> 2744.0222 | F11: =IF(E10<=0.005,0,E10*Compare!$B$4/12) -> 50.93166 | G11: =IF(E10<=0.005,0,MIN(E10+F11,Compare!$B$9)) -> 85 | H11: =MAX(0,H10+I11-J11) -> 2530.7074 | I11: =IF(H10<=0.005,0,H10*Compare!$B$4/12) -> 47.541377 | J11: =IF(H10<=0.005,0,MIN(H10+I11,Compare!$B$9+Compare!$B$8)) -> 110
A12: 9 | B12: =MAX(0,B11+C12-D12) -> 2740.5517 | C12: =IF(B11<=0.005,0,B11*Compare!$B$4/12) -> 50.750958 | D12: =IF(B11<=0.005,0,MIN(B11+C12,MAX(Compare!$B$7,B11*Compare!$B$5+IF(Compare!$B$6="Yes",C12,0)))) -> 78.433299 | E12: =MAX(0,E11+F12-G12) -> 2709.3293 | F12: =IF(E11<=0.005,0,E11*Compare!$B$4/12) -> 50.307074 | G12: =IF(E11<=0.005,0,MIN(E11+F12,Compare!$B$9)) -> 85 | H12: =MAX(0,H11+I12-J12) -> 2467.1037 | I12: =IF(H11<=0.005,0,H11*Compare!$B$4/12) -> 46.396302 | J12: =IF(H11<=0.005,0,MIN(H11+I12,Compare!$B$9+Compare!$B$8)) -> 110
A13: 10 | B13: =MAX(0,B12+C13-D13) -> 2713.1462 | C13: =IF(B12<=0.005,0,B12*Compare!$B$4/12) -> 50.243449 | D13: =IF(B12<=0.005,0,MIN(B12+C13,MAX(Compare!$B$7,B12*Compare!$B$5+IF(Compare!$B$6="Yes",C13,0)))) -> 77.648966 | E13: =MAX(0,E12+F13-G13) -> 2674.0003 | F13: =IF(E12<=0.005,0,E12*Compare!$B$4/12) -> 49.671037 | G13: =IF(E12<=0.005,0,MIN(E12+F13,Compare!$B$9)) -> 85 | H13: =MAX(0,H12+I13-J13) -> 2402.3339 | I13: =IF(H12<=0.005,0,H12*Compare!$B$4/12) -> 45.230234 | J13: =IF(H12<=0.005,0,MIN(H12+I13,Compare!$B$9+Compare!$B$8)) -> 110
A14: 11 | B14: =MAX(0,B13+C14-D14) -> 2686.0148 | C14: =IF(B13<=0.005,0,B13*Compare!$B$4/12) -> 49.741014 | D14: =IF(B13<=0.005,0,MIN(B13+C14,MAX(Compare!$B$7,B13*Compare!$B$5+IF(Compare!$B$6="Yes",C14,0)))) -> 76.872476 | E14: =MAX(0,E13+F14-G14) -> 2638.0237 | F14: =IF(E13<=0.005,0,E13*Compare!$B$4/12) -> 49.023339 | G14: =IF(E13<=0.005,0,MIN(E13+F14,Compare!$B$9)) -> 85 | H14: =MAX(0,H13+I14-J14) -> 2336.3767 | I14: =IF(H13<=0.005,0,H13*Compare!$B$4/12) -> 44.042788 | J14: =IF(H13<=0.005,0,MIN(H13+I14,Compare!$B$9+Compare!$B$8)) -> 110
A15: 12 | B15: =MAX(0,B14+C15-D15) -> 2659.1546 | C15: =IF(B14<=0.005,0,B14*Compare!$B$4/12) -> 49.243604 | D15: =IF(B14<=0.005,0,MIN(B14+C15,MAX(Compare!$B$7,B14*Compare!$B$5+IF(Compare!$B$6="Yes",C15,0)))) -> 76.103752 | E15: =MAX(0,E14+F15-G15) -> 2601.3874 | F15: =IF(E14<=0.005,0,E14*Compare!$B$4/12) -> 48.363767 | G15: =IF(E14<=0.005,0,MIN(E14+F15,Compare!$B$9)) -> 85 | H15: =MAX(0,H14+I15-J15) -> 2269.2103 | I15: =IF(H14<=0.005,0,H14*Compare!$B$4/12) -> 42.833573 | J15: =IF(H14<=0.005,0,MIN(H14+I15,Compare!$B$9+Compare!$B$8)) -> 110
A16: 13 | B16: =MAX(0,B15+C16-D16) -> 2632.5631 | C16: =IF(B15<=0.005,0,B15*Compare!$B$4/12) -> 48.751168 | D16: =IF(B15<=0.005,0,MIN(B15+C16,MAX(Compare!$B$7,B15*Compare!$B$5+IF(Compare!$B$6="Yes",C16,0)))) -> 75.342714 | E16: =MAX(0,E15+F16-G16) -> 2564.0795 | F16: =IF(E15<=0.005,0,E15*Compare!$B$4/12) -> 47.692103 | G16: =IF(E15<=0.005,0,MIN(E15+F16,Compare!$B$9)) -> 85 | H16: =MAX(0,H15+I16-J16) -> 2200.8125 | I16: =IF(H15<=0.005,0,H15*Compare!$B$4/12) -> 41.602188 | J16: =IF(H15<=0.005,0,MIN(H15+I16,Compare!$B$9+Compare!$B$8)) -> 110
... A603: 600 | B603: =MAX(0,B602+C603-D603) -> 0 | C603: =IF(B602<=0.005,0,B602*Compare!$B$4/12) -> 0 | D603: =IF(B602<=0.005,0,MIN(B602+C603,MAX(Compare!$B$7,B602*Compare!$B$5+IF(Compare!$B$6="Yes",C603,0)))) -> 0 | E603: =MAX(0,E602+F603-G603) -> 0 | F603: =IF(E602<=0.005,0,E602*Compare!$B$4/12) -> 0 | G603: =IF(E602<=0.005,0,MIN(E602+F603,Compare!$B$9)) -> 0 | H603: =MAX(0,H602+I603-J603) -> 0 | I603: =IF(H602<=0.005,0,H602*Compare!$B$4/12) -> 0 | J603: =IF(H602<=0.005,0,MIN(H602+I603,Compare!$B$9+Compare!$B$8)) -> 0
