Workbook

Sheet Start here
A1: Gig income and tax tracker (US)
A3: How to use it
A4: 1. On the Payouts tab, set your tax set-aside percentage (25% is a good start) and your mileage rate.
A5: 2. Log every payout with its date, the miles you drove for work and any other work costs.
A6: 3. Move the "Set aside" amount into a separate savings account the day the payout lands.
A7: 4. The Quarters tab totals each IRS payment period and shows a rough self-employment tax estimate.
A9: Rough estimate for planning only. It ignores income tax, state tax and credits. Not tax advice.
A10: IRS business mileage rate for 2026: 72.5 cents a mile Jan 1 to Jun 30, 76 cents from Jul 1.
A12: Yellow cells are for you to type in. White cells calculate automatically, so leave them alone.
A13: The example numbers only show the format. Replace them with your own.
A15: Step-by-step guide: https://guidelark.com/blog/gig-worker-taxes/
A16: Free to use and share. General information, not financial advice.

Sheet Payouts
A1: Gig payouts
A3: Tax set-aside | B3: 0.25
A4: Mileage rate per mile | B4: 0.76
A6: Date | B6: App or client | C6: Payout | D6: Set aside | E6: Work miles | F6: Mileage deduction | G6: Other work costs | H6: Note
A7: 46272 | B7: DoorDash | C7: 300 | D7: =IF(N(C7)=0,"",C7*$B$3) -> 75 | E7: 92 | F7: =IF(N(E7)=0,"",E7*$B$4) -> 69.92 | G7: 40 | H7: Phone share
A8: 46279 | B8: Uber Eats | C8: 300 | D8: =IF(N(C8)=0,"",C8*$B$3) -> 75 | E8: 92 | F8: =IF(N(E8)=0,"",E8*$B$4) -> 69.92
A9: 46286 | B9: Instacart | C9: 300 | D9: =IF(N(C9)=0,"",C9*$B$3) -> 75 | E9: 92 | F9: =IF(N(E9)=0,"",E9*$B$4) -> 69.92
A10: 46293 | B10: DoorDash | C10: 300 | D10: =IF(N(C10)=0,"",C10*$B$3) -> 75 | E10: 92 | F10: =IF(N(E10)=0,"",E10*$B$4) -> 69.92
A11: 46300 | B11: Uber Eats | C11: 300 | D11: =IF(N(C11)=0,"",C11*$B$3) -> 75 | E11: 92 | F11: =IF(N(E11)=0,"",E11*$B$4) -> 69.92 | G11: 30 | H11: Delivery bag
A12: 46307 | B12: Instacart | C12: 300 | D12: =IF(N(C12)=0,"",C12*$B$3) -> 75 | E12: 92 | F12: =IF(N(E12)=0,"",E12*$B$4) -> 69.92
A13: 46314 | B13: DoorDash | C13: 300 | D13: =IF(N(C13)=0,"",C13*$B$3) -> 75 | E13: 92 | F13: =IF(N(E13)=0,"",E13*$B$4) -> 69.92
A14: 46321 | B14: Uber Eats | C14: 300 | D14: =IF(N(C14)=0,"",C14*$B$3) -> 75 | E14: 92 | F14: =IF(N(E14)=0,"",E14*$B$4) -> 69.92
A15: 46328 | B15: Instacart | C15: 300 | D15: =IF(N(C15)=0,"",C15*$B$3) -> 75 | E15: 92 | F15: =IF(N(E15)=0,"",E15*$B$4) -> 69.92 | G15: 18 | H15: Phone mount
A16: 46335 | B16: DoorDash | C16: 300 | D16: =IF(N(C16)=0,"",C16*$B$3) -> 75 | E16: 92 | F16: =IF(N(E16)=0,"",E16*$B$4) -> 69.92
A17: 46342 | B17: Uber Eats | C17: 300 | D17: =IF(N(C17)=0,"",C17*$B$3) -> 75 | E17: 92 | F17: =IF(N(E17)=0,"",E17*$B$4) -> 69.92
A18: 46349 | B18: Instacart | C18: 300 | D18: =IF(N(C18)=0,"",C18*$B$3) -> 75 | E18: 92 | F18: =IF(N(E18)=0,"",E18*$B$4) -> 69.92
A19: 46356 | B19: DoorDash | C19: 300 | D19: =IF(N(C19)=0,"",C19*$B$3) -> 75 | E19: 96 | F19: =IF(N(E19)=0,"",E19*$B$4) -> 72.96
D20: =IF(N(C20)=0,"",C20*$B$3) | F20: =IF(N(E20)=0,"",E20*$B$4)
D21: =IF(N(C21)=0,"",C21*$B$3) | F21: =IF(N(E21)=0,"",E21*$B$4)
D22: =IF(N(C22)=0,"",C22*$B$3) | F22: =IF(N(E22)=0,"",E22*$B$4)
D23: =IF(N(C23)=0,"",C23*$B$3) | F23: =IF(N(E23)=0,"",E23*$B$4)
D24: =IF(N(C24)=0,"",C24*$B$3) | F24: =IF(N(E24)=0,"",E24*$B$4)
D25: =IF(N(C25)=0,"",C25*$B$3) | F25: =IF(N(E25)=0,"",E25*$B$4)
D26: =IF(N(C26)=0,"",C26*$B$3) | F26: =IF(N(E26)=0,"",E26*$B$4)
D27: =IF(N(C27)=0,"",C27*$B$3) | F27: =IF(N(E27)=0,"",E27*$B$4)
D28: =IF(N(C28)=0,"",C28*$B$3) | F28: =IF(N(E28)=0,"",E28*$B$4)
D29: =IF(N(C29)=0,"",C29*$B$3) | F29: =IF(N(E29)=0,"",E29*$B$4)
D30: =IF(N(C30)=0,"",C30*$B$3) | F30: =IF(N(E30)=0,"",E30*$B$4)
D31: =IF(N(C31)=0,"",C31*$B$3) | F31: =IF(N(E31)=0,"",E31*$B$4)
... D206: =IF(N(C206)=0,"",C206*$B$3) | F206: =IF(N(E206)=0,"",E206*$B$4)

Sheet Quarters
A1: IRS payment periods
A2: Totals come from the Payouts tab. Change the year to see another year.
A3: Tax year | B3: 2026
A5: Period | B5: From | C5: To | D5: Payouts | E5: Set aside | F5: Work costs | G5: Profit | H5: Rough SE tax | I5: Payment due
A6: Period 1 | B6: =DATE($B$3,1,1) -> 46023 | C6: =DATE($B$3,3,31) -> 46112 | D6: =SUMIFS(Payouts!$C$7:$C$206,Payouts!$A$7:$A$206,">="&B6,Payouts!$A$7:$A$206,"<="&C6) -> 0 | E6: =SUMIFS(Payouts!$D$7:$D$206,Payouts!$A$7:$A$206,">="&B6,Payouts!$A$7:$A$206,"<="&C6) -> 0 | F6: =SUMIFS(Payouts!$F$7:$F$206,Payouts!$A$7:$A$206,">="&B6,Payouts!$A$7:$A$206,"<="&C6)+SUMIFS(Payouts!$G$7:$G$206,Payouts!$A$7:$A$206,">="&B6,Payouts!$A$7:$A$206,"<="&C6) -> 0 | G6: =MAX(0,D6-F6) -> 0 | H6: =G6*0.9235*0.153 -> 0 | I6: April 15
A7: Period 2 | B7: =DATE($B$3,4,1) -> 46113 | C7: =DATE($B$3,5,31) -> 46173 | D7: =SUMIFS(Payouts!$C$7:$C$206,Payouts!$A$7:$A$206,">="&B7,Payouts!$A$7:$A$206,"<="&C7) -> 0 | E7: =SUMIFS(Payouts!$D$7:$D$206,Payouts!$A$7:$A$206,">="&B7,Payouts!$A$7:$A$206,"<="&C7) -> 0 | F7: =SUMIFS(Payouts!$F$7:$F$206,Payouts!$A$7:$A$206,">="&B7,Payouts!$A$7:$A$206,"<="&C7)+SUMIFS(Payouts!$G$7:$G$206,Payouts!$A$7:$A$206,">="&B7,Payouts!$A$7:$A$206,"<="&C7) -> 0 | G7: =MAX(0,D7-F7) -> 0 | H7: =G7*0.9235*0.153 -> 0 | I7: June 15
A8: Period 3 | B8: =DATE($B$3,6,1) -> 46174 | C8: =DATE($B$3,8,31) -> 46265 | D8: =SUMIFS(Payouts!$C$7:$C$206,Payouts!$A$7:$A$206,">="&B8,Payouts!$A$7:$A$206,"<="&C8) -> 0 | E8: =SUMIFS(Payouts!$D$7:$D$206,Payouts!$A$7:$A$206,">="&B8,Payouts!$A$7:$A$206,"<="&C8) -> 0 | F8: =SUMIFS(Payouts!$F$7:$F$206,Payouts!$A$7:$A$206,">="&B8,Payouts!$A$7:$A$206,"<="&C8)+SUMIFS(Payouts!$G$7:$G$206,Payouts!$A$7:$A$206,">="&B8,Payouts!$A$7:$A$206,"<="&C8) -> 0 | G8: =MAX(0,D8-F8) -> 0 | H8: =G8*0.9235*0.153 -> 0 | I8: September 15
A9: Period 4 | B9: =DATE($B$3,9,1) -> 46266 | C9: =DATE($B$3,12,31) -> 46387 | D9: =SUMIFS(Payouts!$C$7:$C$206,Payouts!$A$7:$A$206,">="&B9,Payouts!$A$7:$A$206,"<="&C9) -> 3900 | E9: =SUMIFS(Payouts!$D$7:$D$206,Payouts!$A$7:$A$206,">="&B9,Payouts!$A$7:$A$206,"<="&C9) -> 975 | F9: =SUMIFS(Payouts!$F$7:$F$206,Payouts!$A$7:$A$206,">="&B9,Payouts!$A$7:$A$206,"<="&C9)+SUMIFS(Payouts!$G$7:$G$206,Payouts!$A$7:$A$206,">="&B9,Payouts!$A$7:$A$206,"<="&C9) -> 1000 | G9: =MAX(0,D9-F9) -> 2900 | H9: =G9*0.9235*0.153 -> 409.75695 | I9: January 15 next year
A10: Year total | D10: =SUM(D6:D9) -> 3900 | E10: =SUM(E6:E9) -> 975 | F10: =SUM(F6:F9) -> 1000 | G10: =SUM(G6:G9) -> 2900 | H10: =IF(G10*0.9235<400,0,G10*0.9235*0.153) -> 409.75695
A12: Self-employment tax is 15.3% of 92.35% of profit. Income tax may be due on top if your total income is above the standard deduction.
