Workbook

Sheet Start here
A1: Debt snowball and avalanche planner
A3: How to use it
A4: 1. On the Debts tab, choose Snowball (smallest balance first) or Avalanche (highest rate first).
A5: 2. Type how much extra you can pay each month on top of your minimums.
A6: 3. List up to six debts: name, balance, yearly interest rate and minimum payment.
A7: 4. Read the results: payoff order, the month each debt is cleared, total months and total interest.
A8: 5. Switch the method to compare. The Schedule tab shows every month in detail.
A10: This is an estimate using simple monthly interest. Your lender's numbers will differ slightly.
A11: Needs Google Sheets, or Excel 2019 / Microsoft 365 (it uses the MINIFS function).
A13: Yellow cells are for you to type in. White cells calculate automatically, so leave them alone.
A14: The example numbers only show the format. Replace them with your own.
A16: Step-by-step guide: https://guidelark.com/blog/debt-snowball-spreadsheet/
A17: Free to use and share. General information, not financial advice.

Sheet Debts
A1: Debt payoff planner
A3: Method | B3: Snowball | C3: Snowball = smallest balance first. Avalanche = highest interest rate first.
A4: Extra payment each month | B4: 100 | C4: On top of all your minimum payments.
A6: Debt | B6: Balance | C6: Interest rate (APR) | D6: Minimum payment | E6: Payoff order | F6: Paid off in month
A7: Store card | B7: 900 | C7: 0.15 | D7: 30 | E7: =IF(N(B7)>0,IF($B$3="Avalanche",COUNTIFS($B$7:$B$12,">0",$C$7:$C$12,">"&N(C7))+COUNTIFS($C$7:C7,N(C7),$B$7:B7,">0"),COUNTIFS($B$7:$B$12,">0",$B$7:$B$12,"<"&B7)+COUNTIFS($B$7:B7,B7)),"") -> 1 | F7: =IF(N(B7)>0,IF(COUNTIF(Schedule!AC$5:AC$124,">0.005")>=120,"Over 10 years",COUNTIF(Schedule!AC$5:AC$124,">0.005")+1),"") -> 8
A8: Car loan | B8: 2000 | C8: 0.08 | D8: 60 | E8: =IF(N(B8)>0,IF($B$3="Avalanche",COUNTIFS($B$7:$B$12,">0",$C$7:$C$12,">"&N(C8))+COUNTIFS($C$7:C8,N(C8),$B$7:B8,">0"),COUNTIFS($B$7:$B$12,">0",$B$7:$B$12,"<"&B8)+COUNTIFS($B$7:B8,B8)),"") -> 2 | F8: =IF(N(B8)>0,IF(COUNTIF(Schedule!AD$5:AD$124,">0.005")>=120,"Over 10 years",COUNTIF(Schedule!AD$5:AD$124,">0.005")+1),"") -> 17
A9: Credit card | B9: 3200 | C9: 0.26 | D9: 96 | E9: =IF(N(B9)>0,IF($B$3="Avalanche",COUNTIFS($B$7:$B$12,">0",$C$7:$C$12,">"&N(C9))+COUNTIFS($C$7:C9,N(C9),$B$7:B9,">0"),COUNTIFS($B$7:$B$12,">0",$B$7:$B$12,"<"&B9)+COUNTIFS($B$7:B9,B9)),"") -> 3 | F9: =IF(N(B9)>0,IF(COUNTIF(Schedule!AE$5:AE$124,">0.005")>=120,"Over 10 years",COUNTIF(Schedule!AE$5:AE$124,">0.005")+1),"") -> 28
E10: =IF(N(B10)>0,IF($B$3="Avalanche",COUNTIFS($B$7:$B$12,">0",$C$7:$C$12,">"&N(C10))+COUNTIFS($C$7:C10,N(C10),$B$7:B10,">0"),COUNTIFS($B$7:$B$12,">0",$B$7:$B$12,"<"&B10)+COUNTIFS($B$7:B10,B10)),"") | F10: =IF(N(B10)>0,IF(COUNTIF(Schedule!AF$5:AF$124,">0.005")>=120,"Over 10 years",COUNTIF(Schedule!AF$5:AF$124,">0.005")+1),"")
E11: =IF(N(B11)>0,IF($B$3="Avalanche",COUNTIFS($B$7:$B$12,">0",$C$7:$C$12,">"&N(C11))+COUNTIFS($C$7:C11,N(C11),$B$7:B11,">0"),COUNTIFS($B$7:$B$12,">0",$B$7:$B$12,"<"&B11)+COUNTIFS($B$7:B11,B11)),"") | F11: =IF(N(B11)>0,IF(COUNTIF(Schedule!AG$5:AG$124,">0.005")>=120,"Over 10 years",COUNTIF(Schedule!AG$5:AG$124,">0.005")+1),"")
E12: =IF(N(B12)>0,IF($B$3="Avalanche",COUNTIFS($B$7:$B$12,">0",$C$7:$C$12,">"&N(C12))+COUNTIFS($C$7:C12,N(C12),$B$7:B12,">0"),COUNTIFS($B$7:$B$12,">0",$B$7:$B$12,"<"&B12)+COUNTIFS($B$7:B12,B12)),"") | F12: =IF(N(B12)>0,IF(COUNTIF(Schedule!AH$5:AH$124,">0.005")>=120,"Over 10 years",COUNTIF(Schedule!AH$5:AH$124,">0.005")+1),"")
A14: Total monthly payment | B14: =SUM(D7:D12)+B4 -> 286 | C14: Stays the same every month: cleared minimums roll into the next debt.
A15: Months until debt-free | B15: =IF(SUM(B7:B12)=0,"-",IF(COUNTIF(Schedule!AJ5:AJ124,">0.005")>=120,"Over 10 years",COUNTIF(Schedule!AJ5:AJ124,">0.005")+1)) -> 28
A16: Total interest paid | B16: =SUM(Schedule!AI5:AI124) -> 1632.5524
A17: Total paid | B17: =SUM(B7:B12)+B16 -> 7732.5524

Sheet Schedule
A1: Month-by-month schedule (calculated, no need to edit)
A2: Rows 1-3 hold each debt's minimum, rate and payoff order.
B3: =Debts!E7 -> 1 | C3: =Debts!E8 -> 2 | D3: =Debts!E9 -> 3 | E3: =Debts!E10 | F3: =Debts!E11 | G3: =Debts!E12
A4: Month | B4: Start 1 | C4: Start 2 | D4: Start 3 | E4: Start 4 | F4: Start 5 | G4: Start 6 | H4: Interest 1 | I4: Interest 2 | J4: Interest 3 | K4: Interest 4 | L4: Interest 5 | M4: Interest 6 | N4: Minimum 1 | O4: Minimum 2 | P4: Minimum 3 | Q4: Minimum 4 | R4: Minimum 5 | S4: Minimum 6 | T4: Total payment | U4: Extra pool | V4: Target | W4: Payment 1 | X4: Payment 2 | Y4: Payment 3 | Z4: Payment 4 | AA4: Payment 5 | AB4: Payment 6 | AC4: End 1 | AD4: End 2 | AE4: End 3 | AF4: End 4 | AG4: End 5 | AH4: End 6 | AI4: Interest total | AJ4: Balance left
A5: 1 | B5: =N(Debts!B7) -> 900 | C5: =N(Debts!B8) -> 2000 | D5: =N(Debts!B9) -> 3200 | E5: =N(Debts!B10) -> 0 | F5: =N(Debts!B11) -> 0 | G5: =N(Debts!B12) -> 0 | H5: =B5*N(Debts!C7)/12 -> 11.25 | I5: =C5*N(Debts!C8)/12 -> 13.333333 | J5: =D5*N(Debts!C9)/12 -> 69.333333 | K5: =E5*N(Debts!C10)/12 -> 0 | L5: =F5*N(Debts!C11)/12 -> 0 | M5: =G5*N(Debts!C12)/12 -> 0 | N5: =MIN(B5+H5,N(Debts!D7)) -> 30 | O5: =MIN(C5+I5,N(Debts!D8)) -> 60 | P5: =MIN(D5+J5,N(Debts!D9)) -> 96 | Q5: =MIN(E5+K5,N(Debts!D10)) -> 0 | R5: =MIN(F5+L5,N(Debts!D11)) -> 0 | S5: =MIN(G5+M5,N(Debts!D12)) -> 0 | T5: =Debts!$B$14 -> 286 | U5: =MAX(0,T5-SUM(N5:S5)) -> 100 | V5: =_xlfn.MINIFS($B$3:$G$3,B5:G5,">0.005") -> 1 | W5: =IF(B5<=0.005,0,MIN(B5+H5,N5+IF(B$3=$V5,$U5,0))) -> 130 | X5: =IF(C5<=0.005,0,MIN(C5+I5,O5+IF(C$3=$V5,$U5,0))) -> 60 | Y5: =IF(D5<=0.005,0,MIN(D5+J5,P5+IF(D$3=$V5,$U5,0))) -> 96 | Z5: =IF(E5<=0.005,0,MIN(E5+K5,Q5+IF(E$3=$V5,$U5,0))) -> 0 | AA5: =IF(F5<=0.005,0,MIN(F5+L5,R5+IF(F$3=$V5,$U5,0))) -> 0 | AB5: =IF(G5<=0.005,0,MIN(G5+M5,S5+IF(G$3=$V5,$U5,0))) -> 0 | AC5: =MAX(0,B5+H5-W5) -> 781.25 | AD5: =MAX(0,C5+I5-X5) -> 1953.3333 | AE5: =MAX(0,D5+J5-Y5) -> 3173.3333 | AF5: =MAX(0,E5+K5-Z5) -> 0 | AG5: =MAX(0,F5+L5-AA5) -> 0 | AH5: =MAX(0,G5+M5-AB5) -> 0 | AI5: =SUM(H5:M5) -> 93.916667 | AJ5: =SUM(AC5:AH5) -> 5907.9167
A6: 2 | B6: =AC5 -> 781.25 | C6: =AD5 -> 1953.3333 | D6: =AE5 -> 3173.3333 | E6: =AF5 -> 0 | F6: =AG5 -> 0 | G6: =AH5 -> 0 | H6: =B6*N(Debts!C7)/12 -> 9.765625 | I6: =C6*N(Debts!C8)/12 -> 13.022222 | J6: =D6*N(Debts!C9)/12 -> 68.755556 | K6: =E6*N(Debts!C10)/12 -> 0 | L6: =F6*N(Debts!C11)/12 -> 0 | M6: =G6*N(Debts!C12)/12 -> 0 | N6: =MIN(B6+H6,N(Debts!D7)) -> 30 | O6: =MIN(C6+I6,N(Debts!D8)) -> 60 | P6: =MIN(D6+J6,N(Debts!D9)) -> 96 | Q6: =MIN(E6+K6,N(Debts!D10)) -> 0 | R6: =MIN(F6+L6,N(Debts!D11)) -> 0 | S6: =MIN(G6+M6,N(Debts!D12)) -> 0 | T6: =Debts!$B$14 -> 286 | U6: =MAX(0,T6-SUM(N6:S6)) -> 100 | V6: =_xlfn.MINIFS($B$3:$G$3,B6:G6,">0.005") -> 1 | W6: =IF(B6<=0.005,0,MIN(B6+H6,N6+IF(B$3=$V6,$U6,0))) -> 130 | X6: =IF(C6<=0.005,0,MIN(C6+I6,O6+IF(C$3=$V6,$U6,0))) -> 60 | Y6: =IF(D6<=0.005,0,MIN(D6+J6,P6+IF(D$3=$V6,$U6,0))) -> 96 | Z6: =IF(E6<=0.005,0,MIN(E6+K6,Q6+IF(E$3=$V6,$U6,0))) -> 0 | AA6: =IF(F6<=0.005,0,MIN(F6+L6,R6+IF(F$3=$V6,$U6,0))) -> 0 | AB6: =IF(G6<=0.005,0,MIN(G6+M6,S6+IF(G$3=$V6,$U6,0))) -> 0 | AC6: =MAX(0,B6+H6-W6) -> 661.01562 | AD6: =MAX(0,C6+I6-X6) -> 1906.3556 | AE6: =MAX(0,D6+J6-Y6) -> 3146.0889 | AF6: =MAX(0,E6+K6-Z6) -> 0 | AG6: =MAX(0,F6+L6-AA6) -> 0 | AH6: =MAX(0,G6+M6-AB6) -> 0 | AI6: =SUM(H6:M6) -> 91.543403 | AJ6: =SUM(AC6:AH6) -> 5713.4601
A7: 3 | B7: =AC6 -> 661.01562 | C7: =AD6 -> 1906.3556 | D7: =AE6 -> 3146.0889 | E7: =AF6 -> 0 | F7: =AG6 -> 0 | G7: =AH6 -> 0 | H7: =B7*N(Debts!C7)/12 -> 8.2626953 | I7: =C7*N(Debts!C8)/12 -> 12.709037 | J7: =D7*N(Debts!C9)/12 -> 68.165259 | K7: =E7*N(Debts!C10)/12 -> 0 | L7: =F7*N(Debts!C11)/12 -> 0 | M7: =G7*N(Debts!C12)/12 -> 0 | N7: =MIN(B7+H7,N(Debts!D7)) -> 30 | O7: =MIN(C7+I7,N(Debts!D8)) -> 60 | P7: =MIN(D7+J7,N(Debts!D9)) -> 96 | Q7: =MIN(E7+K7,N(Debts!D10)) -> 0 | R7: =MIN(F7+L7,N(Debts!D11)) -> 0 | S7: =MIN(G7+M7,N(Debts!D12)) -> 0 | T7: =Debts!$B$14 -> 286 | U7: =MAX(0,T7-SUM(N7:S7)) -> 100 | V7: =_xlfn.MINIFS($B$3:$G$3,B7:G7,">0.005") -> 1 | W7: =IF(B7<=0.005,0,MIN(B7+H7,N7+IF(B$3=$V7,$U7,0))) -> 130 | X7: =IF(C7<=0.005,0,MIN(C7+I7,O7+IF(C$3=$V7,$U7,0))) -> 60 | Y7: =IF(D7<=0.005,0,MIN(D7+J7,P7+IF(D$3=$V7,$U7,0))) -> 96 | Z7: =IF(E7<=0.005,0,MIN(E7+K7,Q7+IF(E$3=$V7,$U7,0))) -> 0 | AA7: =IF(F7<=0.005,0,MIN(F7+L7,R7+IF(F$3=$V7,$U7,0))) -> 0 | AB7: =IF(G7<=0.005,0,MIN(G7+M7,S7+IF(G$3=$V7,$U7,0))) -> 0 | AC7: =MAX(0,B7+H7-W7) -> 539.27832 | AD7: =MAX(0,C7+I7-X7) -> 1859.0646 | AE7: =MAX(0,D7+J7-Y7) -> 3118.2541 | AF7: =MAX(0,E7+K7-Z7) -> 0 | AG7: =MAX(0,F7+L7-AA7) -> 0 | AH7: =MAX(0,G7+M7-AB7) -> 0 | AI7: =SUM(H7:M7) -> 89.136992 | AJ7: =SUM(AC7:AH7) -> 5516.5971
A8: 4 | B8: =AC7 -> 539.27832 | C8: =AD7 -> 1859.0646 | D8: =AE7 -> 3118.2541 | E8: =AF7 -> 0 | F8: =AG7 -> 0 | G8: =AH7 -> 0 | H8: =B8*N(Debts!C7)/12 -> 6.740979 | I8: =C8*N(Debts!C8)/12 -> 12.393764 | J8: =D8*N(Debts!C9)/12 -> 67.562173 | K8: =E8*N(Debts!C10)/12 -> 0 | L8: =F8*N(Debts!C11)/12 -> 0 | M8: =G8*N(Debts!C12)/12 -> 0 | N8: =MIN(B8+H8,N(Debts!D7)) -> 30 | O8: =MIN(C8+I8,N(Debts!D8)) -> 60 | P8: =MIN(D8+J8,N(Debts!D9)) -> 96 | Q8: =MIN(E8+K8,N(Debts!D10)) -> 0 | R8: =MIN(F8+L8,N(Debts!D11)) -> 0 | S8: =MIN(G8+M8,N(Debts!D12)) -> 0 | T8: =Debts!$B$14 -> 286 | U8: =MAX(0,T8-SUM(N8:S8)) -> 100 | V8: =_xlfn.MINIFS($B$3:$G$3,B8:G8,">0.005") -> 1 | W8: =IF(B8<=0.005,0,MIN(B8+H8,N8+IF(B$3=$V8,$U8,0))) -> 130 | X8: =IF(C8<=0.005,0,MIN(C8+I8,O8+IF(C$3=$V8,$U8,0))) -> 60 | Y8: =IF(D8<=0.005,0,MIN(D8+J8,P8+IF(D$3=$V8,$U8,0))) -> 96 | Z8: =IF(E8<=0.005,0,MIN(E8+K8,Q8+IF(E$3=$V8,$U8,0))) -> 0 | AA8: =IF(F8<=0.005,0,MIN(F8+L8,R8+IF(F$3=$V8,$U8,0))) -> 0 | AB8: =IF(G8<=0.005,0,MIN(G8+M8,S8+IF(G$3=$V8,$U8,0))) -> 0 | AC8: =MAX(0,B8+H8-W8) -> 416.0193 | AD8: =MAX(0,C8+I8-X8) -> 1811.4584 | AE8: =MAX(0,D8+J8-Y8) -> 3089.8163 | AF8: =MAX(0,E8+K8-Z8) -> 0 | AG8: =MAX(0,F8+L8-AA8) -> 0 | AH8: =MAX(0,G8+M8-AB8) -> 0 | AI8: =SUM(H8:M8) -> 86.696916 | AJ8: =SUM(AC8:AH8) -> 5317.294
A9: 5 | B9: =AC8 -> 416.0193 | C9: =AD8 -> 1811.4584 | D9: =AE8 -> 3089.8163 | E9: =AF8 -> 0 | F9: =AG8 -> 0 | G9: =AH8 -> 0 | H9: =B9*N(Debts!C7)/12 -> 5.2002412 | I9: =C9*N(Debts!C8)/12 -> 12.076389 | J9: =D9*N(Debts!C9)/12 -> 66.94602 | K9: =E9*N(Debts!C10)/12 -> 0 | L9: =F9*N(Debts!C11)/12 -> 0 | M9: =G9*N(Debts!C12)/12 -> 0 | N9: =MIN(B9+H9,N(Debts!D7)) -> 30 | O9: =MIN(C9+I9,N(Debts!D8)) -> 60 | P9: =MIN(D9+J9,N(Debts!D9)) -> 96 | Q9: =MIN(E9+K9,N(Debts!D10)) -> 0 | R9: =MIN(F9+L9,N(Debts!D11)) -> 0 | S9: =MIN(G9+M9,N(Debts!D12)) -> 0 | T9: =Debts!$B$14 -> 286 | U9: =MAX(0,T9-SUM(N9:S9)) -> 100 | V9: =_xlfn.MINIFS($B$3:$G$3,B9:G9,">0.005") -> 1 | W9: =IF(B9<=0.005,0,MIN(B9+H9,N9+IF(B$3=$V9,$U9,0))) -> 130 | X9: =IF(C9<=0.005,0,MIN(C9+I9,O9+IF(C$3=$V9,$U9,0))) -> 60 | Y9: =IF(D9<=0.005,0,MIN(D9+J9,P9+IF(D$3=$V9,$U9,0))) -> 96 | Z9: =IF(E9<=0.005,0,MIN(E9+K9,Q9+IF(E$3=$V9,$U9,0))) -> 0 | AA9: =IF(F9<=0.005,0,MIN(F9+L9,R9+IF(F$3=$V9,$U9,0))) -> 0 | AB9: =IF(G9<=0.005,0,MIN(G9+M9,S9+IF(G$3=$V9,$U9,0))) -> 0 | AC9: =MAX(0,B9+H9-W9) -> 291.21954 | AD9: =MAX(0,C9+I9-X9) -> 1763.5347 | AE9: =MAX(0,D9+J9-Y9) -> 3060.7623 | AF9: =MAX(0,E9+K9-Z9) -> 0 | AG9: =MAX(0,F9+L9-AA9) -> 0 | AH9: =MAX(0,G9+M9-AB9) -> 0 | AI9: =SUM(H9:M9) -> 84.222651 | AJ9: =SUM(AC9:AH9) -> 5115.5166
A10: 6 | B10: =AC9 -> 291.21954 | C10: =AD9 -> 1763.5347 | D10: =AE9 -> 3060.7623 | E10: =AF9 -> 0 | F10: =AG9 -> 0 | G10: =AH9 -> 0 | H10: =B10*N(Debts!C7)/12 -> 3.6402443 | I10: =C10*N(Debts!C8)/12 -> 11.756898 | J10: =D10*N(Debts!C9)/12 -> 66.316517 | K10: =E10*N(Debts!C10)/12 -> 0 | L10: =F10*N(Debts!C11)/12 -> 0 | M10: =G10*N(Debts!C12)/12 -> 0 | N10: =MIN(B10+H10,N(Debts!D7)) -> 30 | O10: =MIN(C10+I10,N(Debts!D8)) -> 60 | P10: =MIN(D10+J10,N(Debts!D9)) -> 96 | Q10: =MIN(E10+K10,N(Debts!D10)) -> 0 | R10: =MIN(F10+L10,N(Debts!D11)) -> 0 | S10: =MIN(G10+M10,N(Debts!D12)) -> 0 | T10: =Debts!$B$14 -> 286 | U10: =MAX(0,T10-SUM(N10:S10)) -> 100 | V10: =_xlfn.MINIFS($B$3:$G$3,B10:G10,">0.005") -> 1 | W10: =IF(B10<=0.005,0,MIN(B10+H10,N10+IF(B$3=$V10,$U10,0))) -> 130 | X10: =IF(C10<=0.005,0,MIN(C10+I10,O10+IF(C$3=$V10,$U10,0))) -> 60 | Y10: =IF(D10<=0.005,0,MIN(D10+J10,P10+IF(D$3=$V10,$U10,0))) -> 96 | Z10: =IF(E10<=0.005,0,MIN(E10+K10,Q10+IF(E$3=$V10,$U10,0))) -> 0 | AA10: =IF(F10<=0.005,0,MIN(F10+L10,R10+IF(F$3=$V10,$U10,0))) -> 0 | AB10: =IF(G10<=0.005,0,MIN(G10+M10,S10+IF(G$3=$V10,$U10,0))) -> 0 | AC10: =MAX(0,B10+H10-W10) -> 164.85978 | AD10: =MAX(0,C10+I10-X10) -> 1715.2916 | AE10: =MAX(0,D10+J10-Y10) -> 3031.0789 | AF10: =MAX(0,E10+K10-Z10) -> 0 | AG10: =MAX(0,F10+L10-AA10) -> 0 | AH10: =MAX(0,G10+M10-AB10) -> 0 | AI10: =SUM(H10:M10) -> 81.71366 | AJ10: =SUM(AC10:AH10) -> 4911.2303
A11: 7 | B11: =AC10 -> 164.85978 | C11: =AD10 -> 1715.2916 | D11: =AE10 -> 3031.0789 | E11: =AF10 -> 0 | F11: =AG10 -> 0 | G11: =AH10 -> 0 | H11: =B11*N(Debts!C7)/12 -> 2.0607473 | I11: =C11*N(Debts!C8)/12 -> 11.435278 | J11: =D11*N(Debts!C9)/12 -> 65.673375 | K11: =E11*N(Debts!C10)/12 -> 0 | L11: =F11*N(Debts!C11)/12 -> 0 | M11: =G11*N(Debts!C12)/12 -> 0 | N11: =MIN(B11+H11,N(Debts!D7)) -> 30 | O11: =MIN(C11+I11,N(Debts!D8)) -> 60 | P11: =MIN(D11+J11,N(Debts!D9)) -> 96 | Q11: =MIN(E11+K11,N(Debts!D10)) -> 0 | R11: =MIN(F11+L11,N(Debts!D11)) -> 0 | S11: =MIN(G11+M11,N(Debts!D12)) -> 0 | T11: =Debts!$B$14 -> 286 | U11: =MAX(0,T11-SUM(N11:S11)) -> 100 | V11: =_xlfn.MINIFS($B$3:$G$3,B11:G11,">0.005") -> 1 | W11: =IF(B11<=0.005,0,MIN(B11+H11,N11+IF(B$3=$V11,$U11,0))) -> 130 | X11: =IF(C11<=0.005,0,MIN(C11+I11,O11+IF(C$3=$V11,$U11,0))) -> 60 | Y11: =IF(D11<=0.005,0,MIN(D11+J11,P11+IF(D$3=$V11,$U11,0))) -> 96 | Z11: =IF(E11<=0.005,0,MIN(E11+K11,Q11+IF(E$3=$V11,$U11,0))) -> 0 | AA11: =IF(F11<=0.005,0,MIN(F11+L11,R11+IF(F$3=$V11,$U11,0))) -> 0 | AB11: =IF(G11<=0.005,0,MIN(G11+M11,S11+IF(G$3=$V11,$U11,0))) -> 0 | AC11: =MAX(0,B11+H11-W11) -> 36.920532 | AD11: =MAX(0,C11+I11-X11) -> 1666.7269 | AE11: =MAX(0,D11+J11-Y11) -> 3000.7522 | AF11: =MAX(0,E11+K11-Z11) -> 0 | AG11: =MAX(0,F11+L11-AA11) -> 0 | AH11: =MAX(0,G11+M11-AB11) -> 0 | AI11: =SUM(H11:M11) -> 79.1694 | AJ11: =SUM(AC11:AH11) -> 4704.3997
A12: 8 | B12: =AC11 -> 36.920532 | C12: =AD11 -> 1666.7269 | D12: =AE11 -> 3000.7522 | E12: =AF11 -> 0 | F12: =AG11 -> 0 | G12: =AH11 -> 0 | H12: =B12*N(Debts!C7)/12 -> 0.46150665 | I12: =C12*N(Debts!C8)/12 -> 11.111513 | J12: =D12*N(Debts!C9)/12 -> 65.016298 | K12: =E12*N(Debts!C10)/12 -> 0 | L12: =F12*N(Debts!C11)/12 -> 0 | M12: =G12*N(Debts!C12)/12 -> 0 | N12: =MIN(B12+H12,N(Debts!D7)) -> 30 | O12: =MIN(C12+I12,N(Debts!D8)) -> 60 | P12: =MIN(D12+J12,N(Debts!D9)) -> 96 | Q12: =MIN(E12+K12,N(Debts!D10)) -> 0 | R12: =MIN(F12+L12,N(Debts!D11)) -> 0 | S12: =MIN(G12+M12,N(Debts!D12)) -> 0 | T12: =Debts!$B$14 -> 286 | U12: =MAX(0,T12-SUM(N12:S12)) -> 100 | V12: =_xlfn.MINIFS($B$3:$G$3,B12:G12,">0.005") -> 1 | W12: =IF(B12<=0.005,0,MIN(B12+H12,N12+IF(B$3=$V12,$U12,0))) -> 37.382039 | X12: =IF(C12<=0.005,0,MIN(C12+I12,O12+IF(C$3=$V12,$U12,0))) -> 60 | Y12: =IF(D12<=0.005,0,MIN(D12+J12,P12+IF(D$3=$V12,$U12,0))) -> 96 | Z12: =IF(E12<=0.005,0,MIN(E12+K12,Q12+IF(E$3=$V12,$U12,0))) -> 0 | AA12: =IF(F12<=0.005,0,MIN(F12+L12,R12+IF(F$3=$V12,$U12,0))) -> 0 | AB12: =IF(G12<=0.005,0,MIN(G12+M12,S12+IF(G$3=$V12,$U12,0))) -> 0 | AC12: =MAX(0,B12+H12-W12) -> 0 | AD12: =MAX(0,C12+I12-X12) -> 1617.8384 | AE12: =MAX(0,D12+J12-Y12) -> 2969.7685 | AF12: =MAX(0,E12+K12-Z12) -> 0 | AG12: =MAX(0,F12+L12-AA12) -> 0 | AH12: =MAX(0,G12+M12-AB12) -> 0 | AI12: =SUM(H12:M12) -> 76.589318 | AJ12: =SUM(AC12:AH12) -> 4587.607
A13: 9 | B13: =AC12 -> 0 | C13: =AD12 -> 1617.8384 | D13: =AE12 -> 2969.7685 | E13: =AF12 -> 0 | F13: =AG12 -> 0 | G13: =AH12 -> 0 | H13: =B13*N(Debts!C7)/12 -> 0 | I13: =C13*N(Debts!C8)/12 -> 10.78559 | J13: =D13*N(Debts!C9)/12 -> 64.344985 | K13: =E13*N(Debts!C10)/12 -> 0 | L13: =F13*N(Debts!C11)/12 -> 0 | M13: =G13*N(Debts!C12)/12 -> 0 | N13: =MIN(B13+H13,N(Debts!D7)) -> 0 | O13: =MIN(C13+I13,N(Debts!D8)) -> 60 | P13: =MIN(D13+J13,N(Debts!D9)) -> 96 | Q13: =MIN(E13+K13,N(Debts!D10)) -> 0 | R13: =MIN(F13+L13,N(Debts!D11)) -> 0 | S13: =MIN(G13+M13,N(Debts!D12)) -> 0 | T13: =Debts!$B$14 -> 286 | U13: =MAX(0,T13-SUM(N13:S13)) -> 130 | V13: =_xlfn.MINIFS($B$3:$G$3,B13:G13,">0.005") -> 2 | W13: =IF(B13<=0.005,0,MIN(B13+H13,N13+IF(B$3=$V13,$U13,0))) -> 0 | X13: =IF(C13<=0.005,0,MIN(C13+I13,O13+IF(C$3=$V13,$U13,0))) -> 190 | Y13: =IF(D13<=0.005,0,MIN(D13+J13,P13+IF(D$3=$V13,$U13,0))) -> 96 | Z13: =IF(E13<=0.005,0,MIN(E13+K13,Q13+IF(E$3=$V13,$U13,0))) -> 0 | AA13: =IF(F13<=0.005,0,MIN(F13+L13,R13+IF(F$3=$V13,$U13,0))) -> 0 | AB13: =IF(G13<=0.005,0,MIN(G13+M13,S13+IF(G$3=$V13,$U13,0))) -> 0 | AC13: =MAX(0,B13+H13-W13) -> 0 | AD13: =MAX(0,C13+I13-X13) -> 1438.624 | AE13: =MAX(0,D13+J13-Y13) -> 2938.1135 | AF13: =MAX(0,E13+K13-Z13) -> 0 | AG13: =MAX(0,F13+L13-AA13) -> 0 | AH13: =MAX(0,G13+M13-AB13) -> 0 | AI13: =SUM(H13:M13) -> 75.130574 | AJ13: =SUM(AC13:AH13) -> 4376.7375
A14: 10 | B14: =AC13 -> 0 | C14: =AD13 -> 1438.624 | D14: =AE13 -> 2938.1135 | E14: =AF13 -> 0 | F14: =AG13 -> 0 | G14: =AH13 -> 0 | H14: =B14*N(Debts!C7)/12 -> 0 | I14: =C14*N(Debts!C8)/12 -> 9.5908268 | J14: =D14*N(Debts!C9)/12 -> 63.659126 | K14: =E14*N(Debts!C10)/12 -> 0 | L14: =F14*N(Debts!C11)/12 -> 0 | M14: =G14*N(Debts!C12)/12 -> 0 | N14: =MIN(B14+H14,N(Debts!D7)) -> 0 | O14: =MIN(C14+I14,N(Debts!D8)) -> 60 | P14: =MIN(D14+J14,N(Debts!D9)) -> 96 | Q14: =MIN(E14+K14,N(Debts!D10)) -> 0 | R14: =MIN(F14+L14,N(Debts!D11)) -> 0 | S14: =MIN(G14+M14,N(Debts!D12)) -> 0 | T14: =Debts!$B$14 -> 286 | U14: =MAX(0,T14-SUM(N14:S14)) -> 130 | V14: =_xlfn.MINIFS($B$3:$G$3,B14:G14,">0.005") -> 2 | W14: =IF(B14<=0.005,0,MIN(B14+H14,N14+IF(B$3=$V14,$U14,0))) -> 0 | X14: =IF(C14<=0.005,0,MIN(C14+I14,O14+IF(C$3=$V14,$U14,0))) -> 190 | Y14: =IF(D14<=0.005,0,MIN(D14+J14,P14+IF(D$3=$V14,$U14,0))) -> 96 | Z14: =IF(E14<=0.005,0,MIN(E14+K14,Q14+IF(E$3=$V14,$U14,0))) -> 0 | AA14: =IF(F14<=0.005,0,MIN(F14+L14,R14+IF(F$3=$V14,$U14,0))) -> 0 | AB14: =IF(G14<=0.005,0,MIN(G14+M14,S14+IF(G$3=$V14,$U14,0))) -> 0 | AC14: =MAX(0,B14+H14-W14) -> 0 | AD14: =MAX(0,C14+I14-X14) -> 1258.2149 | AE14: =MAX(0,D14+J14-Y14) -> 2905.7726 | AF14: =MAX(0,E14+K14-Z14) -> 0 | AG14: =MAX(0,F14+L14-AA14) -> 0 | AH14: =MAX(0,G14+M14-AB14) -> 0 | AI14: =SUM(H14:M14) -> 73.249953 | AJ14: =SUM(AC14:AH14) -> 4163.9875
A15: 11 | B15: =AC14 -> 0 | C15: =AD14 -> 1258.2149 | D15: =AE14 -> 2905.7726 | E15: =AF14 -> 0 | F15: =AG14 -> 0 | G15: =AH14 -> 0 | H15: =B15*N(Debts!C7)/12 -> 0 | I15: =C15*N(Debts!C8)/12 -> 8.388099 | J15: =D15*N(Debts!C9)/12 -> 62.958407 | K15: =E15*N(Debts!C10)/12 -> 0 | L15: =F15*N(Debts!C11)/12 -> 0 | M15: =G15*N(Debts!C12)/12 -> 0 | N15: =MIN(B15+H15,N(Debts!D7)) -> 0 | O15: =MIN(C15+I15,N(Debts!D8)) -> 60 | P15: =MIN(D15+J15,N(Debts!D9)) -> 96 | Q15: =MIN(E15+K15,N(Debts!D10)) -> 0 | R15: =MIN(F15+L15,N(Debts!D11)) -> 0 | S15: =MIN(G15+M15,N(Debts!D12)) -> 0 | T15: =Debts!$B$14 -> 286 | U15: =MAX(0,T15-SUM(N15:S15)) -> 130 | V15: =_xlfn.MINIFS($B$3:$G$3,B15:G15,">0.005") -> 2 | W15: =IF(B15<=0.005,0,MIN(B15+H15,N15+IF(B$3=$V15,$U15,0))) -> 0 | X15: =IF(C15<=0.005,0,MIN(C15+I15,O15+IF(C$3=$V15,$U15,0))) -> 190 | Y15: =IF(D15<=0.005,0,MIN(D15+J15,P15+IF(D$3=$V15,$U15,0))) -> 96 | Z15: =IF(E15<=0.005,0,MIN(E15+K15,Q15+IF(E$3=$V15,$U15,0))) -> 0 | AA15: =IF(F15<=0.005,0,MIN(F15+L15,R15+IF(F$3=$V15,$U15,0))) -> 0 | AB15: =IF(G15<=0.005,0,MIN(G15+M15,S15+IF(G$3=$V15,$U15,0))) -> 0 | AC15: =MAX(0,B15+H15-W15) -> 0 | AD15: =MAX(0,C15+I15-X15) -> 1076.6029 | AE15: =MAX(0,D15+J15-Y15) -> 2872.7311 | AF15: =MAX(0,E15+K15-Z15) -> 0 | AG15: =MAX(0,F15+L15-AA15) -> 0 | AH15: =MAX(0,G15+M15-AB15) -> 0 | AI15: =SUM(H15:M15) -> 71.346506 | AJ15: =SUM(AC15:AH15) -> 3949.334
A16: 12 | B16: =AC15 -> 0 | C16: =AD15 -> 1076.6029 | D16: =AE15 -> 2872.7311 | E16: =AF15 -> 0 | F16: =AG15 -> 0 | G16: =AH15 -> 0 | H16: =B16*N(Debts!C7)/12 -> 0 | I16: =C16*N(Debts!C8)/12 -> 7.177353 | J16: =D16*N(Debts!C9)/12 -> 62.242506 | K16: =E16*N(Debts!C10)/12 -> 0 | L16: =F16*N(Debts!C11)/12 -> 0 | M16: =G16*N(Debts!C12)/12 -> 0 | N16: =MIN(B16+H16,N(Debts!D7)) -> 0 | O16: =MIN(C16+I16,N(Debts!D8)) -> 60 | P16: =MIN(D16+J16,N(Debts!D9)) -> 96 | Q16: =MIN(E16+K16,N(Debts!D10)) -> 0 | R16: =MIN(F16+L16,N(Debts!D11)) -> 0 | S16: =MIN(G16+M16,N(Debts!D12)) -> 0 | T16: =Debts!$B$14 -> 286 | U16: =MAX(0,T16-SUM(N16:S16)) -> 130 | V16: =_xlfn.MINIFS($B$3:$G$3,B16:G16,">0.005") -> 2 | W16: =IF(B16<=0.005,0,MIN(B16+H16,N16+IF(B$3=$V16,$U16,0))) -> 0 | X16: =IF(C16<=0.005,0,MIN(C16+I16,O16+IF(C$3=$V16,$U16,0))) -> 190 | Y16: =IF(D16<=0.005,0,MIN(D16+J16,P16+IF(D$3=$V16,$U16,0))) -> 96 | Z16: =IF(E16<=0.005,0,MIN(E16+K16,Q16+IF(E$3=$V16,$U16,0))) -> 0 | AA16: =IF(F16<=0.005,0,MIN(F16+L16,R16+IF(F$3=$V16,$U16,0))) -> 0 | AB16: =IF(G16<=0.005,0,MIN(G16+M16,S16+IF(G$3=$V16,$U16,0))) -> 0 | AC16: =MAX(0,B16+H16-W16) -> 0 | AD16: =MAX(0,C16+I16-X16) -> 893.7803 | AE16: =MAX(0,D16+J16-Y16) -> 2838.9736 | AF16: =MAX(0,E16+K16-Z16) -> 0 | AG16: =MAX(0,F16+L16-AA16) -> 0 | AH16: =MAX(0,G16+M16-AB16) -> 0 | AI16: =SUM(H16:M16) -> 69.419859 | AJ16: =SUM(AC16:AH16) -> 3732.7539
A17: 13 | B17: =AC16 -> 0 | C17: =AD16 -> 893.7803 | D17: =AE16 -> 2838.9736 | E17: =AF16 -> 0 | F17: =AG16 -> 0 | G17: =AH16 -> 0 | H17: =B17*N(Debts!C7)/12 -> 0 | I17: =C17*N(Debts!C8)/12 -> 5.9585354 | J17: =D17*N(Debts!C9)/12 -> 61.511094 | K17: =E17*N(Debts!C10)/12 -> 0 | L17: =F17*N(Debts!C11)/12 -> 0 | M17: =G17*N(Debts!C12)/12 -> 0 | N17: =MIN(B17+H17,N(Debts!D7)) -> 0 | O17: =MIN(C17+I17,N(Debts!D8)) -> 60 | P17: =MIN(D17+J17,N(Debts!D9)) -> 96 | Q17: =MIN(E17+K17,N(Debts!D10)) -> 0 | R17: =MIN(F17+L17,N(Debts!D11)) -> 0 | S17: =MIN(G17+M17,N(Debts!D12)) -> 0 | T17: =Debts!$B$14 -> 286 | U17: =MAX(0,T17-SUM(N17:S17)) -> 130 | V17: =_xlfn.MINIFS($B$3:$G$3,B17:G17,">0.005") -> 2 | W17: =IF(B17<=0.005,0,MIN(B17+H17,N17+IF(B$3=$V17,$U17,0))) -> 0 | X17: =IF(C17<=0.005,0,MIN(C17+I17,O17+IF(C$3=$V17,$U17,0))) -> 190 | Y17: =IF(D17<=0.005,0,MIN(D17+J17,P17+IF(D$3=$V17,$U17,0))) -> 96 | Z17: =IF(E17<=0.005,0,MIN(E17+K17,Q17+IF(E$3=$V17,$U17,0))) -> 0 | AA17: =IF(F17<=0.005,0,MIN(F17+L17,R17+IF(F$3=$V17,$U17,0))) -> 0 | AB17: =IF(G17<=0.005,0,MIN(G17+M17,S17+IF(G$3=$V17,$U17,0))) -> 0 | AC17: =MAX(0,B17+H17-W17) -> 0 | AD17: =MAX(0,C17+I17-X17) -> 709.73884 | AE17: =MAX(0,D17+J17-Y17) -> 2804.4847 | AF17: =MAX(0,E17+K17-Z17) -> 0 | AG17: =MAX(0,F17+L17-AA17) -> 0 | AH17: =MAX(0,G17+M17-AB17) -> 0 | AI17: =SUM(H17:M17) -> 67.469629 | AJ17: =SUM(AC17:AH17) -> 3514.2235
A18: 14 | B18: =AC17 -> 0 | C18: =AD17 -> 709.73884 | D18: =AE17 -> 2804.4847 | E18: =AF17 -> 0 | F18: =AG17 -> 0 | G18: =AH17 -> 0 | H18: =B18*N(Debts!C7)/12 -> 0 | I18: =C18*N(Debts!C8)/12 -> 4.7315923 | J18: =D18*N(Debts!C9)/12 -> 60.763834 | K18: =E18*N(Debts!C10)/12 -> 0 | L18: =F18*N(Debts!C11)/12 -> 0 | M18: =G18*N(Debts!C12)/12 -> 0 | N18: =MIN(B18+H18,N(Debts!D7)) -> 0 | O18: =MIN(C18+I18,N(Debts!D8)) -> 60 | P18: =MIN(D18+J18,N(Debts!D9)) -> 96 | Q18: =MIN(E18+K18,N(Debts!D10)) -> 0 | R18: =MIN(F18+L18,N(Debts!D11)) -> 0 | S18: =MIN(G18+M18,N(Debts!D12)) -> 0 | T18: =Debts!$B$14 -> 286 | U18: =MAX(0,T18-SUM(N18:S18)) -> 130 | V18: =_xlfn.MINIFS($B$3:$G$3,B18:G18,">0.005") -> 2 | W18: =IF(B18<=0.005,0,MIN(B18+H18,N18+IF(B$3=$V18,$U18,0))) -> 0 | X18: =IF(C18<=0.005,0,MIN(C18+I18,O18+IF(C$3=$V18,$U18,0))) -> 190 | Y18: =IF(D18<=0.005,0,MIN(D18+J18,P18+IF(D$3=$V18,$U18,0))) -> 96 | Z18: =IF(E18<=0.005,0,MIN(E18+K18,Q18+IF(E$3=$V18,$U18,0))) -> 0 | AA18: =IF(F18<=0.005,0,MIN(F18+L18,R18+IF(F$3=$V18,$U18,0))) -> 0 | AB18: =IF(G18<=0.005,0,MIN(G18+M18,S18+IF(G$3=$V18,$U18,0))) -> 0 | AC18: =MAX(0,B18+H18-W18) -> 0 | AD18: =MAX(0,C18+I18-X18) -> 524.47043 | AE18: =MAX(0,D18+J18-Y18) -> 2769.2485 | AF18: =MAX(0,E18+K18-Z18) -> 0 | AG18: =MAX(0,F18+L18-AA18) -> 0 | AH18: =MAX(0,G18+M18-AB18) -> 0 | AI18: =SUM(H18:M18) -> 65.495426 | AJ18: =SUM(AC18:AH18) -> 3293.7189
A19: 15 | B19: =AC18 -> 0 | C19: =AD18 -> 524.47043 | D19: =AE18 -> 2769.2485 | E19: =AF18 -> 0 | F19: =AG18 -> 0 | G19: =AH18 -> 0 | H19: =B19*N(Debts!C7)/12 -> 0 | I19: =C19*N(Debts!C8)/12 -> 3.4964695 | J19: =D19*N(Debts!C9)/12 -> 60.000384 | K19: =E19*N(Debts!C10)/12 -> 0 | L19: =F19*N(Debts!C11)/12 -> 0 | M19: =G19*N(Debts!C12)/12 -> 0 | N19: =MIN(B19+H19,N(Debts!D7)) -> 0 | O19: =MIN(C19+I19,N(Debts!D8)) -> 60 | P19: =MIN(D19+J19,N(Debts!D9)) -> 96 | Q19: =MIN(E19+K19,N(Debts!D10)) -> 0 | R19: =MIN(F19+L19,N(Debts!D11)) -> 0 | S19: =MIN(G19+M19,N(Debts!D12)) -> 0 | T19: =Debts!$B$14 -> 286 | U19: =MAX(0,T19-SUM(N19:S19)) -> 130 | V19: =_xlfn.MINIFS($B$3:$G$3,B19:G19,">0.005") -> 2 | W19: =IF(B19<=0.005,0,MIN(B19+H19,N19+IF(B$3=$V19,$U19,0))) -> 0 | X19: =IF(C19<=0.005,0,MIN(C19+I19,O19+IF(C$3=$V19,$U19,0))) -> 190 | Y19: =IF(D19<=0.005,0,MIN(D19+J19,P19+IF(D$3=$V19,$U19,0))) -> 96 | Z19: =IF(E19<=0.005,0,MIN(E19+K19,Q19+IF(E$3=$V19,$U19,0))) -> 0 | AA19: =IF(F19<=0.005,0,MIN(F19+L19,R19+IF(F$3=$V19,$U19,0))) -> 0 | AB19: =IF(G19<=0.005,0,MIN(G19+M19,S19+IF(G$3=$V19,$U19,0))) -> 0 | AC19: =MAX(0,B19+H19-W19) -> 0 | AD19: =MAX(0,C19+I19-X19) -> 337.9669 | AE19: =MAX(0,D19+J19-Y19) -> 2733.2489 | AF19: =MAX(0,E19+K19-Z19) -> 0 | AG19: =MAX(0,F19+L19-AA19) -> 0 | AH19: =MAX(0,G19+M19-AB19) -> 0 | AI19: =SUM(H19:M19) -> 63.496853 | AJ19: =SUM(AC19:AH19) -> 3071.2158
A20: 16 | B20: =AC19 -> 0 | C20: =AD19 -> 337.9669 | D20: =AE19 -> 2733.2489 | E20: =AF19 -> 0 | F20: =AG19 -> 0 | G20: =AH19 -> 0 | H20: =B20*N(Debts!C7)/12 -> 0 | I20: =C20*N(Debts!C8)/12 -> 2.2531127 | J20: =D20*N(Debts!C9)/12 -> 59.220392 | K20: =E20*N(Debts!C10)/12 -> 0 | L20: =F20*N(Debts!C11)/12 -> 0 | M20: =G20*N(Debts!C12)/12 -> 0 | N20: =MIN(B20+H20,N(Debts!D7)) -> 0 | O20: =MIN(C20+I20,N(Debts!D8)) -> 60 | P20: =MIN(D20+J20,N(Debts!D9)) -> 96 | Q20: =MIN(E20+K20,N(Debts!D10)) -> 0 | R20: =MIN(F20+L20,N(Debts!D11)) -> 0 | S20: =MIN(G20+M20,N(Debts!D12)) -> 0 | T20: =Debts!$B$14 -> 286 | U20: =MAX(0,T20-SUM(N20:S20)) -> 130 | V20: =_xlfn.MINIFS($B$3:$G$3,B20:G20,">0.005") -> 2 | W20: =IF(B20<=0.005,0,MIN(B20+H20,N20+IF(B$3=$V20,$U20,0))) -> 0 | X20: =IF(C20<=0.005,0,MIN(C20+I20,O20+IF(C$3=$V20,$U20,0))) -> 190 | Y20: =IF(D20<=0.005,0,MIN(D20+J20,P20+IF(D$3=$V20,$U20,0))) -> 96 | Z20: =IF(E20<=0.005,0,MIN(E20+K20,Q20+IF(E$3=$V20,$U20,0))) -> 0 | AA20: =IF(F20<=0.005,0,MIN(F20+L20,R20+IF(F$3=$V20,$U20,0))) -> 0 | AB20: =IF(G20<=0.005,0,MIN(G20+M20,S20+IF(G$3=$V20,$U20,0))) -> 0 | AC20: =MAX(0,B20+H20-W20) -> 0 | AD20: =MAX(0,C20+I20-X20) -> 150.22001 | AE20: =MAX(0,D20+J20-Y20) -> 2696.4693 | AF20: =MAX(0,E20+K20-Z20) -> 0 | AG20: =MAX(0,F20+L20-AA20) -> 0 | AH20: =MAX(0,G20+M20-AB20) -> 0 | AI20: =SUM(H20:M20) -> 61.473505 | AJ20: =SUM(AC20:AH20) -> 2846.6893
A21: 17 | B21: =AC20 -> 0 | C21: =AD20 -> 150.22001 | D21: =AE20 -> 2696.4693 | E21: =AF20 -> 0 | F21: =AG20 -> 0 | G21: =AH20 -> 0 | H21: =B21*N(Debts!C7)/12 -> 0 | I21: =C21*N(Debts!C8)/12 -> 1.0014668 | J21: =D21*N(Debts!C9)/12 -> 58.423501 | K21: =E21*N(Debts!C10)/12 -> 0 | L21: =F21*N(Debts!C11)/12 -> 0 | M21: =G21*N(Debts!C12)/12 -> 0 | N21: =MIN(B21+H21,N(Debts!D7)) -> 0 | O21: =MIN(C21+I21,N(Debts!D8)) -> 60 | P21: =MIN(D21+J21,N(Debts!D9)) -> 96 | Q21: =MIN(E21+K21,N(Debts!D10)) -> 0 | R21: =MIN(F21+L21,N(Debts!D11)) -> 0 | S21: =MIN(G21+M21,N(Debts!D12)) -> 0 | T21: =Debts!$B$14 -> 286 | U21: =MAX(0,T21-SUM(N21:S21)) -> 130 | V21: =_xlfn.MINIFS($B$3:$G$3,B21:G21,">0.005") -> 2 | W21: =IF(B21<=0.005,0,MIN(B21+H21,N21+IF(B$3=$V21,$U21,0))) -> 0 | X21: =IF(C21<=0.005,0,MIN(C21+I21,O21+IF(C$3=$V21,$U21,0))) -> 151.22148 | Y21: =IF(D21<=0.005,0,MIN(D21+J21,P21+IF(D$3=$V21,$U21,0))) -> 96 | Z21: =IF(E21<=0.005,0,MIN(E21+K21,Q21+IF(E$3=$V21,$U21,0))) -> 0 | AA21: =IF(F21<=0.005,0,MIN(F21+L21,R21+IF(F$3=$V21,$U21,0))) -> 0 | AB21: =IF(G21<=0.005,0,MIN(G21+M21,S21+IF(G$3=$V21,$U21,0))) -> 0 | AC21: =MAX(0,B21+H21-W21) -> 0 | AD21: =MAX(0,C21+I21-X21) -> 0 | AE21: =MAX(0,D21+J21-Y21) -> 2658.8928 | AF21: =MAX(0,E21+K21-Z21) -> 0 | AG21: =MAX(0,F21+L21-AA21) -> 0 | AH21: =MAX(0,G21+M21-AB21) -> 0 | AI21: =SUM(H21:M21) -> 59.424967 | AJ21: =SUM(AC21:AH21) -> 2658.8928
A22: 18 | B22: =AC21 -> 0 | C22: =AD21 -> 0 | D22: =AE21 -> 2658.8928 | E22: =AF21 -> 0 | F22: =AG21 -> 0 | G22: =AH21 -> 0 | H22: =B22*N(Debts!C7)/12 -> 0 | I22: =C22*N(Debts!C8)/12 -> 0 | J22: =D22*N(Debts!C9)/12 -> 57.609343 | K22: =E22*N(Debts!C10)/12 -> 0 | L22: =F22*N(Debts!C11)/12 -> 0 | M22: =G22*N(Debts!C12)/12 -> 0 | N22: =MIN(B22+H22,N(Debts!D7)) -> 0 | O22: =MIN(C22+I22,N(Debts!D8)) -> 0 | P22: =MIN(D22+J22,N(Debts!D9)) -> 96 | Q22: =MIN(E22+K22,N(Debts!D10)) -> 0 | R22: =MIN(F22+L22,N(Debts!D11)) -> 0 | S22: =MIN(G22+M22,N(Debts!D12)) -> 0 | T22: =Debts!$B$14 -> 286 | U22: =MAX(0,T22-SUM(N22:S22)) -> 190 | V22: =_xlfn.MINIFS($B$3:$G$3,B22:G22,">0.005") -> 3 | W22: =IF(B22<=0.005,0,MIN(B22+H22,N22+IF(B$3=$V22,$U22,0))) -> 0 | X22: =IF(C22<=0.005,0,MIN(C22+I22,O22+IF(C$3=$V22,$U22,0))) -> 0 | Y22: =IF(D22<=0.005,0,MIN(D22+J22,P22+IF(D$3=$V22,$U22,0))) -> 286 | Z22: =IF(E22<=0.005,0,MIN(E22+K22,Q22+IF(E$3=$V22,$U22,0))) -> 0 | AA22: =IF(F22<=0.005,0,MIN(F22+L22,R22+IF(F$3=$V22,$U22,0))) -> 0 | AB22: =IF(G22<=0.005,0,MIN(G22+M22,S22+IF(G$3=$V22,$U22,0))) -> 0 | AC22: =MAX(0,B22+H22-W22) -> 0 | AD22: =MAX(0,C22+I22-X22) -> 0 | AE22: =MAX(0,D22+J22-Y22) -> 2430.5021 | AF22: =MAX(0,E22+K22-Z22) -> 0 | AG22: =MAX(0,F22+L22-AA22) -> 0 | AH22: =MAX(0,G22+M22-AB22) -> 0 | AI22: =SUM(H22:M22) -> 57.609343 | AJ22: =SUM(AC22:AH22) -> 2430.5021
A23: 19 | B23: =AC22 -> 0 | C23: =AD22 -> 0 | D23: =AE22 -> 2430.5021 | E23: =AF22 -> 0 | F23: =AG22 -> 0 | G23: =AH22 -> 0 | H23: =B23*N(Debts!C7)/12 -> 0 | I23: =C23*N(Debts!C8)/12 -> 0 | J23: =D23*N(Debts!C9)/12 -> 52.660879 | K23: =E23*N(Debts!C10)/12 -> 0 | L23: =F23*N(Debts!C11)/12 -> 0 | M23: =G23*N(Debts!C12)/12 -> 0 | N23: =MIN(B23+H23,N(Debts!D7)) -> 0 | O23: =MIN(C23+I23,N(Debts!D8)) -> 0 | P23: =MIN(D23+J23,N(Debts!D9)) -> 96 | Q23: =MIN(E23+K23,N(Debts!D10)) -> 0 | R23: =MIN(F23+L23,N(Debts!D11)) -> 0 | S23: =MIN(G23+M23,N(Debts!D12)) -> 0 | T23: =Debts!$B$14 -> 286 | U23: =MAX(0,T23-SUM(N23:S23)) -> 190 | V23: =_xlfn.MINIFS($B$3:$G$3,B23:G23,">0.005") -> 3 | W23: =IF(B23<=0.005,0,MIN(B23+H23,N23+IF(B$3=$V23,$U23,0))) -> 0 | X23: =IF(C23<=0.005,0,MIN(C23+I23,O23+IF(C$3=$V23,$U23,0))) -> 0 | Y23: =IF(D23<=0.005,0,MIN(D23+J23,P23+IF(D$3=$V23,$U23,0))) -> 286 | Z23: =IF(E23<=0.005,0,MIN(E23+K23,Q23+IF(E$3=$V23,$U23,0))) -> 0 | AA23: =IF(F23<=0.005,0,MIN(F23+L23,R23+IF(F$3=$V23,$U23,0))) -> 0 | AB23: =IF(G23<=0.005,0,MIN(G23+M23,S23+IF(G$3=$V23,$U23,0))) -> 0 | AC23: =MAX(0,B23+H23-W23) -> 0 | AD23: =MAX(0,C23+I23-X23) -> 0 | AE23: =MAX(0,D23+J23-Y23) -> 2197.163 | AF23: =MAX(0,E23+K23-Z23) -> 0 | AG23: =MAX(0,F23+L23-AA23) -> 0 | AH23: =MAX(0,G23+M23-AB23) -> 0 | AI23: =SUM(H23:M23) -> 52.660879 | AJ23: =SUM(AC23:AH23) -> 2197.163
A24: 20 | B24: =AC23 -> 0 | C24: =AD23 -> 0 | D24: =AE23 -> 2197.163 | E24: =AF23 -> 0 | F24: =AG23 -> 0 | G24: =AH23 -> 0 | H24: =B24*N(Debts!C7)/12 -> 0 | I24: =C24*N(Debts!C8)/12 -> 0 | J24: =D24*N(Debts!C9)/12 -> 47.605198 | K24: =E24*N(Debts!C10)/12 -> 0 | L24: =F24*N(Debts!C11)/12 -> 0 | M24: =G24*N(Debts!C12)/12 -> 0 | N24: =MIN(B24+H24,N(Debts!D7)) -> 0 | O24: =MIN(C24+I24,N(Debts!D8)) -> 0 | P24: =MIN(D24+J24,N(Debts!D9)) -> 96 | Q24: =MIN(E24+K24,N(Debts!D10)) -> 0 | R24: =MIN(F24+L24,N(Debts!D11)) -> 0 | S24: =MIN(G24+M24,N(Debts!D12)) -> 0 | T24: =Debts!$B$14 -> 286 | U24: =MAX(0,T24-SUM(N24:S24)) -> 190 | V24: =_xlfn.MINIFS($B$3:$G$3,B24:G24,">0.005") -> 3 | W24: =IF(B24<=0.005,0,MIN(B24+H24,N24+IF(B$3=$V24,$U24,0))) -> 0 | X24: =IF(C24<=0.005,0,MIN(C24+I24,O24+IF(C$3=$V24,$U24,0))) -> 0 | Y24: =IF(D24<=0.005,0,MIN(D24+J24,P24+IF(D$3=$V24,$U24,0))) -> 286 | Z24: =IF(E24<=0.005,0,MIN(E24+K24,Q24+IF(E$3=$V24,$U24,0))) -> 0 | AA24: =IF(F24<=0.005,0,MIN(F24+L24,R24+IF(F$3=$V24,$U24,0))) -> 0 | AB24: =IF(G24<=0.005,0,MIN(G24+M24,S24+IF(G$3=$V24,$U24,0))) -> 0 | AC24: =MAX(0,B24+H24-W24) -> 0 | AD24: =MAX(0,C24+I24-X24) -> 0 | AE24: =MAX(0,D24+J24-Y24) -> 1958.7682 | AF24: =MAX(0,E24+K24-Z24) -> 0 | AG24: =MAX(0,F24+L24-AA24) -> 0 | AH24: =MAX(0,G24+M24-AB24) -> 0 | AI24: =SUM(H24:M24) -> 47.605198 | AJ24: =SUM(AC24:AH24) -> 1958.7682
A25: 21 | B25: =AC24 -> 0 | C25: =AD24 -> 0 | D25: =AE24 -> 1958.7682 | E25: =AF24 -> 0 | F25: =AG24 -> 0 | G25: =AH24 -> 0 | H25: =B25*N(Debts!C7)/12 -> 0 | I25: =C25*N(Debts!C8)/12 -> 0 | J25: =D25*N(Debts!C9)/12 -> 42.439977 | K25: =E25*N(Debts!C10)/12 -> 0 | L25: =F25*N(Debts!C11)/12 -> 0 | M25: =G25*N(Debts!C12)/12 -> 0 | N25: =MIN(B25+H25,N(Debts!D7)) -> 0 | O25: =MIN(C25+I25,N(Debts!D8)) -> 0 | P25: =MIN(D25+J25,N(Debts!D9)) -> 96 | Q25: =MIN(E25+K25,N(Debts!D10)) -> 0 | R25: =MIN(F25+L25,N(Debts!D11)) -> 0 | S25: =MIN(G25+M25,N(Debts!D12)) -> 0 | T25: =Debts!$B$14 -> 286 | U25: =MAX(0,T25-SUM(N25:S25)) -> 190 | V25: =_xlfn.MINIFS($B$3:$G$3,B25:G25,">0.005") -> 3 | W25: =IF(B25<=0.005,0,MIN(B25+H25,N25+IF(B$3=$V25,$U25,0))) -> 0 | X25: =IF(C25<=0.005,0,MIN(C25+I25,O25+IF(C$3=$V25,$U25,0))) -> 0 | Y25: =IF(D25<=0.005,0,MIN(D25+J25,P25+IF(D$3=$V25,$U25,0))) -> 286 | Z25: =IF(E25<=0.005,0,MIN(E25+K25,Q25+IF(E$3=$V25,$U25,0))) -> 0 | AA25: =IF(F25<=0.005,0,MIN(F25+L25,R25+IF(F$3=$V25,$U25,0))) -> 0 | AB25: =IF(G25<=0.005,0,MIN(G25+M25,S25+IF(G$3=$V25,$U25,0))) -> 0 | AC25: =MAX(0,B25+H25-W25) -> 0 | AD25: =MAX(0,C25+I25-X25) -> 0 | AE25: =MAX(0,D25+J25-Y25) -> 1715.2082 | AF25: =MAX(0,E25+K25-Z25) -> 0 | AG25: =MAX(0,F25+L25-AA25) -> 0 | AH25: =MAX(0,G25+M25-AB25) -> 0 | AI25: =SUM(H25:M25) -> 42.439977 | AJ25: =SUM(AC25:AH25) -> 1715.2082
A26: 22 | B26: =AC25 -> 0 | C26: =AD25 -> 0 | D26: =AE25 -> 1715.2082 | E26: =AF25 -> 0 | F26: =AG25 -> 0 | G26: =AH25 -> 0 | H26: =B26*N(Debts!C7)/12 -> 0 | I26: =C26*N(Debts!C8)/12 -> 0 | J26: =D26*N(Debts!C9)/12 -> 37.162843 | K26: =E26*N(Debts!C10)/12 -> 0 | L26: =F26*N(Debts!C11)/12 -> 0 | M26: =G26*N(Debts!C12)/12 -> 0 | N26: =MIN(B26+H26,N(Debts!D7)) -> 0 | O26: =MIN(C26+I26,N(Debts!D8)) -> 0 | P26: =MIN(D26+J26,N(Debts!D9)) -> 96 | Q26: =MIN(E26+K26,N(Debts!D10)) -> 0 | R26: =MIN(F26+L26,N(Debts!D11)) -> 0 | S26: =MIN(G26+M26,N(Debts!D12)) -> 0 | T26: =Debts!$B$14 -> 286 | U26: =MAX(0,T26-SUM(N26:S26)) -> 190 | V26: =_xlfn.MINIFS($B$3:$G$3,B26:G26,">0.005") -> 3 | W26: =IF(B26<=0.005,0,MIN(B26+H26,N26+IF(B$3=$V26,$U26,0))) -> 0 | X26: =IF(C26<=0.005,0,MIN(C26+I26,O26+IF(C$3=$V26,$U26,0))) -> 0 | Y26: =IF(D26<=0.005,0,MIN(D26+J26,P26+IF(D$3=$V26,$U26,0))) -> 286 | Z26: =IF(E26<=0.005,0,MIN(E26+K26,Q26+IF(E$3=$V26,$U26,0))) -> 0 | AA26: =IF(F26<=0.005,0,MIN(F26+L26,R26+IF(F$3=$V26,$U26,0))) -> 0 | AB26: =IF(G26<=0.005,0,MIN(G26+M26,S26+IF(G$3=$V26,$U26,0))) -> 0 | AC26: =MAX(0,B26+H26-W26) -> 0 | AD26: =MAX(0,C26+I26-X26) -> 0 | AE26: =MAX(0,D26+J26-Y26) -> 1466.371 | AF26: =MAX(0,E26+K26-Z26) -> 0 | AG26: =MAX(0,F26+L26-AA26) -> 0 | AH26: =MAX(0,G26+M26-AB26) -> 0 | AI26: =SUM(H26:M26) -> 37.162843 | AJ26: =SUM(AC26:AH26) -> 1466.371
A27: 23 | B27: =AC26 -> 0 | C27: =AD26 -> 0 | D27: =AE26 -> 1466.371 | E27: =AF26 -> 0 | F27: =AG26 -> 0 | G27: =AH26 -> 0 | H27: =B27*N(Debts!C7)/12 -> 0 | I27: =C27*N(Debts!C8)/12 -> 0 | J27: =D27*N(Debts!C9)/12 -> 31.771372 | K27: =E27*N(Debts!C10)/12 -> 0 | L27: =F27*N(Debts!C11)/12 -> 0 | M27: =G27*N(Debts!C12)/12 -> 0 | N27: =MIN(B27+H27,N(Debts!D7)) -> 0 | O27: =MIN(C27+I27,N(Debts!D8)) -> 0 | P27: =MIN(D27+J27,N(Debts!D9)) -> 96 | Q27: =MIN(E27+K27,N(Debts!D10)) -> 0 | R27: =MIN(F27+L27,N(Debts!D11)) -> 0 | S27: =MIN(G27+M27,N(Debts!D12)) -> 0 | T27: =Debts!$B$14 -> 286 | U27: =MAX(0,T27-SUM(N27:S27)) -> 190 | V27: =_xlfn.MINIFS($B$3:$G$3,B27:G27,">0.005") -> 3 | W27: =IF(B27<=0.005,0,MIN(B27+H27,N27+IF(B$3=$V27,$U27,0))) -> 0 | X27: =IF(C27<=0.005,0,MIN(C27+I27,O27+IF(C$3=$V27,$U27,0))) -> 0 | Y27: =IF(D27<=0.005,0,MIN(D27+J27,P27+IF(D$3=$V27,$U27,0))) -> 286 | Z27: =IF(E27<=0.005,0,MIN(E27+K27,Q27+IF(E$3=$V27,$U27,0))) -> 0 | AA27: =IF(F27<=0.005,0,MIN(F27+L27,R27+IF(F$3=$V27,$U27,0))) -> 0 | AB27: =IF(G27<=0.005,0,MIN(G27+M27,S27+IF(G$3=$V27,$U27,0))) -> 0 | AC27: =MAX(0,B27+H27-W27) -> 0 | AD27: =MAX(0,C27+I27-X27) -> 0 | AE27: =MAX(0,D27+J27-Y27) -> 1212.1424 | AF27: =MAX(0,E27+K27-Z27) -> 0 | AG27: =MAX(0,F27+L27-AA27) -> 0 | AH27: =MAX(0,G27+M27-AB27) -> 0 | AI27: =SUM(H27:M27) -> 31.771372 | AJ27: =SUM(AC27:AH27) -> 1212.1424
A28: 24 | B28: =AC27 -> 0 | C28: =AD27 -> 0 | D28: =AE27 -> 1212.1424 | E28: =AF27 -> 0 | F28: =AG27 -> 0 | G28: =AH27 -> 0 | H28: =B28*N(Debts!C7)/12 -> 0 | I28: =C28*N(Debts!C8)/12 -> 0 | J28: =D28*N(Debts!C9)/12 -> 26.263085 | K28: =E28*N(Debts!C10)/12 -> 0 | L28: =F28*N(Debts!C11)/12 -> 0 | M28: =G28*N(Debts!C12)/12 -> 0 | N28: =MIN(B28+H28,N(Debts!D7)) -> 0 | O28: =MIN(C28+I28,N(Debts!D8)) -> 0 | P28: =MIN(D28+J28,N(Debts!D9)) -> 96 | Q28: =MIN(E28+K28,N(Debts!D10)) -> 0 | R28: =MIN(F28+L28,N(Debts!D11)) -> 0 | S28: =MIN(G28+M28,N(Debts!D12)) -> 0 | T28: =Debts!$B$14 -> 286 | U28: =MAX(0,T28-SUM(N28:S28)) -> 190 | V28: =_xlfn.MINIFS($B$3:$G$3,B28:G28,">0.005") -> 3 | W28: =IF(B28<=0.005,0,MIN(B28+H28,N28+IF(B$3=$V28,$U28,0))) -> 0 | X28: =IF(C28<=0.005,0,MIN(C28+I28,O28+IF(C$3=$V28,$U28,0))) -> 0 | Y28: =IF(D28<=0.005,0,MIN(D28+J28,P28+IF(D$3=$V28,$U28,0))) -> 286 | Z28: =IF(E28<=0.005,0,MIN(E28+K28,Q28+IF(E$3=$V28,$U28,0))) -> 0 | AA28: =IF(F28<=0.005,0,MIN(F28+L28,R28+IF(F$3=$V28,$U28,0))) -> 0 | AB28: =IF(G28<=0.005,0,MIN(G28+M28,S28+IF(G$3=$V28,$U28,0))) -> 0 | AC28: =MAX(0,B28+H28-W28) -> 0 | AD28: =MAX(0,C28+I28-X28) -> 0 | AE28: =MAX(0,D28+J28-Y28) -> 952.40546 | AF28: =MAX(0,E28+K28-Z28) -> 0 | AG28: =MAX(0,F28+L28-AA28) -> 0 | AH28: =MAX(0,G28+M28-AB28) -> 0 | AI28: =SUM(H28:M28) -> 26.263085 | AJ28: =SUM(AC28:AH28) -> 952.40546
A29: 25 | B29: =AC28 -> 0 | C29: =AD28 -> 0 | D29: =AE28 -> 952.40546 | E29: =AF28 -> 0 | F29: =AG28 -> 0 | G29: =AH28 -> 0 | H29: =B29*N(Debts!C7)/12 -> 0 | I29: =C29*N(Debts!C8)/12 -> 0 | J29: =D29*N(Debts!C9)/12 -> 20.635452 | K29: =E29*N(Debts!C10)/12 -> 0 | L29: =F29*N(Debts!C11)/12 -> 0 | M29: =G29*N(Debts!C12)/12 -> 0 | N29: =MIN(B29+H29,N(Debts!D7)) -> 0 | O29: =MIN(C29+I29,N(Debts!D8)) -> 0 | P29: =MIN(D29+J29,N(Debts!D9)) -> 96 | Q29: =MIN(E29+K29,N(Debts!D10)) -> 0 | R29: =MIN(F29+L29,N(Debts!D11)) -> 0 | S29: =MIN(G29+M29,N(Debts!D12)) -> 0 | T29: =Debts!$B$14 -> 286 | U29: =MAX(0,T29-SUM(N29:S29)) -> 190 | V29: =_xlfn.MINIFS($B$3:$G$3,B29:G29,">0.005") -> 3 | W29: =IF(B29<=0.005,0,MIN(B29+H29,N29+IF(B$3=$V29,$U29,0))) -> 0 | X29: =IF(C29<=0.005,0,MIN(C29+I29,O29+IF(C$3=$V29,$U29,0))) -> 0 | Y29: =IF(D29<=0.005,0,MIN(D29+J29,P29+IF(D$3=$V29,$U29,0))) -> 286 | Z29: =IF(E29<=0.005,0,MIN(E29+K29,Q29+IF(E$3=$V29,$U29,0))) -> 0 | AA29: =IF(F29<=0.005,0,MIN(F29+L29,R29+IF(F$3=$V29,$U29,0))) -> 0 | AB29: =IF(G29<=0.005,0,MIN(G29+M29,S29+IF(G$3=$V29,$U29,0))) -> 0 | AC29: =MAX(0,B29+H29-W29) -> 0 | AD29: =MAX(0,C29+I29-X29) -> 0 | AE29: =MAX(0,D29+J29-Y29) -> 687.04091 | AF29: =MAX(0,E29+K29-Z29) -> 0 | AG29: =MAX(0,F29+L29-AA29) -> 0 | AH29: =MAX(0,G29+M29-AB29) -> 0 | AI29: =SUM(H29:M29) -> 20.635452 | AJ29: =SUM(AC29:AH29) -> 687.04091
A30: 26 | B30: =AC29 -> 0 | C30: =AD29 -> 0 | D30: =AE29 -> 687.04091 | E30: =AF29 -> 0 | F30: =AG29 -> 0 | G30: =AH29 -> 0 | H30: =B30*N(Debts!C7)/12 -> 0 | I30: =C30*N(Debts!C8)/12 -> 0 | J30: =D30*N(Debts!C9)/12 -> 14.885886 | K30: =E30*N(Debts!C10)/12 -> 0 | L30: =F30*N(Debts!C11)/12 -> 0 | M30: =G30*N(Debts!C12)/12 -> 0 | N30: =MIN(B30+H30,N(Debts!D7)) -> 0 | O30: =MIN(C30+I30,N(Debts!D8)) -> 0 | P30: =MIN(D30+J30,N(Debts!D9)) -> 96 | Q30: =MIN(E30+K30,N(Debts!D10)) -> 0 | R30: =MIN(F30+L30,N(Debts!D11)) -> 0 | S30: =MIN(G30+M30,N(Debts!D12)) -> 0 | T30: =Debts!$B$14 -> 286 | U30: =MAX(0,T30-SUM(N30:S30)) -> 190 | V30: =_xlfn.MINIFS($B$3:$G$3,B30:G30,">0.005") -> 3 | W30: =IF(B30<=0.005,0,MIN(B30+H30,N30+IF(B$3=$V30,$U30,0))) -> 0 | X30: =IF(C30<=0.005,0,MIN(C30+I30,O30+IF(C$3=$V30,$U30,0))) -> 0 | Y30: =IF(D30<=0.005,0,MIN(D30+J30,P30+IF(D$3=$V30,$U30,0))) -> 286 | Z30: =IF(E30<=0.005,0,MIN(E30+K30,Q30+IF(E$3=$V30,$U30,0))) -> 0 | AA30: =IF(F30<=0.005,0,MIN(F30+L30,R30+IF(F$3=$V30,$U30,0))) -> 0 | AB30: =IF(G30<=0.005,0,MIN(G30+M30,S30+IF(G$3=$V30,$U30,0))) -> 0 | AC30: =MAX(0,B30+H30-W30) -> 0 | AD30: =MAX(0,C30+I30-X30) -> 0 | AE30: =MAX(0,D30+J30-Y30) -> 415.9268 | AF30: =MAX(0,E30+K30-Z30) -> 0 | AG30: =MAX(0,F30+L30-AA30) -> 0 | AH30: =MAX(0,G30+M30-AB30) -> 0 | AI30: =SUM(H30:M30) -> 14.885886 | AJ30: =SUM(AC30:AH30) -> 415.9268
A31: 27 | B31: =AC30 -> 0 | C31: =AD30 -> 0 | D31: =AE30 -> 415.9268 | E31: =AF30 -> 0 | F31: =AG30 -> 0 | G31: =AH30 -> 0 | H31: =B31*N(Debts!C7)/12 -> 0 | I31: =C31*N(Debts!C8)/12 -> 0 | J31: =D31*N(Debts!C9)/12 -> 9.0117473 | K31: =E31*N(Debts!C10)/12 -> 0 | L31: =F31*N(Debts!C11)/12 -> 0 | M31: =G31*N(Debts!C12)/12 -> 0 | N31: =MIN(B31+H31,N(Debts!D7)) -> 0 | O31: =MIN(C31+I31,N(Debts!D8)) -> 0 | P31: =MIN(D31+J31,N(Debts!D9)) -> 96 | Q31: =MIN(E31+K31,N(Debts!D10)) -> 0 | R31: =MIN(F31+L31,N(Debts!D11)) -> 0 | S31: =MIN(G31+M31,N(Debts!D12)) -> 0 | T31: =Debts!$B$14 -> 286 | U31: =MAX(0,T31-SUM(N31:S31)) -> 190 | V31: =_xlfn.MINIFS($B$3:$G$3,B31:G31,">0.005") -> 3 | W31: =IF(B31<=0.005,0,MIN(B31+H31,N31+IF(B$3=$V31,$U31,0))) -> 0 | X31: =IF(C31<=0.005,0,MIN(C31+I31,O31+IF(C$3=$V31,$U31,0))) -> 0 | Y31: =IF(D31<=0.005,0,MIN(D31+J31,P31+IF(D$3=$V31,$U31,0))) -> 286 | Z31: =IF(E31<=0.005,0,MIN(E31+K31,Q31+IF(E$3=$V31,$U31,0))) -> 0 | AA31: =IF(F31<=0.005,0,MIN(F31+L31,R31+IF(F$3=$V31,$U31,0))) -> 0 | AB31: =IF(G31<=0.005,0,MIN(G31+M31,S31+IF(G$3=$V31,$U31,0))) -> 0 | AC31: =MAX(0,B31+H31-W31) -> 0 | AD31: =MAX(0,C31+I31-X31) -> 0 | AE31: =MAX(0,D31+J31-Y31) -> 138.93854 | AF31: =MAX(0,E31+K31-Z31) -> 0 | AG31: =MAX(0,F31+L31-AA31) -> 0 | AH31: =MAX(0,G31+M31-AB31) -> 0 | AI31: =SUM(H31:M31) -> 9.0117473 | AJ31: =SUM(AC31:AH31) -> 138.93854
A32: 28 | B32: =AC31 -> 0 | C32: =AD31 -> 0 | D32: =AE31 -> 138.93854 | E32: =AF31 -> 0 | F32: =AG31 -> 0 | G32: =AH31 -> 0 | H32: =B32*N(Debts!C7)/12 -> 0 | I32: =C32*N(Debts!C8)/12 -> 0 | J32: =D32*N(Debts!C9)/12 -> 3.0103351 | K32: =E32*N(Debts!C10)/12 -> 0 | L32: =F32*N(Debts!C11)/12 -> 0 | M32: =G32*N(Debts!C12)/12 -> 0 | N32: =MIN(B32+H32,N(Debts!D7)) -> 0 | O32: =MIN(C32+I32,N(Debts!D8)) -> 0 | P32: =MIN(D32+J32,N(Debts!D9)) -> 96 | Q32: =MIN(E32+K32,N(Debts!D10)) -> 0 | R32: =MIN(F32+L32,N(Debts!D11)) -> 0 | S32: =MIN(G32+M32,N(Debts!D12)) -> 0 | T32: =Debts!$B$14 -> 286 | U32: =MAX(0,T32-SUM(N32:S32)) -> 190 | V32: =_xlfn.MINIFS($B$3:$G$3,B32:G32,">0.005") -> 3 | W32: =IF(B32<=0.005,0,MIN(B32+H32,N32+IF(B$3=$V32,$U32,0))) -> 0 | X32: =IF(C32<=0.005,0,MIN(C32+I32,O32+IF(C$3=$V32,$U32,0))) -> 0 | Y32: =IF(D32<=0.005,0,MIN(D32+J32,P32+IF(D$3=$V32,$U32,0))) -> 141.94888 | Z32: =IF(E32<=0.005,0,MIN(E32+K32,Q32+IF(E$3=$V32,$U32,0))) -> 0 | AA32: =IF(F32<=0.005,0,MIN(F32+L32,R32+IF(F$3=$V32,$U32,0))) -> 0 | AB32: =IF(G32<=0.005,0,MIN(G32+M32,S32+IF(G$3=$V32,$U32,0))) -> 0 | AC32: =MAX(0,B32+H32-W32) -> 0 | AD32: =MAX(0,C32+I32-X32) -> 0 | AE32: =MAX(0,D32+J32-Y32) -> 0 | AF32: =MAX(0,E32+K32-Z32) -> 0 | AG32: =MAX(0,F32+L32-AA32) -> 0 | AH32: =MAX(0,G32+M32-AB32) -> 0 | AI32: =SUM(H32:M32) -> 3.0103351 | AJ32: =SUM(AC32:AH32) -> 0
A33: 29 | B33: =AC32 -> 0 | C33: =AD32 -> 0 | D33: =AE32 -> 0 | E33: =AF32 -> 0 | F33: =AG32 -> 0 | G33: =AH32 -> 0 | H33: =B33*N(Debts!C7)/12 -> 0 | I33: =C33*N(Debts!C8)/12 -> 0 | J33: =D33*N(Debts!C9)/12 -> 0 | K33: =E33*N(Debts!C10)/12 -> 0 | L33: =F33*N(Debts!C11)/12 -> 0 | M33: =G33*N(Debts!C12)/12 -> 0 | N33: =MIN(B33+H33,N(Debts!D7)) -> 0 | O33: =MIN(C33+I33,N(Debts!D8)) -> 0 | P33: =MIN(D33+J33,N(Debts!D9)) -> 0 | Q33: =MIN(E33+K33,N(Debts!D10)) -> 0 | R33: =MIN(F33+L33,N(Debts!D11)) -> 0 | S33: =MIN(G33+M33,N(Debts!D12)) -> 0 | T33: =Debts!$B$14 -> 286 | U33: =MAX(0,T33-SUM(N33:S33)) -> 286 | V33: =_xlfn.MINIFS($B$3:$G$3,B33:G33,">0.005") -> 0 | W33: =IF(B33<=0.005,0,MIN(B33+H33,N33+IF(B$3=$V33,$U33,0))) -> 0 | X33: =IF(C33<=0.005,0,MIN(C33+I33,O33+IF(C$3=$V33,$U33,0))) -> 0 | Y33: =IF(D33<=0.005,0,MIN(D33+J33,P33+IF(D$3=$V33,$U33,0))) -> 0 | Z33: =IF(E33<=0.005,0,MIN(E33+K33,Q33+IF(E$3=$V33,$U33,0))) -> 0 | AA33: =IF(F33<=0.005,0,MIN(F33+L33,R33+IF(F$3=$V33,$U33,0))) -> 0 | AB33: =IF(G33<=0.005,0,MIN(G33+M33,S33+IF(G$3=$V33,$U33,0))) -> 0 | AC33: =MAX(0,B33+H33-W33) -> 0 | AD33: =MAX(0,C33+I33-X33) -> 0 | AE33: =MAX(0,D33+J33-Y33) -> 0 | AF33: =MAX(0,E33+K33-Z33) -> 0 | AG33: =MAX(0,F33+L33-AA33) -> 0 | AH33: =MAX(0,G33+M33-AB33) -> 0 | AI33: =SUM(H33:M33) -> 0 | AJ33: =SUM(AC33:AH33) -> 0
A34: 30 | B34: =AC33 -> 0 | C34: =AD33 -> 0 | D34: =AE33 -> 0 | E34: =AF33 -> 0 | F34: =AG33 -> 0 | G34: =AH33 -> 0 | H34: =B34*N(Debts!C7)/12 -> 0 | I34: =C34*N(Debts!C8)/12 -> 0 | J34: =D34*N(Debts!C9)/12 -> 0 | K34: =E34*N(Debts!C10)/12 -> 0 | L34: =F34*N(Debts!C11)/12 -> 0 | M34: =G34*N(Debts!C12)/12 -> 0 | N34: =MIN(B34+H34,N(Debts!D7)) -> 0 | O34: =MIN(C34+I34,N(Debts!D8)) -> 0 | P34: =MIN(D34+J34,N(Debts!D9)) -> 0 | Q34: =MIN(E34+K34,N(Debts!D10)) -> 0 | R34: =MIN(F34+L34,N(Debts!D11)) -> 0 | S34: =MIN(G34+M34,N(Debts!D12)) -> 0 | T34: =Debts!$B$14 -> 286 | U34: =MAX(0,T34-SUM(N34:S34)) -> 286 | V34: =_xlfn.MINIFS($B$3:$G$3,B34:G34,">0.005") -> 0 | W34: =IF(B34<=0.005,0,MIN(B34+H34,N34+IF(B$3=$V34,$U34,0))) -> 0 | X34: =IF(C34<=0.005,0,MIN(C34+I34,O34+IF(C$3=$V34,$U34,0))) -> 0 | Y34: =IF(D34<=0.005,0,MIN(D34+J34,P34+IF(D$3=$V34,$U34,0))) -> 0 | Z34: =IF(E34<=0.005,0,MIN(E34+K34,Q34+IF(E$3=$V34,$U34,0))) -> 0 | AA34: =IF(F34<=0.005,0,MIN(F34+L34,R34+IF(F$3=$V34,$U34,0))) -> 0 | AB34: =IF(G34<=0.005,0,MIN(G34+M34,S34+IF(G$3=$V34,$U34,0))) -> 0 | AC34: =MAX(0,B34+H34-W34) -> 0 | AD34: =MAX(0,C34+I34-X34) -> 0 | AE34: =MAX(0,D34+J34-Y34) -> 0 | AF34: =MAX(0,E34+K34-Z34) -> 0 | AG34: =MAX(0,F34+L34-AA34) -> 0 | AH34: =MAX(0,G34+M34-AB34) -> 0 | AI34: =SUM(H34:M34) -> 0 | AJ34: =SUM(AC34:AH34) -> 0
A35: 31 | B35: =AC34 -> 0 | C35: =AD34 -> 0 | D35: =AE34 -> 0 | E35: =AF34 -> 0 | F35: =AG34 -> 0 | G35: =AH34 -> 0 | H35: =B35*N(Debts!C7)/12 -> 0 | I35: =C35*N(Debts!C8)/12 -> 0 | J35: =D35*N(Debts!C9)/12 -> 0 | K35: =E35*N(Debts!C10)/12 -> 0 | L35: =F35*N(Debts!C11)/12 -> 0 | M35: =G35*N(Debts!C12)/12 -> 0 | N35: =MIN(B35+H35,N(Debts!D7)) -> 0 | O35: =MIN(C35+I35,N(Debts!D8)) -> 0 | P35: =MIN(D35+J35,N(Debts!D9)) -> 0 | Q35: =MIN(E35+K35,N(Debts!D10)) -> 0 | R35: =MIN(F35+L35,N(Debts!D11)) -> 0 | S35: =MIN(G35+M35,N(Debts!D12)) -> 0 | T35: =Debts!$B$14 -> 286 | U35: =MAX(0,T35-SUM(N35:S35)) -> 286 | V35: =_xlfn.MINIFS($B$3:$G$3,B35:G35,">0.005") -> 0 | W35: =IF(B35<=0.005,0,MIN(B35+H35,N35+IF(B$3=$V35,$U35,0))) -> 0 | X35: =IF(C35<=0.005,0,MIN(C35+I35,O35+IF(C$3=$V35,$U35,0))) -> 0 | Y35: =IF(D35<=0.005,0,MIN(D35+J35,P35+IF(D$3=$V35,$U35,0))) -> 0 | Z35: =IF(E35<=0.005,0,MIN(E35+K35,Q35+IF(E$3=$V35,$U35,0))) -> 0 | AA35: =IF(F35<=0.005,0,MIN(F35+L35,R35+IF(F$3=$V35,$U35,0))) -> 0 | AB35: =IF(G35<=0.005,0,MIN(G35+M35,S35+IF(G$3=$V35,$U35,0))) -> 0 | AC35: =MAX(0,B35+H35-W35) -> 0 | AD35: =MAX(0,C35+I35-X35) -> 0 | AE35: =MAX(0,D35+J35-Y35) -> 0 | AF35: =MAX(0,E35+K35-Z35) -> 0 | AG35: =MAX(0,F35+L35-AA35) -> 0 | AH35: =MAX(0,G35+M35-AB35) -> 0 | AI35: =SUM(H35:M35) -> 0 | AJ35: =SUM(AC35:AH35) -> 0
A36: 32 | B36: =AC35 -> 0 | C36: =AD35 -> 0 | D36: =AE35 -> 0 | E36: =AF35 -> 0 | F36: =AG35 -> 0 | G36: =AH35 -> 0 | H36: =B36*N(Debts!C7)/12 -> 0 | I36: =C36*N(Debts!C8)/12 -> 0 | J36: =D36*N(Debts!C9)/12 -> 0 | K36: =E36*N(Debts!C10)/12 -> 0 | L36: =F36*N(Debts!C11)/12 -> 0 | M36: =G36*N(Debts!C12)/12 -> 0 | N36: =MIN(B36+H36,N(Debts!D7)) -> 0 | O36: =MIN(C36+I36,N(Debts!D8)) -> 0 | P36: =MIN(D36+J36,N(Debts!D9)) -> 0 | Q36: =MIN(E36+K36,N(Debts!D10)) -> 0 | R36: =MIN(F36+L36,N(Debts!D11)) -> 0 | S36: =MIN(G36+M36,N(Debts!D12)) -> 0 | T36: =Debts!$B$14 -> 286 | U36: =MAX(0,T36-SUM(N36:S36)) -> 286 | V36: =_xlfn.MINIFS($B$3:$G$3,B36:G36,">0.005") -> 0 | W36: =IF(B36<=0.005,0,MIN(B36+H36,N36+IF(B$3=$V36,$U36,0))) -> 0 | X36: =IF(C36<=0.005,0,MIN(C36+I36,O36+IF(C$3=$V36,$U36,0))) -> 0 | Y36: =IF(D36<=0.005,0,MIN(D36+J36,P36+IF(D$3=$V36,$U36,0))) -> 0 | Z36: =IF(E36<=0.005,0,MIN(E36+K36,Q36+IF(E$3=$V36,$U36,0))) -> 0 | AA36: =IF(F36<=0.005,0,MIN(F36+L36,R36+IF(F$3=$V36,$U36,0))) -> 0 | AB36: =IF(G36<=0.005,0,MIN(G36+M36,S36+IF(G$3=$V36,$U36,0))) -> 0 | AC36: =MAX(0,B36+H36-W36) -> 0 | AD36: =MAX(0,C36+I36-X36) -> 0 | AE36: =MAX(0,D36+J36-Y36) -> 0 | AF36: =MAX(0,E36+K36-Z36) -> 0 | AG36: =MAX(0,F36+L36-AA36) -> 0 | AH36: =MAX(0,G36+M36-AB36) -> 0 | AI36: =SUM(H36:M36) -> 0 | AJ36: =SUM(AC36:AH36) -> 0
A37: 33 | B37: =AC36 -> 0 | C37: =AD36 -> 0 | D37: =AE36 -> 0 | E37: =AF36 -> 0 | F37: =AG36 -> 0 | G37: =AH36 -> 0 | H37: =B37*N(Debts!C7)/12 -> 0 | I37: =C37*N(Debts!C8)/12 -> 0 | J37: =D37*N(Debts!C9)/12 -> 0 | K37: =E37*N(Debts!C10)/12 -> 0 | L37: =F37*N(Debts!C11)/12 -> 0 | M37: =G37*N(Debts!C12)/12 -> 0 | N37: =MIN(B37+H37,N(Debts!D7)) -> 0 | O37: =MIN(C37+I37,N(Debts!D8)) -> 0 | P37: =MIN(D37+J37,N(Debts!D9)) -> 0 | Q37: =MIN(E37+K37,N(Debts!D10)) -> 0 | R37: =MIN(F37+L37,N(Debts!D11)) -> 0 | S37: =MIN(G37+M37,N(Debts!D12)) -> 0 | T37: =Debts!$B$14 -> 286 | U37: =MAX(0,T37-SUM(N37:S37)) -> 286 | V37: =_xlfn.MINIFS($B$3:$G$3,B37:G37,">0.005") -> 0 | W37: =IF(B37<=0.005,0,MIN(B37+H37,N37+IF(B$3=$V37,$U37,0))) -> 0 | X37: =IF(C37<=0.005,0,MIN(C37+I37,O37+IF(C$3=$V37,$U37,0))) -> 0 | Y37: =IF(D37<=0.005,0,MIN(D37+J37,P37+IF(D$3=$V37,$U37,0))) -> 0 | Z37: =IF(E37<=0.005,0,MIN(E37+K37,Q37+IF(E$3=$V37,$U37,0))) -> 0 | AA37: =IF(F37<=0.005,0,MIN(F37+L37,R37+IF(F$3=$V37,$U37,0))) -> 0 | AB37: =IF(G37<=0.005,0,MIN(G37+M37,S37+IF(G$3=$V37,$U37,0))) -> 0 | AC37: =MAX(0,B37+H37-W37) -> 0 | AD37: =MAX(0,C37+I37-X37) -> 0 | AE37: =MAX(0,D37+J37-Y37) -> 0 | AF37: =MAX(0,E37+K37-Z37) -> 0 | AG37: =MAX(0,F37+L37-AA37) -> 0 | AH37: =MAX(0,G37+M37-AB37) -> 0 | AI37: =SUM(H37:M37) -> 0 | AJ37: =SUM(AC37:AH37) -> 0
A38: 34 | B38: =AC37 -> 0 | C38: =AD37 -> 0 | D38: =AE37 -> 0 | E38: =AF37 -> 0 | F38: =AG37 -> 0 | G38: =AH37 -> 0 | H38: =B38*N(Debts!C7)/12 -> 0 | I38: =C38*N(Debts!C8)/12 -> 0 | J38: =D38*N(Debts!C9)/12 -> 0 | K38: =E38*N(Debts!C10)/12 -> 0 | L38: =F38*N(Debts!C11)/12 -> 0 | M38: =G38*N(Debts!C12)/12 -> 0 | N38: =MIN(B38+H38,N(Debts!D7)) -> 0 | O38: =MIN(C38+I38,N(Debts!D8)) -> 0 | P38: =MIN(D38+J38,N(Debts!D9)) -> 0 | Q38: =MIN(E38+K38,N(Debts!D10)) -> 0 | R38: =MIN(F38+L38,N(Debts!D11)) -> 0 | S38: =MIN(G38+M38,N(Debts!D12)) -> 0 | T38: =Debts!$B$14 -> 286 | U38: =MAX(0,T38-SUM(N38:S38)) -> 286 | V38: =_xlfn.MINIFS($B$3:$G$3,B38:G38,">0.005") -> 0 | W38: =IF(B38<=0.005,0,MIN(B38+H38,N38+IF(B$3=$V38,$U38,0))) -> 0 | X38: =IF(C38<=0.005,0,MIN(C38+I38,O38+IF(C$3=$V38,$U38,0))) -> 0 | Y38: =IF(D38<=0.005,0,MIN(D38+J38,P38+IF(D$3=$V38,$U38,0))) -> 0 | Z38: =IF(E38<=0.005,0,MIN(E38+K38,Q38+IF(E$3=$V38,$U38,0))) -> 0 | AA38: =IF(F38<=0.005,0,MIN(F38+L38,R38+IF(F$3=$V38,$U38,0))) -> 0 | AB38: =IF(G38<=0.005,0,MIN(G38+M38,S38+IF(G$3=$V38,$U38,0))) -> 0 | AC38: =MAX(0,B38+H38-W38) -> 0 | AD38: =MAX(0,C38+I38-X38) -> 0 | AE38: =MAX(0,D38+J38-Y38) -> 0 | AF38: =MAX(0,E38+K38-Z38) -> 0 | AG38: =MAX(0,F38+L38-AA38) -> 0 | AH38: =MAX(0,G38+M38-AB38) -> 0 | AI38: =SUM(H38:M38) -> 0 | AJ38: =SUM(AC38:AH38) -> 0
A39: 35 | B39: =AC38 -> 0 | C39: =AD38 -> 0 | D39: =AE38 -> 0 | E39: =AF38 -> 0 | F39: =AG38 -> 0 | G39: =AH38 -> 0 | H39: =B39*N(Debts!C7)/12 -> 0 | I39: =C39*N(Debts!C8)/12 -> 0 | J39: =D39*N(Debts!C9)/12 -> 0 | K39: =E39*N(Debts!C10)/12 -> 0 | L39: =F39*N(Debts!C11)/12 -> 0 | M39: =G39*N(Debts!C12)/12 -> 0 | N39: =MIN(B39+H39,N(Debts!D7)) -> 0 | O39: =MIN(C39+I39,N(Debts!D8)) -> 0 | P39: =MIN(D39+J39,N(Debts!D9)) -> 0 | Q39: =MIN(E39+K39,N(Debts!D10)) -> 0 | R39: =MIN(F39+L39,N(Debts!D11)) -> 0 | S39: =MIN(G39+M39,N(Debts!D12)) -> 0 | T39: =Debts!$B$14 -> 286 | U39: =MAX(0,T39-SUM(N39:S39)) -> 286 | V39: =_xlfn.MINIFS($B$3:$G$3,B39:G39,">0.005") -> 0 | W39: =IF(B39<=0.005,0,MIN(B39+H39,N39+IF(B$3=$V39,$U39,0))) -> 0 | X39: =IF(C39<=0.005,0,MIN(C39+I39,O39+IF(C$3=$V39,$U39,0))) -> 0 | Y39: =IF(D39<=0.005,0,MIN(D39+J39,P39+IF(D$3=$V39,$U39,0))) -> 0 | Z39: =IF(E39<=0.005,0,MIN(E39+K39,Q39+IF(E$3=$V39,$U39,0))) -> 0 | AA39: =IF(F39<=0.005,0,MIN(F39+L39,R39+IF(F$3=$V39,$U39,0))) -> 0 | AB39: =IF(G39<=0.005,0,MIN(G39+M39,S39+IF(G$3=$V39,$U39,0))) -> 0 | AC39: =MAX(0,B39+H39-W39) -> 0 | AD39: =MAX(0,C39+I39-X39) -> 0 | AE39: =MAX(0,D39+J39-Y39) -> 0 | AF39: =MAX(0,E39+K39-Z39) -> 0 | AG39: =MAX(0,F39+L39-AA39) -> 0 | AH39: =MAX(0,G39+M39-AB39) -> 0 | AI39: =SUM(H39:M39) -> 0 | AJ39: =SUM(AC39:AH39) -> 0
A40: 36 | B40: =AC39 -> 0 | C40: =AD39 -> 0 | D40: =AE39 -> 0 | E40: =AF39 -> 0 | F40: =AG39 -> 0 | G40: =AH39 -> 0 | H40: =B40*N(Debts!C7)/12 -> 0 | I40: =C40*N(Debts!C8)/12 -> 0 | J40: =D40*N(Debts!C9)/12 -> 0 | K40: =E40*N(Debts!C10)/12 -> 0 | L40: =F40*N(Debts!C11)/12 -> 0 | M40: =G40*N(Debts!C12)/12 -> 0 | N40: =MIN(B40+H40,N(Debts!D7)) -> 0 | O40: =MIN(C40+I40,N(Debts!D8)) -> 0 | P40: =MIN(D40+J40,N(Debts!D9)) -> 0 | Q40: =MIN(E40+K40,N(Debts!D10)) -> 0 | R40: =MIN(F40+L40,N(Debts!D11)) -> 0 | S40: =MIN(G40+M40,N(Debts!D12)) -> 0 | T40: =Debts!$B$14 -> 286 | U40: =MAX(0,T40-SUM(N40:S40)) -> 286 | V40: =_xlfn.MINIFS($B$3:$G$3,B40:G40,">0.005") -> 0 | W40: =IF(B40<=0.005,0,MIN(B40+H40,N40+IF(B$3=$V40,$U40,0))) -> 0 | X40: =IF(C40<=0.005,0,MIN(C40+I40,O40+IF(C$3=$V40,$U40,0))) -> 0 | Y40: =IF(D40<=0.005,0,MIN(D40+J40,P40+IF(D$3=$V40,$U40,0))) -> 0 | Z40: =IF(E40<=0.005,0,MIN(E40+K40,Q40+IF(E$3=$V40,$U40,0))) -> 0 | AA40: =IF(F40<=0.005,0,MIN(F40+L40,R40+IF(F$3=$V40,$U40,0))) -> 0 | AB40: =IF(G40<=0.005,0,MIN(G40+M40,S40+IF(G$3=$V40,$U40,0))) -> 0 | AC40: =MAX(0,B40+H40-W40) -> 0 | AD40: =MAX(0,C40+I40-X40) -> 0 | AE40: =MAX(0,D40+J40-Y40) -> 0 | AF40: =MAX(0,E40+K40-Z40) -> 0 | AG40: =MAX(0,F40+L40-AA40) -> 0 | AH40: =MAX(0,G40+M40-AB40) -> 0 | AI40: =SUM(H40:M40) -> 0 | AJ40: =SUM(AC40:AH40) -> 0
A41: 37 | B41: =AC40 -> 0 | C41: =AD40 -> 0 | D41: =AE40 -> 0 | E41: =AF40 -> 0 | F41: =AG40 -> 0 | G41: =AH40 -> 0 | H41: =B41*N(Debts!C7)/12 -> 0 | I41: =C41*N(Debts!C8)/12 -> 0 | J41: =D41*N(Debts!C9)/12 -> 0 | K41: =E41*N(Debts!C10)/12 -> 0 | L41: =F41*N(Debts!C11)/12 -> 0 | M41: =G41*N(Debts!C12)/12 -> 0 | N41: =MIN(B41+H41,N(Debts!D7)) -> 0 | O41: =MIN(C41+I41,N(Debts!D8)) -> 0 | P41: =MIN(D41+J41,N(Debts!D9)) -> 0 | Q41: =MIN(E41+K41,N(Debts!D10)) -> 0 | R41: =MIN(F41+L41,N(Debts!D11)) -> 0 | S41: =MIN(G41+M41,N(Debts!D12)) -> 0 | T41: =Debts!$B$14 -> 286 | U41: =MAX(0,T41-SUM(N41:S41)) -> 286 | V41: =_xlfn.MINIFS($B$3:$G$3,B41:G41,">0.005") -> 0 | W41: =IF(B41<=0.005,0,MIN(B41+H41,N41+IF(B$3=$V41,$U41,0))) -> 0 | X41: =IF(C41<=0.005,0,MIN(C41+I41,O41+IF(C$3=$V41,$U41,0))) -> 0 | Y41: =IF(D41<=0.005,0,MIN(D41+J41,P41+IF(D$3=$V41,$U41,0))) -> 0 | Z41: =IF(E41<=0.005,0,MIN(E41+K41,Q41+IF(E$3=$V41,$U41,0))) -> 0 | AA41: =IF(F41<=0.005,0,MIN(F41+L41,R41+IF(F$3=$V41,$U41,0))) -> 0 | AB41: =IF(G41<=0.005,0,MIN(G41+M41,S41+IF(G$3=$V41,$U41,0))) -> 0 | AC41: =MAX(0,B41+H41-W41) -> 0 | AD41: =MAX(0,C41+I41-X41) -> 0 | AE41: =MAX(0,D41+J41-Y41) -> 0 | AF41: =MAX(0,E41+K41-Z41) -> 0 | AG41: =MAX(0,F41+L41-AA41) -> 0 | AH41: =MAX(0,G41+M41-AB41) -> 0 | AI41: =SUM(H41:M41) -> 0 | AJ41: =SUM(AC41:AH41) -> 0
A42: 38 | B42: =AC41 -> 0 | C42: =AD41 -> 0 | D42: =AE41 -> 0 | E42: =AF41 -> 0 | F42: =AG41 -> 0 | G42: =AH41 -> 0 | H42: =B42*N(Debts!C7)/12 -> 0 | I42: =C42*N(Debts!C8)/12 -> 0 | J42: =D42*N(Debts!C9)/12 -> 0 | K42: =E42*N(Debts!C10)/12 -> 0 | L42: =F42*N(Debts!C11)/12 -> 0 | M42: =G42*N(Debts!C12)/12 -> 0 | N42: =MIN(B42+H42,N(Debts!D7)) -> 0 | O42: =MIN(C42+I42,N(Debts!D8)) -> 0 | P42: =MIN(D42+J42,N(Debts!D9)) -> 0 | Q42: =MIN(E42+K42,N(Debts!D10)) -> 0 | R42: =MIN(F42+L42,N(Debts!D11)) -> 0 | S42: =MIN(G42+M42,N(Debts!D12)) -> 0 | T42: =Debts!$B$14 -> 286 | U42: =MAX(0,T42-SUM(N42:S42)) -> 286 | V42: =_xlfn.MINIFS($B$3:$G$3,B42:G42,">0.005") -> 0 | W42: =IF(B42<=0.005,0,MIN(B42+H42,N42+IF(B$3=$V42,$U42,0))) -> 0 | X42: =IF(C42<=0.005,0,MIN(C42+I42,O42+IF(C$3=$V42,$U42,0))) -> 0 | Y42: =IF(D42<=0.005,0,MIN(D42+J42,P42+IF(D$3=$V42,$U42,0))) -> 0 | Z42: =IF(E42<=0.005,0,MIN(E42+K42,Q42+IF(E$3=$V42,$U42,0))) -> 0 | AA42: =IF(F42<=0.005,0,MIN(F42+L42,R42+IF(F$3=$V42,$U42,0))) -> 0 | AB42: =IF(G42<=0.005,0,MIN(G42+M42,S42+IF(G$3=$V42,$U42,0))) -> 0 | AC42: =MAX(0,B42+H42-W42) -> 0 | AD42: =MAX(0,C42+I42-X42) -> 0 | AE42: =MAX(0,D42+J42-Y42) -> 0 | AF42: =MAX(0,E42+K42-Z42) -> 0 | AG42: =MAX(0,F42+L42-AA42) -> 0 | AH42: =MAX(0,G42+M42-AB42) -> 0 | AI42: =SUM(H42:M42) -> 0 | AJ42: =SUM(AC42:AH42) -> 0
A43: 39 | B43: =AC42 -> 0 | C43: =AD42 -> 0 | D43: =AE42 -> 0 | E43: =AF42 -> 0 | F43: =AG42 -> 0 | G43: =AH42 -> 0 | H43: =B43*N(Debts!C7)/12 -> 0 | I43: =C43*N(Debts!C8)/12 -> 0 | J43: =D43*N(Debts!C9)/12 -> 0 | K43: =E43*N(Debts!C10)/12 -> 0 | L43: =F43*N(Debts!C11)/12 -> 0 | M43: =G43*N(Debts!C12)/12 -> 0 | N43: =MIN(B43+H43,N(Debts!D7)) -> 0 | O43: =MIN(C43+I43,N(Debts!D8)) -> 0 | P43: =MIN(D43+J43,N(Debts!D9)) -> 0 | Q43: =MIN(E43+K43,N(Debts!D10)) -> 0 | R43: =MIN(F43+L43,N(Debts!D11)) -> 0 | S43: =MIN(G43+M43,N(Debts!D12)) -> 0 | T43: =Debts!$B$14 -> 286 | U43: =MAX(0,T43-SUM(N43:S43)) -> 286 | V43: =_xlfn.MINIFS($B$3:$G$3,B43:G43,">0.005") -> 0 | W43: =IF(B43<=0.005,0,MIN(B43+H43,N43+IF(B$3=$V43,$U43,0))) -> 0 | X43: =IF(C43<=0.005,0,MIN(C43+I43,O43+IF(C$3=$V43,$U43,0))) -> 0 | Y43: =IF(D43<=0.005,0,MIN(D43+J43,P43+IF(D$3=$V43,$U43,0))) -> 0 | Z43: =IF(E43<=0.005,0,MIN(E43+K43,Q43+IF(E$3=$V43,$U43,0))) -> 0 | AA43: =IF(F43<=0.005,0,MIN(F43+L43,R43+IF(F$3=$V43,$U43,0))) -> 0 | AB43: =IF(G43<=0.005,0,MIN(G43+M43,S43+IF(G$3=$V43,$U43,0))) -> 0 | AC43: =MAX(0,B43+H43-W43) -> 0 | AD43: =MAX(0,C43+I43-X43) -> 0 | AE43: =MAX(0,D43+J43-Y43) -> 0 | AF43: =MAX(0,E43+K43-Z43) -> 0 | AG43: =MAX(0,F43+L43-AA43) -> 0 | AH43: =MAX(0,G43+M43-AB43) -> 0 | AI43: =SUM(H43:M43) -> 0 | AJ43: =SUM(AC43:AH43) -> 0
A44: 40 | B44: =AC43 -> 0 | C44: =AD43 -> 0 | D44: =AE43 -> 0 | E44: =AF43 -> 0 | F44: =AG43 -> 0 | G44: =AH43 -> 0 | H44: =B44*N(Debts!C7)/12 -> 0 | I44: =C44*N(Debts!C8)/12 -> 0 | J44: =D44*N(Debts!C9)/12 -> 0 | K44: =E44*N(Debts!C10)/12 -> 0 | L44: =F44*N(Debts!C11)/12 -> 0 | M44: =G44*N(Debts!C12)/12 -> 0 | N44: =MIN(B44+H44,N(Debts!D7)) -> 0 | O44: =MIN(C44+I44,N(Debts!D8)) -> 0 | P44: =MIN(D44+J44,N(Debts!D9)) -> 0 | Q44: =MIN(E44+K44,N(Debts!D10)) -> 0 | R44: =MIN(F44+L44,N(Debts!D11)) -> 0 | S44: =MIN(G44+M44,N(Debts!D12)) -> 0 | T44: =Debts!$B$14 -> 286 | U44: =MAX(0,T44-SUM(N44:S44)) -> 286 | V44: =_xlfn.MINIFS($B$3:$G$3,B44:G44,">0.005") -> 0 | W44: =IF(B44<=0.005,0,MIN(B44+H44,N44+IF(B$3=$V44,$U44,0))) -> 0 | X44: =IF(C44<=0.005,0,MIN(C44+I44,O44+IF(C$3=$V44,$U44,0))) -> 0 | Y44: =IF(D44<=0.005,0,MIN(D44+J44,P44+IF(D$3=$V44,$U44,0))) -> 0 | Z44: =IF(E44<=0.005,0,MIN(E44+K44,Q44+IF(E$3=$V44,$U44,0))) -> 0 | AA44: =IF(F44<=0.005,0,MIN(F44+L44,R44+IF(F$3=$V44,$U44,0))) -> 0 | AB44: =IF(G44<=0.005,0,MIN(G44+M44,S44+IF(G$3=$V44,$U44,0))) -> 0 | AC44: =MAX(0,B44+H44-W44) -> 0 | AD44: =MAX(0,C44+I44-X44) -> 0 | AE44: =MAX(0,D44+J44-Y44) -> 0 | AF44: =MAX(0,E44+K44-Z44) -> 0 | AG44: =MAX(0,F44+L44-AA44) -> 0 | AH44: =MAX(0,G44+M44-AB44) -> 0 | AI44: =SUM(H44:M44) -> 0 | AJ44: =SUM(AC44:AH44) -> 0
A45: 41 | B45: =AC44 -> 0 | C45: =AD44 -> 0 | D45: =AE44 -> 0 | E45: =AF44 -> 0 | F45: =AG44 -> 0 | G45: =AH44 -> 0 | H45: =B45*N(Debts!C7)/12 -> 0 | I45: =C45*N(Debts!C8)/12 -> 0 | J45: =D45*N(Debts!C9)/12 -> 0 | K45: =E45*N(Debts!C10)/12 -> 0 | L45: =F45*N(Debts!C11)/12 -> 0 | M45: =G45*N(Debts!C12)/12 -> 0 | N45: =MIN(B45+H45,N(Debts!D7)) -> 0 | O45: =MIN(C45+I45,N(Debts!D8)) -> 0 | P45: =MIN(D45+J45,N(Debts!D9)) -> 0 | Q45: =MIN(E45+K45,N(Debts!D10)) -> 0 | R45: =MIN(F45+L45,N(Debts!D11)) -> 0 | S45: =MIN(G45+M45,N(Debts!D12)) -> 0 | T45: =Debts!$B$14 -> 286 | U45: =MAX(0,T45-SUM(N45:S45)) -> 286 | V45: =_xlfn.MINIFS($B$3:$G$3,B45:G45,">0.005") -> 0 | W45: =IF(B45<=0.005,0,MIN(B45+H45,N45+IF(B$3=$V45,$U45,0))) -> 0 | X45: =IF(C45<=0.005,0,MIN(C45+I45,O45+IF(C$3=$V45,$U45,0))) -> 0 | Y45: =IF(D45<=0.005,0,MIN(D45+J45,P45+IF(D$3=$V45,$U45,0))) -> 0 | Z45: =IF(E45<=0.005,0,MIN(E45+K45,Q45+IF(E$3=$V45,$U45,0))) -> 0 | AA45: =IF(F45<=0.005,0,MIN(F45+L45,R45+IF(F$3=$V45,$U45,0))) -> 0 | AB45: =IF(G45<=0.005,0,MIN(G45+M45,S45+IF(G$3=$V45,$U45,0))) -> 0 | AC45: =MAX(0,B45+H45-W45) -> 0 | AD45: =MAX(0,C45+I45-X45) -> 0 | AE45: =MAX(0,D45+J45-Y45) -> 0 | AF45: =MAX(0,E45+K45-Z45) -> 0 | AG45: =MAX(0,F45+L45-AA45) -> 0 | AH45: =MAX(0,G45+M45-AB45) -> 0 | AI45: =SUM(H45:M45) -> 0 | AJ45: =SUM(AC45:AH45) -> 0
A46: 42 | B46: =AC45 -> 0 | C46: =AD45 -> 0 | D46: =AE45 -> 0 | E46: =AF45 -> 0 | F46: =AG45 -> 0 | G46: =AH45 -> 0 | H46: =B46*N(Debts!C7)/12 -> 0 | I46: =C46*N(Debts!C8)/12 -> 0 | J46: =D46*N(Debts!C9)/12 -> 0 | K46: =E46*N(Debts!C10)/12 -> 0 | L46: =F46*N(Debts!C11)/12 -> 0 | M46: =G46*N(Debts!C12)/12 -> 0 | N46: =MIN(B46+H46,N(Debts!D7)) -> 0 | O46: =MIN(C46+I46,N(Debts!D8)) -> 0 | P46: =MIN(D46+J46,N(Debts!D9)) -> 0 | Q46: =MIN(E46+K46,N(Debts!D10)) -> 0 | R46: =MIN(F46+L46,N(Debts!D11)) -> 0 | S46: =MIN(G46+M46,N(Debts!D12)) -> 0 | T46: =Debts!$B$14 -> 286 | U46: =MAX(0,T46-SUM(N46:S46)) -> 286 | V46: =_xlfn.MINIFS($B$3:$G$3,B46:G46,">0.005") -> 0 | W46: =IF(B46<=0.005,0,MIN(B46+H46,N46+IF(B$3=$V46,$U46,0))) -> 0 | X46: =IF(C46<=0.005,0,MIN(C46+I46,O46+IF(C$3=$V46,$U46,0))) -> 0 | Y46: =IF(D46<=0.005,0,MIN(D46+J46,P46+IF(D$3=$V46,$U46,0))) -> 0 | Z46: =IF(E46<=0.005,0,MIN(E46+K46,Q46+IF(E$3=$V46,$U46,0))) -> 0 | AA46: =IF(F46<=0.005,0,MIN(F46+L46,R46+IF(F$3=$V46,$U46,0))) -> 0 | AB46: =IF(G46<=0.005,0,MIN(G46+M46,S46+IF(G$3=$V46,$U46,0))) -> 0 | AC46: =MAX(0,B46+H46-W46) -> 0 | AD46: =MAX(0,C46+I46-X46) -> 0 | AE46: =MAX(0,D46+J46-Y46) -> 0 | AF46: =MAX(0,E46+K46-Z46) -> 0 | AG46: =MAX(0,F46+L46-AA46) -> 0 | AH46: =MAX(0,G46+M46-AB46) -> 0 | AI46: =SUM(H46:M46) -> 0 | AJ46: =SUM(AC46:AH46) -> 0
A47: 43 | B47: =AC46 -> 0 | C47: =AD46 -> 0 | D47: =AE46 -> 0 | E47: =AF46 -> 0 | F47: =AG46 -> 0 | G47: =AH46 -> 0 | H47: =B47*N(Debts!C7)/12 -> 0 | I47: =C47*N(Debts!C8)/12 -> 0 | J47: =D47*N(Debts!C9)/12 -> 0 | K47: =E47*N(Debts!C10)/12 -> 0 | L47: =F47*N(Debts!C11)/12 -> 0 | M47: =G47*N(Debts!C12)/12 -> 0 | N47: =MIN(B47+H47,N(Debts!D7)) -> 0 | O47: =MIN(C47+I47,N(Debts!D8)) -> 0 | P47: =MIN(D47+J47,N(Debts!D9)) -> 0 | Q47: =MIN(E47+K47,N(Debts!D10)) -> 0 | R47: =MIN(F47+L47,N(Debts!D11)) -> 0 | S47: =MIN(G47+M47,N(Debts!D12)) -> 0 | T47: =Debts!$B$14 -> 286 | U47: =MAX(0,T47-SUM(N47:S47)) -> 286 | V47: =_xlfn.MINIFS($B$3:$G$3,B47:G47,">0.005") -> 0 | W47: =IF(B47<=0.005,0,MIN(B47+H47,N47+IF(B$3=$V47,$U47,0))) -> 0 | X47: =IF(C47<=0.005,0,MIN(C47+I47,O47+IF(C$3=$V47,$U47,0))) -> 0 | Y47: =IF(D47<=0.005,0,MIN(D47+J47,P47+IF(D$3=$V47,$U47,0))) -> 0 | Z47: =IF(E47<=0.005,0,MIN(E47+K47,Q47+IF(E$3=$V47,$U47,0))) -> 0 | AA47: =IF(F47<=0.005,0,MIN(F47+L47,R47+IF(F$3=$V47,$U47,0))) -> 0 | AB47: =IF(G47<=0.005,0,MIN(G47+M47,S47+IF(G$3=$V47,$U47,0))) -> 0 | AC47: =MAX(0,B47+H47-W47) -> 0 | AD47: =MAX(0,C47+I47-X47) -> 0 | AE47: =MAX(0,D47+J47-Y47) -> 0 | AF47: =MAX(0,E47+K47-Z47) -> 0 | AG47: =MAX(0,F47+L47-AA47) -> 0 | AH47: =MAX(0,G47+M47-AB47) -> 0 | AI47: =SUM(H47:M47) -> 0 | AJ47: =SUM(AC47:AH47) -> 0
A48: 44 | B48: =AC47 -> 0 | C48: =AD47 -> 0 | D48: =AE47 -> 0 | E48: =AF47 -> 0 | F48: =AG47 -> 0 | G48: =AH47 -> 0 | H48: =B48*N(Debts!C7)/12 -> 0 | I48: =C48*N(Debts!C8)/12 -> 0 | J48: =D48*N(Debts!C9)/12 -> 0 | K48: =E48*N(Debts!C10)/12 -> 0 | L48: =F48*N(Debts!C11)/12 -> 0 | M48: =G48*N(Debts!C12)/12 -> 0 | N48: =MIN(B48+H48,N(Debts!D7)) -> 0 | O48: =MIN(C48+I48,N(Debts!D8)) -> 0 | P48: =MIN(D48+J48,N(Debts!D9)) -> 0 | Q48: =MIN(E48+K48,N(Debts!D10)) -> 0 | R48: =MIN(F48+L48,N(Debts!D11)) -> 0 | S48: =MIN(G48+M48,N(Debts!D12)) -> 0 | T48: =Debts!$B$14 -> 286 | U48: =MAX(0,T48-SUM(N48:S48)) -> 286 | V48: =_xlfn.MINIFS($B$3:$G$3,B48:G48,">0.005") -> 0 | W48: =IF(B48<=0.005,0,MIN(B48+H48,N48+IF(B$3=$V48,$U48,0))) -> 0 | X48: =IF(C48<=0.005,0,MIN(C48+I48,O48+IF(C$3=$V48,$U48,0))) -> 0 | Y48: =IF(D48<=0.005,0,MIN(D48+J48,P48+IF(D$3=$V48,$U48,0))) -> 0 | Z48: =IF(E48<=0.005,0,MIN(E48+K48,Q48+IF(E$3=$V48,$U48,0))) -> 0 | AA48: =IF(F48<=0.005,0,MIN(F48+L48,R48+IF(F$3=$V48,$U48,0))) -> 0 | AB48: =IF(G48<=0.005,0,MIN(G48+M48,S48+IF(G$3=$V48,$U48,0))) -> 0 | AC48: =MAX(0,B48+H48-W48) -> 0 | AD48: =MAX(0,C48+I48-X48) -> 0 | AE48: =MAX(0,D48+J48-Y48) -> 0 | AF48: =MAX(0,E48+K48-Z48) -> 0 | AG48: =MAX(0,F48+L48-AA48) -> 0 | AH48: =MAX(0,G48+M48-AB48) -> 0 | AI48: =SUM(H48:M48) -> 0 | AJ48: =SUM(AC48:AH48) -> 0
A49: 45 | B49: =AC48 -> 0 | C49: =AD48 -> 0 | D49: =AE48 -> 0 | E49: =AF48 -> 0 | F49: =AG48 -> 0 | G49: =AH48 -> 0 | H49: =B49*N(Debts!C7)/12 -> 0 | I49: =C49*N(Debts!C8)/12 -> 0 | J49: =D49*N(Debts!C9)/12 -> 0 | K49: =E49*N(Debts!C10)/12 -> 0 | L49: =F49*N(Debts!C11)/12 -> 0 | M49: =G49*N(Debts!C12)/12 -> 0 | N49: =MIN(B49+H49,N(Debts!D7)) -> 0 | O49: =MIN(C49+I49,N(Debts!D8)) -> 0 | P49: =MIN(D49+J49,N(Debts!D9)) -> 0 | Q49: =MIN(E49+K49,N(Debts!D10)) -> 0 | R49: =MIN(F49+L49,N(Debts!D11)) -> 0 | S49: =MIN(G49+M49,N(Debts!D12)) -> 0 | T49: =Debts!$B$14 -> 286 | U49: =MAX(0,T49-SUM(N49:S49)) -> 286 | V49: =_xlfn.MINIFS($B$3:$G$3,B49:G49,">0.005") -> 0 | W49: =IF(B49<=0.005,0,MIN(B49+H49,N49+IF(B$3=$V49,$U49,0))) -> 0 | X49: =IF(C49<=0.005,0,MIN(C49+I49,O49+IF(C$3=$V49,$U49,0))) -> 0 | Y49: =IF(D49<=0.005,0,MIN(D49+J49,P49+IF(D$3=$V49,$U49,0))) -> 0 | Z49: =IF(E49<=0.005,0,MIN(E49+K49,Q49+IF(E$3=$V49,$U49,0))) -> 0 | AA49: =IF(F49<=0.005,0,MIN(F49+L49,R49+IF(F$3=$V49,$U49,0))) -> 0 | AB49: =IF(G49<=0.005,0,MIN(G49+M49,S49+IF(G$3=$V49,$U49,0))) -> 0 | AC49: =MAX(0,B49+H49-W49) -> 0 | AD49: =MAX(0,C49+I49-X49) -> 0 | AE49: =MAX(0,D49+J49-Y49) -> 0 | AF49: =MAX(0,E49+K49-Z49) -> 0 | AG49: =MAX(0,F49+L49-AA49) -> 0 | AH49: =MAX(0,G49+M49-AB49) -> 0 | AI49: =SUM(H49:M49) -> 0 | AJ49: =SUM(AC49:AH49) -> 0
A50: 46 | B50: =AC49 -> 0 | C50: =AD49 -> 0 | D50: =AE49 -> 0 | E50: =AF49 -> 0 | F50: =AG49 -> 0 | G50: =AH49 -> 0 | H50: =B50*N(Debts!C7)/12 -> 0 | I50: =C50*N(Debts!C8)/12 -> 0 | J50: =D50*N(Debts!C9)/12 -> 0 | K50: =E50*N(Debts!C10)/12 -> 0 | L50: =F50*N(Debts!C11)/12 -> 0 | M50: =G50*N(Debts!C12)/12 -> 0 | N50: =MIN(B50+H50,N(Debts!D7)) -> 0 | O50: =MIN(C50+I50,N(Debts!D8)) -> 0 | P50: =MIN(D50+J50,N(Debts!D9)) -> 0 | Q50: =MIN(E50+K50,N(Debts!D10)) -> 0 | R50: =MIN(F50+L50,N(Debts!D11)) -> 0 | S50: =MIN(G50+M50,N(Debts!D12)) -> 0 | T50: =Debts!$B$14 -> 286 | U50: =MAX(0,T50-SUM(N50:S50)) -> 286 | V50: =_xlfn.MINIFS($B$3:$G$3,B50:G50,">0.005") -> 0 | W50: =IF(B50<=0.005,0,MIN(B50+H50,N50+IF(B$3=$V50,$U50,0))) -> 0 | X50: =IF(C50<=0.005,0,MIN(C50+I50,O50+IF(C$3=$V50,$U50,0))) -> 0 | Y50: =IF(D50<=0.005,0,MIN(D50+J50,P50+IF(D$3=$V50,$U50,0))) -> 0 | Z50: =IF(E50<=0.005,0,MIN(E50+K50,Q50+IF(E$3=$V50,$U50,0))) -> 0 | AA50: =IF(F50<=0.005,0,MIN(F50+L50,R50+IF(F$3=$V50,$U50,0))) -> 0 | AB50: =IF(G50<=0.005,0,MIN(G50+M50,S50+IF(G$3=$V50,$U50,0))) -> 0 | AC50: =MAX(0,B50+H50-W50) -> 0 | AD50: =MAX(0,C50+I50-X50) -> 0 | AE50: =MAX(0,D50+J50-Y50) -> 0 | AF50: =MAX(0,E50+K50-Z50) -> 0 | AG50: =MAX(0,F50+L50-AA50) -> 0 | AH50: =MAX(0,G50+M50-AB50) -> 0 | AI50: =SUM(H50:M50) -> 0 | AJ50: =SUM(AC50:AH50) -> 0
A51: 47 | B51: =AC50 -> 0 | C51: =AD50 -> 0 | D51: =AE50 -> 0 | E51: =AF50 -> 0 | F51: =AG50 -> 0 | G51: =AH50 -> 0 | H51: =B51*N(Debts!C7)/12 -> 0 | I51: =C51*N(Debts!C8)/12 -> 0 | J51: =D51*N(Debts!C9)/12 -> 0 | K51: =E51*N(Debts!C10)/12 -> 0 | L51: =F51*N(Debts!C11)/12 -> 0 | M51: =G51*N(Debts!C12)/12 -> 0 | N51: =MIN(B51+H51,N(Debts!D7)) -> 0 | O51: =MIN(C51+I51,N(Debts!D8)) -> 0 | P51: =MIN(D51+J51,N(Debts!D9)) -> 0 | Q51: =MIN(E51+K51,N(Debts!D10)) -> 0 | R51: =MIN(F51+L51,N(Debts!D11)) -> 0 | S51: =MIN(G51+M51,N(Debts!D12)) -> 0 | T51: =Debts!$B$14 -> 286 | U51: =MAX(0,T51-SUM(N51:S51)) -> 286 | V51: =_xlfn.MINIFS($B$3:$G$3,B51:G51,">0.005") -> 0 | W51: =IF(B51<=0.005,0,MIN(B51+H51,N51+IF(B$3=$V51,$U51,0))) -> 0 | X51: =IF(C51<=0.005,0,MIN(C51+I51,O51+IF(C$3=$V51,$U51,0))) -> 0 | Y51: =IF(D51<=0.005,0,MIN(D51+J51,P51+IF(D$3=$V51,$U51,0))) -> 0 | Z51: =IF(E51<=0.005,0,MIN(E51+K51,Q51+IF(E$3=$V51,$U51,0))) -> 0 | AA51: =IF(F51<=0.005,0,MIN(F51+L51,R51+IF(F$3=$V51,$U51,0))) -> 0 | AB51: =IF(G51<=0.005,0,MIN(G51+M51,S51+IF(G$3=$V51,$U51,0))) -> 0 | AC51: =MAX(0,B51+H51-W51) -> 0 | AD51: =MAX(0,C51+I51-X51) -> 0 | AE51: =MAX(0,D51+J51-Y51) -> 0 | AF51: =MAX(0,E51+K51-Z51) -> 0 | AG51: =MAX(0,F51+L51-AA51) -> 0 | AH51: =MAX(0,G51+M51-AB51) -> 0 | AI51: =SUM(H51:M51) -> 0 | AJ51: =SUM(AC51:AH51) -> 0
A52: 48 | B52: =AC51 -> 0 | C52: =AD51 -> 0 | D52: =AE51 -> 0 | E52: =AF51 -> 0 | F52: =AG51 -> 0 | G52: =AH51 -> 0 | H52: =B52*N(Debts!C7)/12 -> 0 | I52: =C52*N(Debts!C8)/12 -> 0 | J52: =D52*N(Debts!C9)/12 -> 0 | K52: =E52*N(Debts!C10)/12 -> 0 | L52: =F52*N(Debts!C11)/12 -> 0 | M52: =G52*N(Debts!C12)/12 -> 0 | N52: =MIN(B52+H52,N(Debts!D7)) -> 0 | O52: =MIN(C52+I52,N(Debts!D8)) -> 0 | P52: =MIN(D52+J52,N(Debts!D9)) -> 0 | Q52: =MIN(E52+K52,N(Debts!D10)) -> 0 | R52: =MIN(F52+L52,N(Debts!D11)) -> 0 | S52: =MIN(G52+M52,N(Debts!D12)) -> 0 | T52: =Debts!$B$14 -> 286 | U52: =MAX(0,T52-SUM(N52:S52)) -> 286 | V52: =_xlfn.MINIFS($B$3:$G$3,B52:G52,">0.005") -> 0 | W52: =IF(B52<=0.005,0,MIN(B52+H52,N52+IF(B$3=$V52,$U52,0))) -> 0 | X52: =IF(C52<=0.005,0,MIN(C52+I52,O52+IF(C$3=$V52,$U52,0))) -> 0 | Y52: =IF(D52<=0.005,0,MIN(D52+J52,P52+IF(D$3=$V52,$U52,0))) -> 0 | Z52: =IF(E52<=0.005,0,MIN(E52+K52,Q52+IF(E$3=$V52,$U52,0))) -> 0 | AA52: =IF(F52<=0.005,0,MIN(F52+L52,R52+IF(F$3=$V52,$U52,0))) -> 0 | AB52: =IF(G52<=0.005,0,MIN(G52+M52,S52+IF(G$3=$V52,$U52,0))) -> 0 | AC52: =MAX(0,B52+H52-W52) -> 0 | AD52: =MAX(0,C52+I52-X52) -> 0 | AE52: =MAX(0,D52+J52-Y52) -> 0 | AF52: =MAX(0,E52+K52-Z52) -> 0 | AG52: =MAX(0,F52+L52-AA52) -> 0 | AH52: =MAX(0,G52+M52-AB52) -> 0 | AI52: =SUM(H52:M52) -> 0 | AJ52: =SUM(AC52:AH52) -> 0
A53: 49 | B53: =AC52 -> 0 | C53: =AD52 -> 0 | D53: =AE52 -> 0 | E53: =AF52 -> 0 | F53: =AG52 -> 0 | G53: =AH52 -> 0 | H53: =B53*N(Debts!C7)/12 -> 0 | I53: =C53*N(Debts!C8)/12 -> 0 | J53: =D53*N(Debts!C9)/12 -> 0 | K53: =E53*N(Debts!C10)/12 -> 0 | L53: =F53*N(Debts!C11)/12 -> 0 | M53: =G53*N(Debts!C12)/12 -> 0 | N53: =MIN(B53+H53,N(Debts!D7)) -> 0 | O53: =MIN(C53+I53,N(Debts!D8)) -> 0 | P53: =MIN(D53+J53,N(Debts!D9)) -> 0 | Q53: =MIN(E53+K53,N(Debts!D10)) -> 0 | R53: =MIN(F53+L53,N(Debts!D11)) -> 0 | S53: =MIN(G53+M53,N(Debts!D12)) -> 0 | T53: =Debts!$B$14 -> 286 | U53: =MAX(0,T53-SUM(N53:S53)) -> 286 | V53: =_xlfn.MINIFS($B$3:$G$3,B53:G53,">0.005") -> 0 | W53: =IF(B53<=0.005,0,MIN(B53+H53,N53+IF(B$3=$V53,$U53,0))) -> 0 | X53: =IF(C53<=0.005,0,MIN(C53+I53,O53+IF(C$3=$V53,$U53,0))) -> 0 | Y53: =IF(D53<=0.005,0,MIN(D53+J53,P53+IF(D$3=$V53,$U53,0))) -> 0 | Z53: =IF(E53<=0.005,0,MIN(E53+K53,Q53+IF(E$3=$V53,$U53,0))) -> 0 | AA53: =IF(F53<=0.005,0,MIN(F53+L53,R53+IF(F$3=$V53,$U53,0))) -> 0 | AB53: =IF(G53<=0.005,0,MIN(G53+M53,S53+IF(G$3=$V53,$U53,0))) -> 0 | AC53: =MAX(0,B53+H53-W53) -> 0 | AD53: =MAX(0,C53+I53-X53) -> 0 | AE53: =MAX(0,D53+J53-Y53) -> 0 | AF53: =MAX(0,E53+K53-Z53) -> 0 | AG53: =MAX(0,F53+L53-AA53) -> 0 | AH53: =MAX(0,G53+M53-AB53) -> 0 | AI53: =SUM(H53:M53) -> 0 | AJ53: =SUM(AC53:AH53) -> 0
A54: 50 | B54: =AC53 -> 0 | C54: =AD53 -> 0 | D54: =AE53 -> 0 | E54: =AF53 -> 0 | F54: =AG53 -> 0 | G54: =AH53 -> 0 | H54: =B54*N(Debts!C7)/12 -> 0 | I54: =C54*N(Debts!C8)/12 -> 0 | J54: =D54*N(Debts!C9)/12 -> 0 | K54: =E54*N(Debts!C10)/12 -> 0 | L54: =F54*N(Debts!C11)/12 -> 0 | M54: =G54*N(Debts!C12)/12 -> 0 | N54: =MIN(B54+H54,N(Debts!D7)) -> 0 | O54: =MIN(C54+I54,N(Debts!D8)) -> 0 | P54: =MIN(D54+J54,N(Debts!D9)) -> 0 | Q54: =MIN(E54+K54,N(Debts!D10)) -> 0 | R54: =MIN(F54+L54,N(Debts!D11)) -> 0 | S54: =MIN(G54+M54,N(Debts!D12)) -> 0 | T54: =Debts!$B$14 -> 286 | U54: =MAX(0,T54-SUM(N54:S54)) -> 286 | V54: =_xlfn.MINIFS($B$3:$G$3,B54:G54,">0.005") -> 0 | W54: =IF(B54<=0.005,0,MIN(B54+H54,N54+IF(B$3=$V54,$U54,0))) -> 0 | X54: =IF(C54<=0.005,0,MIN(C54+I54,O54+IF(C$3=$V54,$U54,0))) -> 0 | Y54: =IF(D54<=0.005,0,MIN(D54+J54,P54+IF(D$3=$V54,$U54,0))) -> 0 | Z54: =IF(E54<=0.005,0,MIN(E54+K54,Q54+IF(E$3=$V54,$U54,0))) -> 0 | AA54: =IF(F54<=0.005,0,MIN(F54+L54,R54+IF(F$3=$V54,$U54,0))) -> 0 | AB54: =IF(G54<=0.005,0,MIN(G54+M54,S54+IF(G$3=$V54,$U54,0))) -> 0 | AC54: =MAX(0,B54+H54-W54) -> 0 | AD54: =MAX(0,C54+I54-X54) -> 0 | AE54: =MAX(0,D54+J54-Y54) -> 0 | AF54: =MAX(0,E54+K54-Z54) -> 0 | AG54: =MAX(0,F54+L54-AA54) -> 0 | AH54: =MAX(0,G54+M54-AB54) -> 0 | AI54: =SUM(H54:M54) -> 0 | AJ54: =SUM(AC54:AH54) -> 0
A55: 51 | B55: =AC54 -> 0 | C55: =AD54 -> 0 | D55: =AE54 -> 0 | E55: =AF54 -> 0 | F55: =AG54 -> 0 | G55: =AH54 -> 0 | H55: =B55*N(Debts!C7)/12 -> 0 | I55: =C55*N(Debts!C8)/12 -> 0 | J55: =D55*N(Debts!C9)/12 -> 0 | K55: =E55*N(Debts!C10)/12 -> 0 | L55: =F55*N(Debts!C11)/12 -> 0 | M55: =G55*N(Debts!C12)/12 -> 0 | N55: =MIN(B55+H55,N(Debts!D7)) -> 0 | O55: =MIN(C55+I55,N(Debts!D8)) -> 0 | P55: =MIN(D55+J55,N(Debts!D9)) -> 0 | Q55: =MIN(E55+K55,N(Debts!D10)) -> 0 | R55: =MIN(F55+L55,N(Debts!D11)) -> 0 | S55: =MIN(G55+M55,N(Debts!D12)) -> 0 | T55: =Debts!$B$14 -> 286 | U55: =MAX(0,T55-SUM(N55:S55)) -> 286 | V55: =_xlfn.MINIFS($B$3:$G$3,B55:G55,">0.005") -> 0 | W55: =IF(B55<=0.005,0,MIN(B55+H55,N55+IF(B$3=$V55,$U55,0))) -> 0 | X55: =IF(C55<=0.005,0,MIN(C55+I55,O55+IF(C$3=$V55,$U55,0))) -> 0 | Y55: =IF(D55<=0.005,0,MIN(D55+J55,P55+IF(D$3=$V55,$U55,0))) -> 0 | Z55: =IF(E55<=0.005,0,MIN(E55+K55,Q55+IF(E$3=$V55,$U55,0))) -> 0 | AA55: =IF(F55<=0.005,0,MIN(F55+L55,R55+IF(F$3=$V55,$U55,0))) -> 0 | AB55: =IF(G55<=0.005,0,MIN(G55+M55,S55+IF(G$3=$V55,$U55,0))) -> 0 | AC55: =MAX(0,B55+H55-W55) -> 0 | AD55: =MAX(0,C55+I55-X55) -> 0 | AE55: =MAX(0,D55+J55-Y55) -> 0 | AF55: =MAX(0,E55+K55-Z55) -> 0 | AG55: =MAX(0,F55+L55-AA55) -> 0 | AH55: =MAX(0,G55+M55-AB55) -> 0 | AI55: =SUM(H55:M55) -> 0 | AJ55: =SUM(AC55:AH55) -> 0
A56: 52 | B56: =AC55 -> 0 | C56: =AD55 -> 0 | D56: =AE55 -> 0 | E56: =AF55 -> 0 | F56: =AG55 -> 0 | G56: =AH55 -> 0 | H56: =B56*N(Debts!C7)/12 -> 0 | I56: =C56*N(Debts!C8)/12 -> 0 | J56: =D56*N(Debts!C9)/12 -> 0 | K56: =E56*N(Debts!C10)/12 -> 0 | L56: =F56*N(Debts!C11)/12 -> 0 | M56: =G56*N(Debts!C12)/12 -> 0 | N56: =MIN(B56+H56,N(Debts!D7)) -> 0 | O56: =MIN(C56+I56,N(Debts!D8)) -> 0 | P56: =MIN(D56+J56,N(Debts!D9)) -> 0 | Q56: =MIN(E56+K56,N(Debts!D10)) -> 0 | R56: =MIN(F56+L56,N(Debts!D11)) -> 0 | S56: =MIN(G56+M56,N(Debts!D12)) -> 0 | T56: =Debts!$B$14 -> 286 | U56: =MAX(0,T56-SUM(N56:S56)) -> 286 | V56: =_xlfn.MINIFS($B$3:$G$3,B56:G56,">0.005") -> 0 | W56: =IF(B56<=0.005,0,MIN(B56+H56,N56+IF(B$3=$V56,$U56,0))) -> 0 | X56: =IF(C56<=0.005,0,MIN(C56+I56,O56+IF(C$3=$V56,$U56,0))) -> 0 | Y56: =IF(D56<=0.005,0,MIN(D56+J56,P56+IF(D$3=$V56,$U56,0))) -> 0 | Z56: =IF(E56<=0.005,0,MIN(E56+K56,Q56+IF(E$3=$V56,$U56,0))) -> 0 | AA56: =IF(F56<=0.005,0,MIN(F56+L56,R56+IF(F$3=$V56,$U56,0))) -> 0 | AB56: =IF(G56<=0.005,0,MIN(G56+M56,S56+IF(G$3=$V56,$U56,0))) -> 0 | AC56: =MAX(0,B56+H56-W56) -> 0 | AD56: =MAX(0,C56+I56-X56) -> 0 | AE56: =MAX(0,D56+J56-Y56) -> 0 | AF56: =MAX(0,E56+K56-Z56) -> 0 | AG56: =MAX(0,F56+L56-AA56) -> 0 | AH56: =MAX(0,G56+M56-AB56) -> 0 | AI56: =SUM(H56:M56) -> 0 | AJ56: =SUM(AC56:AH56) -> 0
A57: 53 | B57: =AC56 -> 0 | C57: =AD56 -> 0 | D57: =AE56 -> 0 | E57: =AF56 -> 0 | F57: =AG56 -> 0 | G57: =AH56 -> 0 | H57: =B57*N(Debts!C7)/12 -> 0 | I57: =C57*N(Debts!C8)/12 -> 0 | J57: =D57*N(Debts!C9)/12 -> 0 | K57: =E57*N(Debts!C10)/12 -> 0 | L57: =F57*N(Debts!C11)/12 -> 0 | M57: =G57*N(Debts!C12)/12 -> 0 | N57: =MIN(B57+H57,N(Debts!D7)) -> 0 | O57: =MIN(C57+I57,N(Debts!D8)) -> 0 | P57: =MIN(D57+J57,N(Debts!D9)) -> 0 | Q57: =MIN(E57+K57,N(Debts!D10)) -> 0 | R57: =MIN(F57+L57,N(Debts!D11)) -> 0 | S57: =MIN(G57+M57,N(Debts!D12)) -> 0 | T57: =Debts!$B$14 -> 286 | U57: =MAX(0,T57-SUM(N57:S57)) -> 286 | V57: =_xlfn.MINIFS($B$3:$G$3,B57:G57,">0.005") -> 0 | W57: =IF(B57<=0.005,0,MIN(B57+H57,N57+IF(B$3=$V57,$U57,0))) -> 0 | X57: =IF(C57<=0.005,0,MIN(C57+I57,O57+IF(C$3=$V57,$U57,0))) -> 0 | Y57: =IF(D57<=0.005,0,MIN(D57+J57,P57+IF(D$3=$V57,$U57,0))) -> 0 | Z57: =IF(E57<=0.005,0,MIN(E57+K57,Q57+IF(E$3=$V57,$U57,0))) -> 0 | AA57: =IF(F57<=0.005,0,MIN(F57+L57,R57+IF(F$3=$V57,$U57,0))) -> 0 | AB57: =IF(G57<=0.005,0,MIN(G57+M57,S57+IF(G$3=$V57,$U57,0))) -> 0 | AC57: =MAX(0,B57+H57-W57) -> 0 | AD57: =MAX(0,C57+I57-X57) -> 0 | AE57: =MAX(0,D57+J57-Y57) -> 0 | AF57: =MAX(0,E57+K57-Z57) -> 0 | AG57: =MAX(0,F57+L57-AA57) -> 0 | AH57: =MAX(0,G57+M57-AB57) -> 0 | AI57: =SUM(H57:M57) -> 0 | AJ57: =SUM(AC57:AH57) -> 0
A58: 54 | B58: =AC57 -> 0 | C58: =AD57 -> 0 | D58: =AE57 -> 0 | E58: =AF57 -> 0 | F58: =AG57 -> 0 | G58: =AH57 -> 0 | H58: =B58*N(Debts!C7)/12 -> 0 | I58: =C58*N(Debts!C8)/12 -> 0 | J58: =D58*N(Debts!C9)/12 -> 0 | K58: =E58*N(Debts!C10)/12 -> 0 | L58: =F58*N(Debts!C11)/12 -> 0 | M58: =G58*N(Debts!C12)/12 -> 0 | N58: =MIN(B58+H58,N(Debts!D7)) -> 0 | O58: =MIN(C58+I58,N(Debts!D8)) -> 0 | P58: =MIN(D58+J58,N(Debts!D9)) -> 0 | Q58: =MIN(E58+K58,N(Debts!D10)) -> 0 | R58: =MIN(F58+L58,N(Debts!D11)) -> 0 | S58: =MIN(G58+M58,N(Debts!D12)) -> 0 | T58: =Debts!$B$14 -> 286 | U58: =MAX(0,T58-SUM(N58:S58)) -> 286 | V58: =_xlfn.MINIFS($B$3:$G$3,B58:G58,">0.005") -> 0 | W58: =IF(B58<=0.005,0,MIN(B58+H58,N58+IF(B$3=$V58,$U58,0))) -> 0 | X58: =IF(C58<=0.005,0,MIN(C58+I58,O58+IF(C$3=$V58,$U58,0))) -> 0 | Y58: =IF(D58<=0.005,0,MIN(D58+J58,P58+IF(D$3=$V58,$U58,0))) -> 0 | Z58: =IF(E58<=0.005,0,MIN(E58+K58,Q58+IF(E$3=$V58,$U58,0))) -> 0 | AA58: =IF(F58<=0.005,0,MIN(F58+L58,R58+IF(F$3=$V58,$U58,0))) -> 0 | AB58: =IF(G58<=0.005,0,MIN(G58+M58,S58+IF(G$3=$V58,$U58,0))) -> 0 | AC58: =MAX(0,B58+H58-W58) -> 0 | AD58: =MAX(0,C58+I58-X58) -> 0 | AE58: =MAX(0,D58+J58-Y58) -> 0 | AF58: =MAX(0,E58+K58-Z58) -> 0 | AG58: =MAX(0,F58+L58-AA58) -> 0 | AH58: =MAX(0,G58+M58-AB58) -> 0 | AI58: =SUM(H58:M58) -> 0 | AJ58: =SUM(AC58:AH58) -> 0
A59: 55 | B59: =AC58 -> 0 | C59: =AD58 -> 0 | D59: =AE58 -> 0 | E59: =AF58 -> 0 | F59: =AG58 -> 0 | G59: =AH58 -> 0 | H59: =B59*N(Debts!C7)/12 -> 0 | I59: =C59*N(Debts!C8)/12 -> 0 | J59: =D59*N(Debts!C9)/12 -> 0 | K59: =E59*N(Debts!C10)/12 -> 0 | L59: =F59*N(Debts!C11)/12 -> 0 | M59: =G59*N(Debts!C12)/12 -> 0 | N59: =MIN(B59+H59,N(Debts!D7)) -> 0 | O59: =MIN(C59+I59,N(Debts!D8)) -> 0 | P59: =MIN(D59+J59,N(Debts!D9)) -> 0 | Q59: =MIN(E59+K59,N(Debts!D10)) -> 0 | R59: =MIN(F59+L59,N(Debts!D11)) -> 0 | S59: =MIN(G59+M59,N(Debts!D12)) -> 0 | T59: =Debts!$B$14 -> 286 | U59: =MAX(0,T59-SUM(N59:S59)) -> 286 | V59: =_xlfn.MINIFS($B$3:$G$3,B59:G59,">0.005") -> 0 | W59: =IF(B59<=0.005,0,MIN(B59+H59,N59+IF(B$3=$V59,$U59,0))) -> 0 | X59: =IF(C59<=0.005,0,MIN(C59+I59,O59+IF(C$3=$V59,$U59,0))) -> 0 | Y59: =IF(D59<=0.005,0,MIN(D59+J59,P59+IF(D$3=$V59,$U59,0))) -> 0 | Z59: =IF(E59<=0.005,0,MIN(E59+K59,Q59+IF(E$3=$V59,$U59,0))) -> 0 | AA59: =IF(F59<=0.005,0,MIN(F59+L59,R59+IF(F$3=$V59,$U59,0))) -> 0 | AB59: =IF(G59<=0.005,0,MIN(G59+M59,S59+IF(G$3=$V59,$U59,0))) -> 0 | AC59: =MAX(0,B59+H59-W59) -> 0 | AD59: =MAX(0,C59+I59-X59) -> 0 | AE59: =MAX(0,D59+J59-Y59) -> 0 | AF59: =MAX(0,E59+K59-Z59) -> 0 | AG59: =MAX(0,F59+L59-AA59) -> 0 | AH59: =MAX(0,G59+M59-AB59) -> 0 | AI59: =SUM(H59:M59) -> 0 | AJ59: =SUM(AC59:AH59) -> 0
A60: 56 | B60: =AC59 -> 0 | C60: =AD59 -> 0 | D60: =AE59 -> 0 | E60: =AF59 -> 0 | F60: =AG59 -> 0 | G60: =AH59 -> 0 | H60: =B60*N(Debts!C7)/12 -> 0 | I60: =C60*N(Debts!C8)/12 -> 0 | J60: =D60*N(Debts!C9)/12 -> 0 | K60: =E60*N(Debts!C10)/12 -> 0 | L60: =F60*N(Debts!C11)/12 -> 0 | M60: =G60*N(Debts!C12)/12 -> 0 | N60: =MIN(B60+H60,N(Debts!D7)) -> 0 | O60: =MIN(C60+I60,N(Debts!D8)) -> 0 | P60: =MIN(D60+J60,N(Debts!D9)) -> 0 | Q60: =MIN(E60+K60,N(Debts!D10)) -> 0 | R60: =MIN(F60+L60,N(Debts!D11)) -> 0 | S60: =MIN(G60+M60,N(Debts!D12)) -> 0 | T60: =Debts!$B$14 -> 286 | U60: =MAX(0,T60-SUM(N60:S60)) -> 286 | V60: =_xlfn.MINIFS($B$3:$G$3,B60:G60,">0.005") -> 0 | W60: =IF(B60<=0.005,0,MIN(B60+H60,N60+IF(B$3=$V60,$U60,0))) -> 0 | X60: =IF(C60<=0.005,0,MIN(C60+I60,O60+IF(C$3=$V60,$U60,0))) -> 0 | Y60: =IF(D60<=0.005,0,MIN(D60+J60,P60+IF(D$3=$V60,$U60,0))) -> 0 | Z60: =IF(E60<=0.005,0,MIN(E60+K60,Q60+IF(E$3=$V60,$U60,0))) -> 0 | AA60: =IF(F60<=0.005,0,MIN(F60+L60,R60+IF(F$3=$V60,$U60,0))) -> 0 | AB60: =IF(G60<=0.005,0,MIN(G60+M60,S60+IF(G$3=$V60,$U60,0))) -> 0 | AC60: =MAX(0,B60+H60-W60) -> 0 | AD60: =MAX(0,C60+I60-X60) -> 0 | AE60: =MAX(0,D60+J60-Y60) -> 0 | AF60: =MAX(0,E60+K60-Z60) -> 0 | AG60: =MAX(0,F60+L60-AA60) -> 0 | AH60: =MAX(0,G60+M60-AB60) -> 0 | AI60: =SUM(H60:M60) -> 0 | AJ60: =SUM(AC60:AH60) -> 0
A61: 57 | B61: =AC60 -> 0 | C61: =AD60 -> 0 | D61: =AE60 -> 0 | E61: =AF60 -> 0 | F61: =AG60 -> 0 | G61: =AH60 -> 0 | H61: =B61*N(Debts!C7)/12 -> 0 | I61: =C61*N(Debts!C8)/12 -> 0 | J61: =D61*N(Debts!C9)/12 -> 0 | K61: =E61*N(Debts!C10)/12 -> 0 | L61: =F61*N(Debts!C11)/12 -> 0 | M61: =G61*N(Debts!C12)/12 -> 0 | N61: =MIN(B61+H61,N(Debts!D7)) -> 0 | O61: =MIN(C61+I61,N(Debts!D8)) -> 0 | P61: =MIN(D61+J61,N(Debts!D9)) -> 0 | Q61: =MIN(E61+K61,N(Debts!D10)) -> 0 | R61: =MIN(F61+L61,N(Debts!D11)) -> 0 | S61: =MIN(G61+M61,N(Debts!D12)) -> 0 | T61: =Debts!$B$14 -> 286 | U61: =MAX(0,T61-SUM(N61:S61)) -> 286 | V61: =_xlfn.MINIFS($B$3:$G$3,B61:G61,">0.005") -> 0 | W61: =IF(B61<=0.005,0,MIN(B61+H61,N61+IF(B$3=$V61,$U61,0))) -> 0 | X61: =IF(C61<=0.005,0,MIN(C61+I61,O61+IF(C$3=$V61,$U61,0))) -> 0 | Y61: =IF(D61<=0.005,0,MIN(D61+J61,P61+IF(D$3=$V61,$U61,0))) -> 0 | Z61: =IF(E61<=0.005,0,MIN(E61+K61,Q61+IF(E$3=$V61,$U61,0))) -> 0 | AA61: =IF(F61<=0.005,0,MIN(F61+L61,R61+IF(F$3=$V61,$U61,0))) -> 0 | AB61: =IF(G61<=0.005,0,MIN(G61+M61,S61+IF(G$3=$V61,$U61,0))) -> 0 | AC61: =MAX(0,B61+H61-W61) -> 0 | AD61: =MAX(0,C61+I61-X61) -> 0 | AE61: =MAX(0,D61+J61-Y61) -> 0 | AF61: =MAX(0,E61+K61-Z61) -> 0 | AG61: =MAX(0,F61+L61-AA61) -> 0 | AH61: =MAX(0,G61+M61-AB61) -> 0 | AI61: =SUM(H61:M61) -> 0 | AJ61: =SUM(AC61:AH61) -> 0
A62: 58 | B62: =AC61 -> 0 | C62: =AD61 -> 0 | D62: =AE61 -> 0 | E62: =AF61 -> 0 | F62: =AG61 -> 0 | G62: =AH61 -> 0 | H62: =B62*N(Debts!C7)/12 -> 0 | I62: =C62*N(Debts!C8)/12 -> 0 | J62: =D62*N(Debts!C9)/12 -> 0 | K62: =E62*N(Debts!C10)/12 -> 0 | L62: =F62*N(Debts!C11)/12 -> 0 | M62: =G62*N(Debts!C12)/12 -> 0 | N62: =MIN(B62+H62,N(Debts!D7)) -> 0 | O62: =MIN(C62+I62,N(Debts!D8)) -> 0 | P62: =MIN(D62+J62,N(Debts!D9)) -> 0 | Q62: =MIN(E62+K62,N(Debts!D10)) -> 0 | R62: =MIN(F62+L62,N(Debts!D11)) -> 0 | S62: =MIN(G62+M62,N(Debts!D12)) -> 0 | T62: =Debts!$B$14 -> 286 | U62: =MAX(0,T62-SUM(N62:S62)) -> 286 | V62: =_xlfn.MINIFS($B$3:$G$3,B62:G62,">0.005") -> 0 | W62: =IF(B62<=0.005,0,MIN(B62+H62,N62+IF(B$3=$V62,$U62,0))) -> 0 | X62: =IF(C62<=0.005,0,MIN(C62+I62,O62+IF(C$3=$V62,$U62,0))) -> 0 | Y62: =IF(D62<=0.005,0,MIN(D62+J62,P62+IF(D$3=$V62,$U62,0))) -> 0 | Z62: =IF(E62<=0.005,0,MIN(E62+K62,Q62+IF(E$3=$V62,$U62,0))) -> 0 | AA62: =IF(F62<=0.005,0,MIN(F62+L62,R62+IF(F$3=$V62,$U62,0))) -> 0 | AB62: =IF(G62<=0.005,0,MIN(G62+M62,S62+IF(G$3=$V62,$U62,0))) -> 0 | AC62: =MAX(0,B62+H62-W62) -> 0 | AD62: =MAX(0,C62+I62-X62) -> 0 | AE62: =MAX(0,D62+J62-Y62) -> 0 | AF62: =MAX(0,E62+K62-Z62) -> 0 | AG62: =MAX(0,F62+L62-AA62) -> 0 | AH62: =MAX(0,G62+M62-AB62) -> 0 | AI62: =SUM(H62:M62) -> 0 | AJ62: =SUM(AC62:AH62) -> 0
A63: 59 | B63: =AC62 -> 0 | C63: =AD62 -> 0 | D63: =AE62 -> 0 | E63: =AF62 -> 0 | F63: =AG62 -> 0 | G63: =AH62 -> 0 | H63: =B63*N(Debts!C7)/12 -> 0 | I63: =C63*N(Debts!C8)/12 -> 0 | J63: =D63*N(Debts!C9)/12 -> 0 | K63: =E63*N(Debts!C10)/12 -> 0 | L63: =F63*N(Debts!C11)/12 -> 0 | M63: =G63*N(Debts!C12)/12 -> 0 | N63: =MIN(B63+H63,N(Debts!D7)) -> 0 | O63: =MIN(C63+I63,N(Debts!D8)) -> 0 | P63: =MIN(D63+J63,N(Debts!D9)) -> 0 | Q63: =MIN(E63+K63,N(Debts!D10)) -> 0 | R63: =MIN(F63+L63,N(Debts!D11)) -> 0 | S63: =MIN(G63+M63,N(Debts!D12)) -> 0 | T63: =Debts!$B$14 -> 286 | U63: =MAX(0,T63-SUM(N63:S63)) -> 286 | V63: =_xlfn.MINIFS($B$3:$G$3,B63:G63,">0.005") -> 0 | W63: =IF(B63<=0.005,0,MIN(B63+H63,N63+IF(B$3=$V63,$U63,0))) -> 0 | X63: =IF(C63<=0.005,0,MIN(C63+I63,O63+IF(C$3=$V63,$U63,0))) -> 0 | Y63: =IF(D63<=0.005,0,MIN(D63+J63,P63+IF(D$3=$V63,$U63,0))) -> 0 | Z63: =IF(E63<=0.005,0,MIN(E63+K63,Q63+IF(E$3=$V63,$U63,0))) -> 0 | AA63: =IF(F63<=0.005,0,MIN(F63+L63,R63+IF(F$3=$V63,$U63,0))) -> 0 | AB63: =IF(G63<=0.005,0,MIN(G63+M63,S63+IF(G$3=$V63,$U63,0))) -> 0 | AC63: =MAX(0,B63+H63-W63) -> 0 | AD63: =MAX(0,C63+I63-X63) -> 0 | AE63: =MAX(0,D63+J63-Y63) -> 0 | AF63: =MAX(0,E63+K63-Z63) -> 0 | AG63: =MAX(0,F63+L63-AA63) -> 0 | AH63: =MAX(0,G63+M63-AB63) -> 0 | AI63: =SUM(H63:M63) -> 0 | AJ63: =SUM(AC63:AH63) -> 0
A64: 60 | B64: =AC63 -> 0 | C64: =AD63 -> 0 | D64: =AE63 -> 0 | E64: =AF63 -> 0 | F64: =AG63 -> 0 | G64: =AH63 -> 0 | H64: =B64*N(Debts!C7)/12 -> 0 | I64: =C64*N(Debts!C8)/12 -> 0 | J64: =D64*N(Debts!C9)/12 -> 0 | K64: =E64*N(Debts!C10)/12 -> 0 | L64: =F64*N(Debts!C11)/12 -> 0 | M64: =G64*N(Debts!C12)/12 -> 0 | N64: =MIN(B64+H64,N(Debts!D7)) -> 0 | O64: =MIN(C64+I64,N(Debts!D8)) -> 0 | P64: =MIN(D64+J64,N(Debts!D9)) -> 0 | Q64: =MIN(E64+K64,N(Debts!D10)) -> 0 | R64: =MIN(F64+L64,N(Debts!D11)) -> 0 | S64: =MIN(G64+M64,N(Debts!D12)) -> 0 | T64: =Debts!$B$14 -> 286 | U64: =MAX(0,T64-SUM(N64:S64)) -> 286 | V64: =_xlfn.MINIFS($B$3:$G$3,B64:G64,">0.005") -> 0 | W64: =IF(B64<=0.005,0,MIN(B64+H64,N64+IF(B$3=$V64,$U64,0))) -> 0 | X64: =IF(C64<=0.005,0,MIN(C64+I64,O64+IF(C$3=$V64,$U64,0))) -> 0 | Y64: =IF(D64<=0.005,0,MIN(D64+J64,P64+IF(D$3=$V64,$U64,0))) -> 0 | Z64: =IF(E64<=0.005,0,MIN(E64+K64,Q64+IF(E$3=$V64,$U64,0))) -> 0 | AA64: =IF(F64<=0.005,0,MIN(F64+L64,R64+IF(F$3=$V64,$U64,0))) -> 0 | AB64: =IF(G64<=0.005,0,MIN(G64+M64,S64+IF(G$3=$V64,$U64,0))) -> 0 | AC64: =MAX(0,B64+H64-W64) -> 0 | AD64: =MAX(0,C64+I64-X64) -> 0 | AE64: =MAX(0,D64+J64-Y64) -> 0 | AF64: =MAX(0,E64+K64-Z64) -> 0 | AG64: =MAX(0,F64+L64-AA64) -> 0 | AH64: =MAX(0,G64+M64-AB64) -> 0 | AI64: =SUM(H64:M64) -> 0 | AJ64: =SUM(AC64:AH64) -> 0
A65: 61 | B65: =AC64 -> 0 | C65: =AD64 -> 0 | D65: =AE64 -> 0 | E65: =AF64 -> 0 | F65: =AG64 -> 0 | G65: =AH64 -> 0 | H65: =B65*N(Debts!C7)/12 -> 0 | I65: =C65*N(Debts!C8)/12 -> 0 | J65: =D65*N(Debts!C9)/12 -> 0 | K65: =E65*N(Debts!C10)/12 -> 0 | L65: =F65*N(Debts!C11)/12 -> 0 | M65: =G65*N(Debts!C12)/12 -> 0 | N65: =MIN(B65+H65,N(Debts!D7)) -> 0 | O65: =MIN(C65+I65,N(Debts!D8)) -> 0 | P65: =MIN(D65+J65,N(Debts!D9)) -> 0 | Q65: =MIN(E65+K65,N(Debts!D10)) -> 0 | R65: =MIN(F65+L65,N(Debts!D11)) -> 0 | S65: =MIN(G65+M65,N(Debts!D12)) -> 0 | T65: =Debts!$B$14 -> 286 | U65: =MAX(0,T65-SUM(N65:S65)) -> 286 | V65: =_xlfn.MINIFS($B$3:$G$3,B65:G65,">0.005") -> 0 | W65: =IF(B65<=0.005,0,MIN(B65+H65,N65+IF(B$3=$V65,$U65,0))) -> 0 | X65: =IF(C65<=0.005,0,MIN(C65+I65,O65+IF(C$3=$V65,$U65,0))) -> 0 | Y65: =IF(D65<=0.005,0,MIN(D65+J65,P65+IF(D$3=$V65,$U65,0))) -> 0 | Z65: =IF(E65<=0.005,0,MIN(E65+K65,Q65+IF(E$3=$V65,$U65,0))) -> 0 | AA65: =IF(F65<=0.005,0,MIN(F65+L65,R65+IF(F$3=$V65,$U65,0))) -> 0 | AB65: =IF(G65<=0.005,0,MIN(G65+M65,S65+IF(G$3=$V65,$U65,0))) -> 0 | AC65: =MAX(0,B65+H65-W65) -> 0 | AD65: =MAX(0,C65+I65-X65) -> 0 | AE65: =MAX(0,D65+J65-Y65) -> 0 | AF65: =MAX(0,E65+K65-Z65) -> 0 | AG65: =MAX(0,F65+L65-AA65) -> 0 | AH65: =MAX(0,G65+M65-AB65) -> 0 | AI65: =SUM(H65:M65) -> 0 | AJ65: =SUM(AC65:AH65) -> 0
A66: 62 | B66: =AC65 -> 0 | C66: =AD65 -> 0 | D66: =AE65 -> 0 | E66: =AF65 -> 0 | F66: =AG65 -> 0 | G66: =AH65 -> 0 | H66: =B66*N(Debts!C7)/12 -> 0 | I66: =C66*N(Debts!C8)/12 -> 0 | J66: =D66*N(Debts!C9)/12 -> 0 | K66: =E66*N(Debts!C10)/12 -> 0 | L66: =F66*N(Debts!C11)/12 -> 0 | M66: =G66*N(Debts!C12)/12 -> 0 | N66: =MIN(B66+H66,N(Debts!D7)) -> 0 | O66: =MIN(C66+I66,N(Debts!D8)) -> 0 | P66: =MIN(D66+J66,N(Debts!D9)) -> 0 | Q66: =MIN(E66+K66,N(Debts!D10)) -> 0 | R66: =MIN(F66+L66,N(Debts!D11)) -> 0 | S66: =MIN(G66+M66,N(Debts!D12)) -> 0 | T66: =Debts!$B$14 -> 286 | U66: =MAX(0,T66-SUM(N66:S66)) -> 286 | V66: =_xlfn.MINIFS($B$3:$G$3,B66:G66,">0.005") -> 0 | W66: =IF(B66<=0.005,0,MIN(B66+H66,N66+IF(B$3=$V66,$U66,0))) -> 0 | X66: =IF(C66<=0.005,0,MIN(C66+I66,O66+IF(C$3=$V66,$U66,0))) -> 0 | Y66: =IF(D66<=0.005,0,MIN(D66+J66,P66+IF(D$3=$V66,$U66,0))) -> 0 | Z66: =IF(E66<=0.005,0,MIN(E66+K66,Q66+IF(E$3=$V66,$U66,0))) -> 0 | AA66: =IF(F66<=0.005,0,MIN(F66+L66,R66+IF(F$3=$V66,$U66,0))) -> 0 | AB66: =IF(G66<=0.005,0,MIN(G66+M66,S66+IF(G$3=$V66,$U66,0))) -> 0 | AC66: =MAX(0,B66+H66-W66) -> 0 | AD66: =MAX(0,C66+I66-X66) -> 0 | AE66: =MAX(0,D66+J66-Y66) -> 0 | AF66: =MAX(0,E66+K66-Z66) -> 0 | AG66: =MAX(0,F66+L66-AA66) -> 0 | AH66: =MAX(0,G66+M66-AB66) -> 0 | AI66: =SUM(H66:M66) -> 0 | AJ66: =SUM(AC66:AH66) -> 0
A67: 63 | B67: =AC66 -> 0 | C67: =AD66 -> 0 | D67: =AE66 -> 0 | E67: =AF66 -> 0 | F67: =AG66 -> 0 | G67: =AH66 -> 0 | H67: =B67*N(Debts!C7)/12 -> 0 | I67: =C67*N(Debts!C8)/12 -> 0 | J67: =D67*N(Debts!C9)/12 -> 0 | K67: =E67*N(Debts!C10)/12 -> 0 | L67: =F67*N(Debts!C11)/12 -> 0 | M67: =G67*N(Debts!C12)/12 -> 0 | N67: =MIN(B67+H67,N(Debts!D7)) -> 0 | O67: =MIN(C67+I67,N(Debts!D8)) -> 0 | P67: =MIN(D67+J67,N(Debts!D9)) -> 0 | Q67: =MIN(E67+K67,N(Debts!D10)) -> 0 | R67: =MIN(F67+L67,N(Debts!D11)) -> 0 | S67: =MIN(G67+M67,N(Debts!D12)) -> 0 | T67: =Debts!$B$14 -> 286 | U67: =MAX(0,T67-SUM(N67:S67)) -> 286 | V67: =_xlfn.MINIFS($B$3:$G$3,B67:G67,">0.005") -> 0 | W67: =IF(B67<=0.005,0,MIN(B67+H67,N67+IF(B$3=$V67,$U67,0))) -> 0 | X67: =IF(C67<=0.005,0,MIN(C67+I67,O67+IF(C$3=$V67,$U67,0))) -> 0 | Y67: =IF(D67<=0.005,0,MIN(D67+J67,P67+IF(D$3=$V67,$U67,0))) -> 0 | Z67: =IF(E67<=0.005,0,MIN(E67+K67,Q67+IF(E$3=$V67,$U67,0))) -> 0 | AA67: =IF(F67<=0.005,0,MIN(F67+L67,R67+IF(F$3=$V67,$U67,0))) -> 0 | AB67: =IF(G67<=0.005,0,MIN(G67+M67,S67+IF(G$3=$V67,$U67,0))) -> 0 | AC67: =MAX(0,B67+H67-W67) -> 0 | AD67: =MAX(0,C67+I67-X67) -> 0 | AE67: =MAX(0,D67+J67-Y67) -> 0 | AF67: =MAX(0,E67+K67-Z67) -> 0 | AG67: =MAX(0,F67+L67-AA67) -> 0 | AH67: =MAX(0,G67+M67-AB67) -> 0 | AI67: =SUM(H67:M67) -> 0 | AJ67: =SUM(AC67:AH67) -> 0
A68: 64 | B68: =AC67 -> 0 | C68: =AD67 -> 0 | D68: =AE67 -> 0 | E68: =AF67 -> 0 | F68: =AG67 -> 0 | G68: =AH67 -> 0 | H68: =B68*N(Debts!C7)/12 -> 0 | I68: =C68*N(Debts!C8)/12 -> 0 | J68: =D68*N(Debts!C9)/12 -> 0 | K68: =E68*N(Debts!C10)/12 -> 0 | L68: =F68*N(Debts!C11)/12 -> 0 | M68: =G68*N(Debts!C12)/12 -> 0 | N68: =MIN(B68+H68,N(Debts!D7)) -> 0 | O68: =MIN(C68+I68,N(Debts!D8)) -> 0 | P68: =MIN(D68+J68,N(Debts!D9)) -> 0 | Q68: =MIN(E68+K68,N(Debts!D10)) -> 0 | R68: =MIN(F68+L68,N(Debts!D11)) -> 0 | S68: =MIN(G68+M68,N(Debts!D12)) -> 0 | T68: =Debts!$B$14 -> 286 | U68: =MAX(0,T68-SUM(N68:S68)) -> 286 | V68: =_xlfn.MINIFS($B$3:$G$3,B68:G68,">0.005") -> 0 | W68: =IF(B68<=0.005,0,MIN(B68+H68,N68+IF(B$3=$V68,$U68,0))) -> 0 | X68: =IF(C68<=0.005,0,MIN(C68+I68,O68+IF(C$3=$V68,$U68,0))) -> 0 | Y68: =IF(D68<=0.005,0,MIN(D68+J68,P68+IF(D$3=$V68,$U68,0))) -> 0 | Z68: =IF(E68<=0.005,0,MIN(E68+K68,Q68+IF(E$3=$V68,$U68,0))) -> 0 | AA68: =IF(F68<=0.005,0,MIN(F68+L68,R68+IF(F$3=$V68,$U68,0))) -> 0 | AB68: =IF(G68<=0.005,0,MIN(G68+M68,S68+IF(G$3=$V68,$U68,0))) -> 0 | AC68: =MAX(0,B68+H68-W68) -> 0 | AD68: =MAX(0,C68+I68-X68) -> 0 | AE68: =MAX(0,D68+J68-Y68) -> 0 | AF68: =MAX(0,E68+K68-Z68) -> 0 | AG68: =MAX(0,F68+L68-AA68) -> 0 | AH68: =MAX(0,G68+M68-AB68) -> 0 | AI68: =SUM(H68:M68) -> 0 | AJ68: =SUM(AC68:AH68) -> 0
A69: 65 | B69: =AC68 -> 0 | C69: =AD68 -> 0 | D69: =AE68 -> 0 | E69: =AF68 -> 0 | F69: =AG68 -> 0 | G69: =AH68 -> 0 | H69: =B69*N(Debts!C7)/12 -> 0 | I69: =C69*N(Debts!C8)/12 -> 0 | J69: =D69*N(Debts!C9)/12 -> 0 | K69: =E69*N(Debts!C10)/12 -> 0 | L69: =F69*N(Debts!C11)/12 -> 0 | M69: =G69*N(Debts!C12)/12 -> 0 | N69: =MIN(B69+H69,N(Debts!D7)) -> 0 | O69: =MIN(C69+I69,N(Debts!D8)) -> 0 | P69: =MIN(D69+J69,N(Debts!D9)) -> 0 | Q69: =MIN(E69+K69,N(Debts!D10)) -> 0 | R69: =MIN(F69+L69,N(Debts!D11)) -> 0 | S69: =MIN(G69+M69,N(Debts!D12)) -> 0 | T69: =Debts!$B$14 -> 286 | U69: =MAX(0,T69-SUM(N69:S69)) -> 286 | V69: =_xlfn.MINIFS($B$3:$G$3,B69:G69,">0.005") -> 0 | W69: =IF(B69<=0.005,0,MIN(B69+H69,N69+IF(B$3=$V69,$U69,0))) -> 0 | X69: =IF(C69<=0.005,0,MIN(C69+I69,O69+IF(C$3=$V69,$U69,0))) -> 0 | Y69: =IF(D69<=0.005,0,MIN(D69+J69,P69+IF(D$3=$V69,$U69,0))) -> 0 | Z69: =IF(E69<=0.005,0,MIN(E69+K69,Q69+IF(E$3=$V69,$U69,0))) -> 0 | AA69: =IF(F69<=0.005,0,MIN(F69+L69,R69+IF(F$3=$V69,$U69,0))) -> 0 | AB69: =IF(G69<=0.005,0,MIN(G69+M69,S69+IF(G$3=$V69,$U69,0))) -> 0 | AC69: =MAX(0,B69+H69-W69) -> 0 | AD69: =MAX(0,C69+I69-X69) -> 0 | AE69: =MAX(0,D69+J69-Y69) -> 0 | AF69: =MAX(0,E69+K69-Z69) -> 0 | AG69: =MAX(0,F69+L69-AA69) -> 0 | AH69: =MAX(0,G69+M69-AB69) -> 0 | AI69: =SUM(H69:M69) -> 0 | AJ69: =SUM(AC69:AH69) -> 0
A70: 66 | B70: =AC69 -> 0 | C70: =AD69 -> 0 | D70: =AE69 -> 0 | E70: =AF69 -> 0 | F70: =AG69 -> 0 | G70: =AH69 -> 0 | H70: =B70*N(Debts!C7)/12 -> 0 | I70: =C70*N(Debts!C8)/12 -> 0 | J70: =D70*N(Debts!C9)/12 -> 0 | K70: =E70*N(Debts!C10)/12 -> 0 | L70: =F70*N(Debts!C11)/12 -> 0 | M70: =G70*N(Debts!C12)/12 -> 0 | N70: =MIN(B70+H70,N(Debts!D7)) -> 0 | O70: =MIN(C70+I70,N(Debts!D8)) -> 0 | P70: =MIN(D70+J70,N(Debts!D9)) -> 0 | Q70: =MIN(E70+K70,N(Debts!D10)) -> 0 | R70: =MIN(F70+L70,N(Debts!D11)) -> 0 | S70: =MIN(G70+M70,N(Debts!D12)) -> 0 | T70: =Debts!$B$14 -> 286 | U70: =MAX(0,T70-SUM(N70:S70)) -> 286 | V70: =_xlfn.MINIFS($B$3:$G$3,B70:G70,">0.005") -> 0 | W70: =IF(B70<=0.005,0,MIN(B70+H70,N70+IF(B$3=$V70,$U70,0))) -> 0 | X70: =IF(C70<=0.005,0,MIN(C70+I70,O70+IF(C$3=$V70,$U70,0))) -> 0 | Y70: =IF(D70<=0.005,0,MIN(D70+J70,P70+IF(D$3=$V70,$U70,0))) -> 0 | Z70: =IF(E70<=0.005,0,MIN(E70+K70,Q70+IF(E$3=$V70,$U70,0))) -> 0 | AA70: =IF(F70<=0.005,0,MIN(F70+L70,R70+IF(F$3=$V70,$U70,0))) -> 0 | AB70: =IF(G70<=0.005,0,MIN(G70+M70,S70+IF(G$3=$V70,$U70,0))) -> 0 | AC70: =MAX(0,B70+H70-W70) -> 0 | AD70: =MAX(0,C70+I70-X70) -> 0 | AE70: =MAX(0,D70+J70-Y70) -> 0 | AF70: =MAX(0,E70+K70-Z70) -> 0 | AG70: =MAX(0,F70+L70-AA70) -> 0 | AH70: =MAX(0,G70+M70-AB70) -> 0 | AI70: =SUM(H70:M70) -> 0 | AJ70: =SUM(AC70:AH70) -> 0
A71: 67 | B71: =AC70 -> 0 | C71: =AD70 -> 0 | D71: =AE70 -> 0 | E71: =AF70 -> 0 | F71: =AG70 -> 0 | G71: =AH70 -> 0 | H71: =B71*N(Debts!C7)/12 -> 0 | I71: =C71*N(Debts!C8)/12 -> 0 | J71: =D71*N(Debts!C9)/12 -> 0 | K71: =E71*N(Debts!C10)/12 -> 0 | L71: =F71*N(Debts!C11)/12 -> 0 | M71: =G71*N(Debts!C12)/12 -> 0 | N71: =MIN(B71+H71,N(Debts!D7)) -> 0 | O71: =MIN(C71+I71,N(Debts!D8)) -> 0 | P71: =MIN(D71+J71,N(Debts!D9)) -> 0 | Q71: =MIN(E71+K71,N(Debts!D10)) -> 0 | R71: =MIN(F71+L71,N(Debts!D11)) -> 0 | S71: =MIN(G71+M71,N(Debts!D12)) -> 0 | T71: =Debts!$B$14 -> 286 | U71: =MAX(0,T71-SUM(N71:S71)) -> 286 | V71: =_xlfn.MINIFS($B$3:$G$3,B71:G71,">0.005") -> 0 | W71: =IF(B71<=0.005,0,MIN(B71+H71,N71+IF(B$3=$V71,$U71,0))) -> 0 | X71: =IF(C71<=0.005,0,MIN(C71+I71,O71+IF(C$3=$V71,$U71,0))) -> 0 | Y71: =IF(D71<=0.005,0,MIN(D71+J71,P71+IF(D$3=$V71,$U71,0))) -> 0 | Z71: =IF(E71<=0.005,0,MIN(E71+K71,Q71+IF(E$3=$V71,$U71,0))) -> 0 | AA71: =IF(F71<=0.005,0,MIN(F71+L71,R71+IF(F$3=$V71,$U71,0))) -> 0 | AB71: =IF(G71<=0.005,0,MIN(G71+M71,S71+IF(G$3=$V71,$U71,0))) -> 0 | AC71: =MAX(0,B71+H71-W71) -> 0 | AD71: =MAX(0,C71+I71-X71) -> 0 | AE71: =MAX(0,D71+J71-Y71) -> 0 | AF71: =MAX(0,E71+K71-Z71) -> 0 | AG71: =MAX(0,F71+L71-AA71) -> 0 | AH71: =MAX(0,G71+M71-AB71) -> 0 | AI71: =SUM(H71:M71) -> 0 | AJ71: =SUM(AC71:AH71) -> 0
A72: 68 | B72: =AC71 -> 0 | C72: =AD71 -> 0 | D72: =AE71 -> 0 | E72: =AF71 -> 0 | F72: =AG71 -> 0 | G72: =AH71 -> 0 | H72: =B72*N(Debts!C7)/12 -> 0 | I72: =C72*N(Debts!C8)/12 -> 0 | J72: =D72*N(Debts!C9)/12 -> 0 | K72: =E72*N(Debts!C10)/12 -> 0 | L72: =F72*N(Debts!C11)/12 -> 0 | M72: =G72*N(Debts!C12)/12 -> 0 | N72: =MIN(B72+H72,N(Debts!D7)) -> 0 | O72: =MIN(C72+I72,N(Debts!D8)) -> 0 | P72: =MIN(D72+J72,N(Debts!D9)) -> 0 | Q72: =MIN(E72+K72,N(Debts!D10)) -> 0 | R72: =MIN(F72+L72,N(Debts!D11)) -> 0 | S72: =MIN(G72+M72,N(Debts!D12)) -> 0 | T72: =Debts!$B$14 -> 286 | U72: =MAX(0,T72-SUM(N72:S72)) -> 286 | V72: =_xlfn.MINIFS($B$3:$G$3,B72:G72,">0.005") -> 0 | W72: =IF(B72<=0.005,0,MIN(B72+H72,N72+IF(B$3=$V72,$U72,0))) -> 0 | X72: =IF(C72<=0.005,0,MIN(C72+I72,O72+IF(C$3=$V72,$U72,0))) -> 0 | Y72: =IF(D72<=0.005,0,MIN(D72+J72,P72+IF(D$3=$V72,$U72,0))) -> 0 | Z72: =IF(E72<=0.005,0,MIN(E72+K72,Q72+IF(E$3=$V72,$U72,0))) -> 0 | AA72: =IF(F72<=0.005,0,MIN(F72+L72,R72+IF(F$3=$V72,$U72,0))) -> 0 | AB72: =IF(G72<=0.005,0,MIN(G72+M72,S72+IF(G$3=$V72,$U72,0))) -> 0 | AC72: =MAX(0,B72+H72-W72) -> 0 | AD72: =MAX(0,C72+I72-X72) -> 0 | AE72: =MAX(0,D72+J72-Y72) -> 0 | AF72: =MAX(0,E72+K72-Z72) -> 0 | AG72: =MAX(0,F72+L72-AA72) -> 0 | AH72: =MAX(0,G72+M72-AB72) -> 0 | AI72: =SUM(H72:M72) -> 0 | AJ72: =SUM(AC72:AH72) -> 0
A73: 69 | B73: =AC72 -> 0 | C73: =AD72 -> 0 | D73: =AE72 -> 0 | E73: =AF72 -> 0 | F73: =AG72 -> 0 | G73: =AH72 -> 0 | H73: =B73*N(Debts!C7)/12 -> 0 | I73: =C73*N(Debts!C8)/12 -> 0 | J73: =D73*N(Debts!C9)/12 -> 0 | K73: =E73*N(Debts!C10)/12 -> 0 | L73: =F73*N(Debts!C11)/12 -> 0 | M73: =G73*N(Debts!C12)/12 -> 0 | N73: =MIN(B73+H73,N(Debts!D7)) -> 0 | O73: =MIN(C73+I73,N(Debts!D8)) -> 0 | P73: =MIN(D73+J73,N(Debts!D9)) -> 0 | Q73: =MIN(E73+K73,N(Debts!D10)) -> 0 | R73: =MIN(F73+L73,N(Debts!D11)) -> 0 | S73: =MIN(G73+M73,N(Debts!D12)) -> 0 | T73: =Debts!$B$14 -> 286 | U73: =MAX(0,T73-SUM(N73:S73)) -> 286 | V73: =_xlfn.MINIFS($B$3:$G$3,B73:G73,">0.005") -> 0 | W73: =IF(B73<=0.005,0,MIN(B73+H73,N73+IF(B$3=$V73,$U73,0))) -> 0 | X73: =IF(C73<=0.005,0,MIN(C73+I73,O73+IF(C$3=$V73,$U73,0))) -> 0 | Y73: =IF(D73<=0.005,0,MIN(D73+J73,P73+IF(D$3=$V73,$U73,0))) -> 0 | Z73: =IF(E73<=0.005,0,MIN(E73+K73,Q73+IF(E$3=$V73,$U73,0))) -> 0 | AA73: =IF(F73<=0.005,0,MIN(F73+L73,R73+IF(F$3=$V73,$U73,0))) -> 0 | AB73: =IF(G73<=0.005,0,MIN(G73+M73,S73+IF(G$3=$V73,$U73,0))) -> 0 | AC73: =MAX(0,B73+H73-W73) -> 0 | AD73: =MAX(0,C73+I73-X73) -> 0 | AE73: =MAX(0,D73+J73-Y73) -> 0 | AF73: =MAX(0,E73+K73-Z73) -> 0 | AG73: =MAX(0,F73+L73-AA73) -> 0 | AH73: =MAX(0,G73+M73-AB73) -> 0 | AI73: =SUM(H73:M73) -> 0 | AJ73: =SUM(AC73:AH73) -> 0
A74: 70 | B74: =AC73 -> 0 | C74: =AD73 -> 0 | D74: =AE73 -> 0 | E74: =AF73 -> 0 | F74: =AG73 -> 0 | G74: =AH73 -> 0 | H74: =B74*N(Debts!C7)/12 -> 0 | I74: =C74*N(Debts!C8)/12 -> 0 | J74: =D74*N(Debts!C9)/12 -> 0 | K74: =E74*N(Debts!C10)/12 -> 0 | L74: =F74*N(Debts!C11)/12 -> 0 | M74: =G74*N(Debts!C12)/12 -> 0 | N74: =MIN(B74+H74,N(Debts!D7)) -> 0 | O74: =MIN(C74+I74,N(Debts!D8)) -> 0 | P74: =MIN(D74+J74,N(Debts!D9)) -> 0 | Q74: =MIN(E74+K74,N(Debts!D10)) -> 0 | R74: =MIN(F74+L74,N(Debts!D11)) -> 0 | S74: =MIN(G74+M74,N(Debts!D12)) -> 0 | T74: =Debts!$B$14 -> 286 | U74: =MAX(0,T74-SUM(N74:S74)) -> 286 | V74: =_xlfn.MINIFS($B$3:$G$3,B74:G74,">0.005") -> 0 | W74: =IF(B74<=0.005,0,MIN(B74+H74,N74+IF(B$3=$V74,$U74,0))) -> 0 | X74: =IF(C74<=0.005,0,MIN(C74+I74,O74+IF(C$3=$V74,$U74,0))) -> 0 | Y74: =IF(D74<=0.005,0,MIN(D74+J74,P74+IF(D$3=$V74,$U74,0))) -> 0 | Z74: =IF(E74<=0.005,0,MIN(E74+K74,Q74+IF(E$3=$V74,$U74,0))) -> 0 | AA74: =IF(F74<=0.005,0,MIN(F74+L74,R74+IF(F$3=$V74,$U74,0))) -> 0 | AB74: =IF(G74<=0.005,0,MIN(G74+M74,S74+IF(G$3=$V74,$U74,0))) -> 0 | AC74: =MAX(0,B74+H74-W74) -> 0 | AD74: =MAX(0,C74+I74-X74) -> 0 | AE74: =MAX(0,D74+J74-Y74) -> 0 | AF74: =MAX(0,E74+K74-Z74) -> 0 | AG74: =MAX(0,F74+L74-AA74) -> 0 | AH74: =MAX(0,G74+M74-AB74) -> 0 | AI74: =SUM(H74:M74) -> 0 | AJ74: =SUM(AC74:AH74) -> 0
A75: 71 | B75: =AC74 -> 0 | C75: =AD74 -> 0 | D75: =AE74 -> 0 | E75: =AF74 -> 0 | F75: =AG74 -> 0 | G75: =AH74 -> 0 | H75: =B75*N(Debts!C7)/12 -> 0 | I75: =C75*N(Debts!C8)/12 -> 0 | J75: =D75*N(Debts!C9)/12 -> 0 | K75: =E75*N(Debts!C10)/12 -> 0 | L75: =F75*N(Debts!C11)/12 -> 0 | M75: =G75*N(Debts!C12)/12 -> 0 | N75: =MIN(B75+H75,N(Debts!D7)) -> 0 | O75: =MIN(C75+I75,N(Debts!D8)) -> 0 | P75: =MIN(D75+J75,N(Debts!D9)) -> 0 | Q75: =MIN(E75+K75,N(Debts!D10)) -> 0 | R75: =MIN(F75+L75,N(Debts!D11)) -> 0 | S75: =MIN(G75+M75,N(Debts!D12)) -> 0 | T75: =Debts!$B$14 -> 286 | U75: =MAX(0,T75-SUM(N75:S75)) -> 286 | V75: =_xlfn.MINIFS($B$3:$G$3,B75:G75,">0.005") -> 0 | W75: =IF(B75<=0.005,0,MIN(B75+H75,N75+IF(B$3=$V75,$U75,0))) -> 0 | X75: =IF(C75<=0.005,0,MIN(C75+I75,O75+IF(C$3=$V75,$U75,0))) -> 0 | Y75: =IF(D75<=0.005,0,MIN(D75+J75,P75+IF(D$3=$V75,$U75,0))) -> 0 | Z75: =IF(E75<=0.005,0,MIN(E75+K75,Q75+IF(E$3=$V75,$U75,0))) -> 0 | AA75: =IF(F75<=0.005,0,MIN(F75+L75,R75+IF(F$3=$V75,$U75,0))) -> 0 | AB75: =IF(G75<=0.005,0,MIN(G75+M75,S75+IF(G$3=$V75,$U75,0))) -> 0 | AC75: =MAX(0,B75+H75-W75) -> 0 | AD75: =MAX(0,C75+I75-X75) -> 0 | AE75: =MAX(0,D75+J75-Y75) -> 0 | AF75: =MAX(0,E75+K75-Z75) -> 0 | AG75: =MAX(0,F75+L75-AA75) -> 0 | AH75: =MAX(0,G75+M75-AB75) -> 0 | AI75: =SUM(H75:M75) -> 0 | AJ75: =SUM(AC75:AH75) -> 0
A76: 72 | B76: =AC75 -> 0 | C76: =AD75 -> 0 | D76: =AE75 -> 0 | E76: =AF75 -> 0 | F76: =AG75 -> 0 | G76: =AH75 -> 0 | H76: =B76*N(Debts!C7)/12 -> 0 | I76: =C76*N(Debts!C8)/12 -> 0 | J76: =D76*N(Debts!C9)/12 -> 0 | K76: =E76*N(Debts!C10)/12 -> 0 | L76: =F76*N(Debts!C11)/12 -> 0 | M76: =G76*N(Debts!C12)/12 -> 0 | N76: =MIN(B76+H76,N(Debts!D7)) -> 0 | O76: =MIN(C76+I76,N(Debts!D8)) -> 0 | P76: =MIN(D76+J76,N(Debts!D9)) -> 0 | Q76: =MIN(E76+K76,N(Debts!D10)) -> 0 | R76: =MIN(F76+L76,N(Debts!D11)) -> 0 | S76: =MIN(G76+M76,N(Debts!D12)) -> 0 | T76: =Debts!$B$14 -> 286 | U76: =MAX(0,T76-SUM(N76:S76)) -> 286 | V76: =_xlfn.MINIFS($B$3:$G$3,B76:G76,">0.005") -> 0 | W76: =IF(B76<=0.005,0,MIN(B76+H76,N76+IF(B$3=$V76,$U76,0))) -> 0 | X76: =IF(C76<=0.005,0,MIN(C76+I76,O76+IF(C$3=$V76,$U76,0))) -> 0 | Y76: =IF(D76<=0.005,0,MIN(D76+J76,P76+IF(D$3=$V76,$U76,0))) -> 0 | Z76: =IF(E76<=0.005,0,MIN(E76+K76,Q76+IF(E$3=$V76,$U76,0))) -> 0 | AA76: =IF(F76<=0.005,0,MIN(F76+L76,R76+IF(F$3=$V76,$U76,0))) -> 0 | AB76: =IF(G76<=0.005,0,MIN(G76+M76,S76+IF(G$3=$V76,$U76,0))) -> 0 | AC76: =MAX(0,B76+H76-W76) -> 0 | AD76: =MAX(0,C76+I76-X76) -> 0 | AE76: =MAX(0,D76+J76-Y76) -> 0 | AF76: =MAX(0,E76+K76-Z76) -> 0 | AG76: =MAX(0,F76+L76-AA76) -> 0 | AH76: =MAX(0,G76+M76-AB76) -> 0 | AI76: =SUM(H76:M76) -> 0 | AJ76: =SUM(AC76:AH76) -> 0
A77: 73 | B77: =AC76 -> 0 | C77: =AD76 -> 0 | D77: =AE76 -> 0 | E77: =AF76 -> 0 | F77: =AG76 -> 0 | G77: =AH76 -> 0 | H77: =B77*N(Debts!C7)/12 -> 0 | I77: =C77*N(Debts!C8)/12 -> 0 | J77: =D77*N(Debts!C9)/12 -> 0 | K77: =E77*N(Debts!C10)/12 -> 0 | L77: =F77*N(Debts!C11)/12 -> 0 | M77: =G77*N(Debts!C12)/12 -> 0 | N77: =MIN(B77+H77,N(Debts!D7)) -> 0 | O77: =MIN(C77+I77,N(Debts!D8)) -> 0 | P77: =MIN(D77+J77,N(Debts!D9)) -> 0 | Q77: =MIN(E77+K77,N(Debts!D10)) -> 0 | R77: =MIN(F77+L77,N(Debts!D11)) -> 0 | S77: =MIN(G77+M77,N(Debts!D12)) -> 0 | T77: =Debts!$B$14 -> 286 | U77: =MAX(0,T77-SUM(N77:S77)) -> 286 | V77: =_xlfn.MINIFS($B$3:$G$3,B77:G77,">0.005") -> 0 | W77: =IF(B77<=0.005,0,MIN(B77+H77,N77+IF(B$3=$V77,$U77,0))) -> 0 | X77: =IF(C77<=0.005,0,MIN(C77+I77,O77+IF(C$3=$V77,$U77,0))) -> 0 | Y77: =IF(D77<=0.005,0,MIN(D77+J77,P77+IF(D$3=$V77,$U77,0))) -> 0 | Z77: =IF(E77<=0.005,0,MIN(E77+K77,Q77+IF(E$3=$V77,$U77,0))) -> 0 | AA77: =IF(F77<=0.005,0,MIN(F77+L77,R77+IF(F$3=$V77,$U77,0))) -> 0 | AB77: =IF(G77<=0.005,0,MIN(G77+M77,S77+IF(G$3=$V77,$U77,0))) -> 0 | AC77: =MAX(0,B77+H77-W77) -> 0 | AD77: =MAX(0,C77+I77-X77) -> 0 | AE77: =MAX(0,D77+J77-Y77) -> 0 | AF77: =MAX(0,E77+K77-Z77) -> 0 | AG77: =MAX(0,F77+L77-AA77) -> 0 | AH77: =MAX(0,G77+M77-AB77) -> 0 | AI77: =SUM(H77:M77) -> 0 | AJ77: =SUM(AC77:AH77) -> 0
A78: 74 | B78: =AC77 -> 0 | C78: =AD77 -> 0 | D78: =AE77 -> 0 | E78: =AF77 -> 0 | F78: =AG77 -> 0 | G78: =AH77 -> 0 | H78: =B78*N(Debts!C7)/12 -> 0 | I78: =C78*N(Debts!C8)/12 -> 0 | J78: =D78*N(Debts!C9)/12 -> 0 | K78: =E78*N(Debts!C10)/12 -> 0 | L78: =F78*N(Debts!C11)/12 -> 0 | M78: =G78*N(Debts!C12)/12 -> 0 | N78: =MIN(B78+H78,N(Debts!D7)) -> 0 | O78: =MIN(C78+I78,N(Debts!D8)) -> 0 | P78: =MIN(D78+J78,N(Debts!D9)) -> 0 | Q78: =MIN(E78+K78,N(Debts!D10)) -> 0 | R78: =MIN(F78+L78,N(Debts!D11)) -> 0 | S78: =MIN(G78+M78,N(Debts!D12)) -> 0 | T78: =Debts!$B$14 -> 286 | U78: =MAX(0,T78-SUM(N78:S78)) -> 286 | V78: =_xlfn.MINIFS($B$3:$G$3,B78:G78,">0.005") -> 0 | W78: =IF(B78<=0.005,0,MIN(B78+H78,N78+IF(B$3=$V78,$U78,0))) -> 0 | X78: =IF(C78<=0.005,0,MIN(C78+I78,O78+IF(C$3=$V78,$U78,0))) -> 0 | Y78: =IF(D78<=0.005,0,MIN(D78+J78,P78+IF(D$3=$V78,$U78,0))) -> 0 | Z78: =IF(E78<=0.005,0,MIN(E78+K78,Q78+IF(E$3=$V78,$U78,0))) -> 0 | AA78: =IF(F78<=0.005,0,MIN(F78+L78,R78+IF(F$3=$V78,$U78,0))) -> 0 | AB78: =IF(G78<=0.005,0,MIN(G78+M78,S78+IF(G$3=$V78,$U78,0))) -> 0 | AC78: =MAX(0,B78+H78-W78) -> 0 | AD78: =MAX(0,C78+I78-X78) -> 0 | AE78: =MAX(0,D78+J78-Y78) -> 0 | AF78: =MAX(0,E78+K78-Z78) -> 0 | AG78: =MAX(0,F78+L78-AA78) -> 0 | AH78: =MAX(0,G78+M78-AB78) -> 0 | AI78: =SUM(H78:M78) -> 0 | AJ78: =SUM(AC78:AH78) -> 0
A79: 75 | B79: =AC78 -> 0 | C79: =AD78 -> 0 | D79: =AE78 -> 0 | E79: =AF78 -> 0 | F79: =AG78 -> 0 | G79: =AH78 -> 0 | H79: =B79*N(Debts!C7)/12 -> 0 | I79: =C79*N(Debts!C8)/12 -> 0 | J79: =D79*N(Debts!C9)/12 -> 0 | K79: =E79*N(Debts!C10)/12 -> 0 | L79: =F79*N(Debts!C11)/12 -> 0 | M79: =G79*N(Debts!C12)/12 -> 0 | N79: =MIN(B79+H79,N(Debts!D7)) -> 0 | O79: =MIN(C79+I79,N(Debts!D8)) -> 0 | P79: =MIN(D79+J79,N(Debts!D9)) -> 0 | Q79: =MIN(E79+K79,N(Debts!D10)) -> 0 | R79: =MIN(F79+L79,N(Debts!D11)) -> 0 | S79: =MIN(G79+M79,N(Debts!D12)) -> 0 | T79: =Debts!$B$14 -> 286 | U79: =MAX(0,T79-SUM(N79:S79)) -> 286 | V79: =_xlfn.MINIFS($B$3:$G$3,B79:G79,">0.005") -> 0 | W79: =IF(B79<=0.005,0,MIN(B79+H79,N79+IF(B$3=$V79,$U79,0))) -> 0 | X79: =IF(C79<=0.005,0,MIN(C79+I79,O79+IF(C$3=$V79,$U79,0))) -> 0 | Y79: =IF(D79<=0.005,0,MIN(D79+J79,P79+IF(D$3=$V79,$U79,0))) -> 0 | Z79: =IF(E79<=0.005,0,MIN(E79+K79,Q79+IF(E$3=$V79,$U79,0))) -> 0 | AA79: =IF(F79<=0.005,0,MIN(F79+L79,R79+IF(F$3=$V79,$U79,0))) -> 0 | AB79: =IF(G79<=0.005,0,MIN(G79+M79,S79+IF(G$3=$V79,$U79,0))) -> 0 | AC79: =MAX(0,B79+H79-W79) -> 0 | AD79: =MAX(0,C79+I79-X79) -> 0 | AE79: =MAX(0,D79+J79-Y79) -> 0 | AF79: =MAX(0,E79+K79-Z79) -> 0 | AG79: =MAX(0,F79+L79-AA79) -> 0 | AH79: =MAX(0,G79+M79-AB79) -> 0 | AI79: =SUM(H79:M79) -> 0 | AJ79: =SUM(AC79:AH79) -> 0
A80: 76 | B80: =AC79 -> 0 | C80: =AD79 -> 0 | D80: =AE79 -> 0 | E80: =AF79 -> 0 | F80: =AG79 -> 0 | G80: =AH79 -> 0 | H80: =B80*N(Debts!C7)/12 -> 0 | I80: =C80*N(Debts!C8)/12 -> 0 | J80: =D80*N(Debts!C9)/12 -> 0 | K80: =E80*N(Debts!C10)/12 -> 0 | L80: =F80*N(Debts!C11)/12 -> 0 | M80: =G80*N(Debts!C12)/12 -> 0 | N80: =MIN(B80+H80,N(Debts!D7)) -> 0 | O80: =MIN(C80+I80,N(Debts!D8)) -> 0 | P80: =MIN(D80+J80,N(Debts!D9)) -> 0 | Q80: =MIN(E80+K80,N(Debts!D10)) -> 0 | R80: =MIN(F80+L80,N(Debts!D11)) -> 0 | S80: =MIN(G80+M80,N(Debts!D12)) -> 0 | T80: =Debts!$B$14 -> 286 | U80: =MAX(0,T80-SUM(N80:S80)) -> 286 | V80: =_xlfn.MINIFS($B$3:$G$3,B80:G80,">0.005") -> 0 | W80: =IF(B80<=0.005,0,MIN(B80+H80,N80+IF(B$3=$V80,$U80,0))) -> 0 | X80: =IF(C80<=0.005,0,MIN(C80+I80,O80+IF(C$3=$V80,$U80,0))) -> 0 | Y80: =IF(D80<=0.005,0,MIN(D80+J80,P80+IF(D$3=$V80,$U80,0))) -> 0 | Z80: =IF(E80<=0.005,0,MIN(E80+K80,Q80+IF(E$3=$V80,$U80,0))) -> 0 | AA80: =IF(F80<=0.005,0,MIN(F80+L80,R80+IF(F$3=$V80,$U80,0))) -> 0 | AB80: =IF(G80<=0.005,0,MIN(G80+M80,S80+IF(G$3=$V80,$U80,0))) -> 0 | AC80: =MAX(0,B80+H80-W80) -> 0 | AD80: =MAX(0,C80+I80-X80) -> 0 | AE80: =MAX(0,D80+J80-Y80) -> 0 | AF80: =MAX(0,E80+K80-Z80) -> 0 | AG80: =MAX(0,F80+L80-AA80) -> 0 | AH80: =MAX(0,G80+M80-AB80) -> 0 | AI80: =SUM(H80:M80) -> 0 | AJ80: =SUM(AC80:AH80) -> 0
A81: 77 | B81: =AC80 -> 0 | C81: =AD80 -> 0 | D81: =AE80 -> 0 | E81: =AF80 -> 0 | F81: =AG80 -> 0 | G81: =AH80 -> 0 | H81: =B81*N(Debts!C7)/12 -> 0 | I81: =C81*N(Debts!C8)/12 -> 0 | J81: =D81*N(Debts!C9)/12 -> 0 | K81: =E81*N(Debts!C10)/12 -> 0 | L81: =F81*N(Debts!C11)/12 -> 0 | M81: =G81*N(Debts!C12)/12 -> 0 | N81: =MIN(B81+H81,N(Debts!D7)) -> 0 | O81: =MIN(C81+I81,N(Debts!D8)) -> 0 | P81: =MIN(D81+J81,N(Debts!D9)) -> 0 | Q81: =MIN(E81+K81,N(Debts!D10)) -> 0 | R81: =MIN(F81+L81,N(Debts!D11)) -> 0 | S81: =MIN(G81+M81,N(Debts!D12)) -> 0 | T81: =Debts!$B$14 -> 286 | U81: =MAX(0,T81-SUM(N81:S81)) -> 286 | V81: =_xlfn.MINIFS($B$3:$G$3,B81:G81,">0.005") -> 0 | W81: =IF(B81<=0.005,0,MIN(B81+H81,N81+IF(B$3=$V81,$U81,0))) -> 0 | X81: =IF(C81<=0.005,0,MIN(C81+I81,O81+IF(C$3=$V81,$U81,0))) -> 0 | Y81: =IF(D81<=0.005,0,MIN(D81+J81,P81+IF(D$3=$V81,$U81,0))) -> 0 | Z81: =IF(E81<=0.005,0,MIN(E81+K81,Q81+IF(E$3=$V81,$U81,0))) -> 0 | AA81: =IF(F81<=0.005,0,MIN(F81+L81,R81+IF(F$3=$V81,$U81,0))) -> 0 | AB81: =IF(G81<=0.005,0,MIN(G81+M81,S81+IF(G$3=$V81,$U81,0))) -> 0 | AC81: =MAX(0,B81+H81-W81) -> 0 | AD81: =MAX(0,C81+I81-X81) -> 0 | AE81: =MAX(0,D81+J81-Y81) -> 0 | AF81: =MAX(0,E81+K81-Z81) -> 0 | AG81: =MAX(0,F81+L81-AA81) -> 0 | AH81: =MAX(0,G81+M81-AB81) -> 0 | AI81: =SUM(H81:M81) -> 0 | AJ81: =SUM(AC81:AH81) -> 0
A82: 78 | B82: =AC81 -> 0 | C82: =AD81 -> 0 | D82: =AE81 -> 0 | E82: =AF81 -> 0 | F82: =AG81 -> 0 | G82: =AH81 -> 0 | H82: =B82*N(Debts!C7)/12 -> 0 | I82: =C82*N(Debts!C8)/12 -> 0 | J82: =D82*N(Debts!C9)/12 -> 0 | K82: =E82*N(Debts!C10)/12 -> 0 | L82: =F82*N(Debts!C11)/12 -> 0 | M82: =G82*N(Debts!C12)/12 -> 0 | N82: =MIN(B82+H82,N(Debts!D7)) -> 0 | O82: =MIN(C82+I82,N(Debts!D8)) -> 0 | P82: =MIN(D82+J82,N(Debts!D9)) -> 0 | Q82: =MIN(E82+K82,N(Debts!D10)) -> 0 | R82: =MIN(F82+L82,N(Debts!D11)) -> 0 | S82: =MIN(G82+M82,N(Debts!D12)) -> 0 | T82: =Debts!$B$14 -> 286 | U82: =MAX(0,T82-SUM(N82:S82)) -> 286 | V82: =_xlfn.MINIFS($B$3:$G$3,B82:G82,">0.005") -> 0 | W82: =IF(B82<=0.005,0,MIN(B82+H82,N82+IF(B$3=$V82,$U82,0))) -> 0 | X82: =IF(C82<=0.005,0,MIN(C82+I82,O82+IF(C$3=$V82,$U82,0))) -> 0 | Y82: =IF(D82<=0.005,0,MIN(D82+J82,P82+IF(D$3=$V82,$U82,0))) -> 0 | Z82: =IF(E82<=0.005,0,MIN(E82+K82,Q82+IF(E$3=$V82,$U82,0))) -> 0 | AA82: =IF(F82<=0.005,0,MIN(F82+L82,R82+IF(F$3=$V82,$U82,0))) -> 0 | AB82: =IF(G82<=0.005,0,MIN(G82+M82,S82+IF(G$3=$V82,$U82,0))) -> 0 | AC82: =MAX(0,B82+H82-W82) -> 0 | AD82: =MAX(0,C82+I82-X82) -> 0 | AE82: =MAX(0,D82+J82-Y82) -> 0 | AF82: =MAX(0,E82+K82-Z82) -> 0 | AG82: =MAX(0,F82+L82-AA82) -> 0 | AH82: =MAX(0,G82+M82-AB82) -> 0 | AI82: =SUM(H82:M82) -> 0 | AJ82: =SUM(AC82:AH82) -> 0
A83: 79 | B83: =AC82 -> 0 | C83: =AD82 -> 0 | D83: =AE82 -> 0 | E83: =AF82 -> 0 | F83: =AG82 -> 0 | G83: =AH82 -> 0 | H83: =B83*N(Debts!C7)/12 -> 0 | I83: =C83*N(Debts!C8)/12 -> 0 | J83: =D83*N(Debts!C9)/12 -> 0 | K83: =E83*N(Debts!C10)/12 -> 0 | L83: =F83*N(Debts!C11)/12 -> 0 | M83: =G83*N(Debts!C12)/12 -> 0 | N83: =MIN(B83+H83,N(Debts!D7)) -> 0 | O83: =MIN(C83+I83,N(Debts!D8)) -> 0 | P83: =MIN(D83+J83,N(Debts!D9)) -> 0 | Q83: =MIN(E83+K83,N(Debts!D10)) -> 0 | R83: =MIN(F83+L83,N(Debts!D11)) -> 0 | S83: =MIN(G83+M83,N(Debts!D12)) -> 0 | T83: =Debts!$B$14 -> 286 | U83: =MAX(0,T83-SUM(N83:S83)) -> 286 | V83: =_xlfn.MINIFS($B$3:$G$3,B83:G83,">0.005") -> 0 | W83: =IF(B83<=0.005,0,MIN(B83+H83,N83+IF(B$3=$V83,$U83,0))) -> 0 | X83: =IF(C83<=0.005,0,MIN(C83+I83,O83+IF(C$3=$V83,$U83,0))) -> 0 | Y83: =IF(D83<=0.005,0,MIN(D83+J83,P83+IF(D$3=$V83,$U83,0))) -> 0 | Z83: =IF(E83<=0.005,0,MIN(E83+K83,Q83+IF(E$3=$V83,$U83,0))) -> 0 | AA83: =IF(F83<=0.005,0,MIN(F83+L83,R83+IF(F$3=$V83,$U83,0))) -> 0 | AB83: =IF(G83<=0.005,0,MIN(G83+M83,S83+IF(G$3=$V83,$U83,0))) -> 0 | AC83: =MAX(0,B83+H83-W83) -> 0 | AD83: =MAX(0,C83+I83-X83) -> 0 | AE83: =MAX(0,D83+J83-Y83) -> 0 | AF83: =MAX(0,E83+K83-Z83) -> 0 | AG83: =MAX(0,F83+L83-AA83) -> 0 | AH83: =MAX(0,G83+M83-AB83) -> 0 | AI83: =SUM(H83:M83) -> 0 | AJ83: =SUM(AC83:AH83) -> 0
A84: 80 | B84: =AC83 -> 0 | C84: =AD83 -> 0 | D84: =AE83 -> 0 | E84: =AF83 -> 0 | F84: =AG83 -> 0 | G84: =AH83 -> 0 | H84: =B84*N(Debts!C7)/12 -> 0 | I84: =C84*N(Debts!C8)/12 -> 0 | J84: =D84*N(Debts!C9)/12 -> 0 | K84: =E84*N(Debts!C10)/12 -> 0 | L84: =F84*N(Debts!C11)/12 -> 0 | M84: =G84*N(Debts!C12)/12 -> 0 | N84: =MIN(B84+H84,N(Debts!D7)) -> 0 | O84: =MIN(C84+I84,N(Debts!D8)) -> 0 | P84: =MIN(D84+J84,N(Debts!D9)) -> 0 | Q84: =MIN(E84+K84,N(Debts!D10)) -> 0 | R84: =MIN(F84+L84,N(Debts!D11)) -> 0 | S84: =MIN(G84+M84,N(Debts!D12)) -> 0 | T84: =Debts!$B$14 -> 286 | U84: =MAX(0,T84-SUM(N84:S84)) -> 286 | V84: =_xlfn.MINIFS($B$3:$G$3,B84:G84,">0.005") -> 0 | W84: =IF(B84<=0.005,0,MIN(B84+H84,N84+IF(B$3=$V84,$U84,0))) -> 0 | X84: =IF(C84<=0.005,0,MIN(C84+I84,O84+IF(C$3=$V84,$U84,0))) -> 0 | Y84: =IF(D84<=0.005,0,MIN(D84+J84,P84+IF(D$3=$V84,$U84,0))) -> 0 | Z84: =IF(E84<=0.005,0,MIN(E84+K84,Q84+IF(E$3=$V84,$U84,0))) -> 0 | AA84: =IF(F84<=0.005,0,MIN(F84+L84,R84+IF(F$3=$V84,$U84,0))) -> 0 | AB84: =IF(G84<=0.005,0,MIN(G84+M84,S84+IF(G$3=$V84,$U84,0))) -> 0 | AC84: =MAX(0,B84+H84-W84) -> 0 | AD84: =MAX(0,C84+I84-X84) -> 0 | AE84: =MAX(0,D84+J84-Y84) -> 0 | AF84: =MAX(0,E84+K84-Z84) -> 0 | AG84: =MAX(0,F84+L84-AA84) -> 0 | AH84: =MAX(0,G84+M84-AB84) -> 0 | AI84: =SUM(H84:M84) -> 0 | AJ84: =SUM(AC84:AH84) -> 0
A85: 81 | B85: =AC84 -> 0 | C85: =AD84 -> 0 | D85: =AE84 -> 0 | E85: =AF84 -> 0 | F85: =AG84 -> 0 | G85: =AH84 -> 0 | H85: =B85*N(Debts!C7)/12 -> 0 | I85: =C85*N(Debts!C8)/12 -> 0 | J85: =D85*N(Debts!C9)/12 -> 0 | K85: =E85*N(Debts!C10)/12 -> 0 | L85: =F85*N(Debts!C11)/12 -> 0 | M85: =G85*N(Debts!C12)/12 -> 0 | N85: =MIN(B85+H85,N(Debts!D7)) -> 0 | O85: =MIN(C85+I85,N(Debts!D8)) -> 0 | P85: =MIN(D85+J85,N(Debts!D9)) -> 0 | Q85: =MIN(E85+K85,N(Debts!D10)) -> 0 | R85: =MIN(F85+L85,N(Debts!D11)) -> 0 | S85: =MIN(G85+M85,N(Debts!D12)) -> 0 | T85: =Debts!$B$14 -> 286 | U85: =MAX(0,T85-SUM(N85:S85)) -> 286 | V85: =_xlfn.MINIFS($B$3:$G$3,B85:G85,">0.005") -> 0 | W85: =IF(B85<=0.005,0,MIN(B85+H85,N85+IF(B$3=$V85,$U85,0))) -> 0 | X85: =IF(C85<=0.005,0,MIN(C85+I85,O85+IF(C$3=$V85,$U85,0))) -> 0 | Y85: =IF(D85<=0.005,0,MIN(D85+J85,P85+IF(D$3=$V85,$U85,0))) -> 0 | Z85: =IF(E85<=0.005,0,MIN(E85+K85,Q85+IF(E$3=$V85,$U85,0))) -> 0 | AA85: =IF(F85<=0.005,0,MIN(F85+L85,R85+IF(F$3=$V85,$U85,0))) -> 0 | AB85: =IF(G85<=0.005,0,MIN(G85+M85,S85+IF(G$3=$V85,$U85,0))) -> 0 | AC85: =MAX(0,B85+H85-W85) -> 0 | AD85: =MAX(0,C85+I85-X85) -> 0 | AE85: =MAX(0,D85+J85-Y85) -> 0 | AF85: =MAX(0,E85+K85-Z85) -> 0 | AG85: =MAX(0,F85+L85-AA85) -> 0 | AH85: =MAX(0,G85+M85-AB85) -> 0 | AI85: =SUM(H85:M85) -> 0 | AJ85: =SUM(AC85:AH85) -> 0
A86: 82 | B86: =AC85 -> 0 | C86: =AD85 -> 0 | D86: =AE85 -> 0 | E86: =AF85 -> 0 | F86: =AG85 -> 0 | G86: =AH85 -> 0 | H86: =B86*N(Debts!C7)/12 -> 0 | I86: =C86*N(Debts!C8)/12 -> 0 | J86: =D86*N(Debts!C9)/12 -> 0 | K86: =E86*N(Debts!C10)/12 -> 0 | L86: =F86*N(Debts!C11)/12 -> 0 | M86: =G86*N(Debts!C12)/12 -> 0 | N86: =MIN(B86+H86,N(Debts!D7)) -> 0 | O86: =MIN(C86+I86,N(Debts!D8)) -> 0 | P86: =MIN(D86+J86,N(Debts!D9)) -> 0 | Q86: =MIN(E86+K86,N(Debts!D10)) -> 0 | R86: =MIN(F86+L86,N(Debts!D11)) -> 0 | S86: =MIN(G86+M86,N(Debts!D12)) -> 0 | T86: =Debts!$B$14 -> 286 | U86: =MAX(0,T86-SUM(N86:S86)) -> 286 | V86: =_xlfn.MINIFS($B$3:$G$3,B86:G86,">0.005") -> 0 | W86: =IF(B86<=0.005,0,MIN(B86+H86,N86+IF(B$3=$V86,$U86,0))) -> 0 | X86: =IF(C86<=0.005,0,MIN(C86+I86,O86+IF(C$3=$V86,$U86,0))) -> 0 | Y86: =IF(D86<=0.005,0,MIN(D86+J86,P86+IF(D$3=$V86,$U86,0))) -> 0 | Z86: =IF(E86<=0.005,0,MIN(E86+K86,Q86+IF(E$3=$V86,$U86,0))) -> 0 | AA86: =IF(F86<=0.005,0,MIN(F86+L86,R86+IF(F$3=$V86,$U86,0))) -> 0 | AB86: =IF(G86<=0.005,0,MIN(G86+M86,S86+IF(G$3=$V86,$U86,0))) -> 0 | AC86: =MAX(0,B86+H86-W86) -> 0 | AD86: =MAX(0,C86+I86-X86) -> 0 | AE86: =MAX(0,D86+J86-Y86) -> 0 | AF86: =MAX(0,E86+K86-Z86) -> 0 | AG86: =MAX(0,F86+L86-AA86) -> 0 | AH86: =MAX(0,G86+M86-AB86) -> 0 | AI86: =SUM(H86:M86) -> 0 | AJ86: =SUM(AC86:AH86) -> 0
A87: 83 | B87: =AC86 -> 0 | C87: =AD86 -> 0 | D87: =AE86 -> 0 | E87: =AF86 -> 0 | F87: =AG86 -> 0 | G87: =AH86 -> 0 | H87: =B87*N(Debts!C7)/12 -> 0 | I87: =C87*N(Debts!C8)/12 -> 0 | J87: =D87*N(Debts!C9)/12 -> 0 | K87: =E87*N(Debts!C10)/12 -> 0 | L87: =F87*N(Debts!C11)/12 -> 0 | M87: =G87*N(Debts!C12)/12 -> 0 | N87: =MIN(B87+H87,N(Debts!D7)) -> 0 | O87: =MIN(C87+I87,N(Debts!D8)) -> 0 | P87: =MIN(D87+J87,N(Debts!D9)) -> 0 | Q87: =MIN(E87+K87,N(Debts!D10)) -> 0 | R87: =MIN(F87+L87,N(Debts!D11)) -> 0 | S87: =MIN(G87+M87,N(Debts!D12)) -> 0 | T87: =Debts!$B$14 -> 286 | U87: =MAX(0,T87-SUM(N87:S87)) -> 286 | V87: =_xlfn.MINIFS($B$3:$G$3,B87:G87,">0.005") -> 0 | W87: =IF(B87<=0.005,0,MIN(B87+H87,N87+IF(B$3=$V87,$U87,0))) -> 0 | X87: =IF(C87<=0.005,0,MIN(C87+I87,O87+IF(C$3=$V87,$U87,0))) -> 0 | Y87: =IF(D87<=0.005,0,MIN(D87+J87,P87+IF(D$3=$V87,$U87,0))) -> 0 | Z87: =IF(E87<=0.005,0,MIN(E87+K87,Q87+IF(E$3=$V87,$U87,0))) -> 0 | AA87: =IF(F87<=0.005,0,MIN(F87+L87,R87+IF(F$3=$V87,$U87,0))) -> 0 | AB87: =IF(G87<=0.005,0,MIN(G87+M87,S87+IF(G$3=$V87,$U87,0))) -> 0 | AC87: =MAX(0,B87+H87-W87) -> 0 | AD87: =MAX(0,C87+I87-X87) -> 0 | AE87: =MAX(0,D87+J87-Y87) -> 0 | AF87: =MAX(0,E87+K87-Z87) -> 0 | AG87: =MAX(0,F87+L87-AA87) -> 0 | AH87: =MAX(0,G87+M87-AB87) -> 0 | AI87: =SUM(H87:M87) -> 0 | AJ87: =SUM(AC87:AH87) -> 0
A88: 84 | B88: =AC87 -> 0 | C88: =AD87 -> 0 | D88: =AE87 -> 0 | E88: =AF87 -> 0 | F88: =AG87 -> 0 | G88: =AH87 -> 0 | H88: =B88*N(Debts!C7)/12 -> 0 | I88: =C88*N(Debts!C8)/12 -> 0 | J88: =D88*N(Debts!C9)/12 -> 0 | K88: =E88*N(Debts!C10)/12 -> 0 | L88: =F88*N(Debts!C11)/12 -> 0 | M88: =G88*N(Debts!C12)/12 -> 0 | N88: =MIN(B88+H88,N(Debts!D7)) -> 0 | O88: =MIN(C88+I88,N(Debts!D8)) -> 0 | P88: =MIN(D88+J88,N(Debts!D9)) -> 0 | Q88: =MIN(E88+K88,N(Debts!D10)) -> 0 | R88: =MIN(F88+L88,N(Debts!D11)) -> 0 | S88: =MIN(G88+M88,N(Debts!D12)) -> 0 | T88: =Debts!$B$14 -> 286 | U88: =MAX(0,T88-SUM(N88:S88)) -> 286 | V88: =_xlfn.MINIFS($B$3:$G$3,B88:G88,">0.005") -> 0 | W88: =IF(B88<=0.005,0,MIN(B88+H88,N88+IF(B$3=$V88,$U88,0))) -> 0 | X88: =IF(C88<=0.005,0,MIN(C88+I88,O88+IF(C$3=$V88,$U88,0))) -> 0 | Y88: =IF(D88<=0.005,0,MIN(D88+J88,P88+IF(D$3=$V88,$U88,0))) -> 0 | Z88: =IF(E88<=0.005,0,MIN(E88+K88,Q88+IF(E$3=$V88,$U88,0))) -> 0 | AA88: =IF(F88<=0.005,0,MIN(F88+L88,R88+IF(F$3=$V88,$U88,0))) -> 0 | AB88: =IF(G88<=0.005,0,MIN(G88+M88,S88+IF(G$3=$V88,$U88,0))) -> 0 | AC88: =MAX(0,B88+H88-W88) -> 0 | AD88: =MAX(0,C88+I88-X88) -> 0 | AE88: =MAX(0,D88+J88-Y88) -> 0 | AF88: =MAX(0,E88+K88-Z88) -> 0 | AG88: =MAX(0,F88+L88-AA88) -> 0 | AH88: =MAX(0,G88+M88-AB88) -> 0 | AI88: =SUM(H88:M88) -> 0 | AJ88: =SUM(AC88:AH88) -> 0
A89: 85 | B89: =AC88 -> 0 | C89: =AD88 -> 0 | D89: =AE88 -> 0 | E89: =AF88 -> 0 | F89: =AG88 -> 0 | G89: =AH88 -> 0 | H89: =B89*N(Debts!C7)/12 -> 0 | I89: =C89*N(Debts!C8)/12 -> 0 | J89: =D89*N(Debts!C9)/12 -> 0 | K89: =E89*N(Debts!C10)/12 -> 0 | L89: =F89*N(Debts!C11)/12 -> 0 | M89: =G89*N(Debts!C12)/12 -> 0 | N89: =MIN(B89+H89,N(Debts!D7)) -> 0 | O89: =MIN(C89+I89,N(Debts!D8)) -> 0 | P89: =MIN(D89+J89,N(Debts!D9)) -> 0 | Q89: =MIN(E89+K89,N(Debts!D10)) -> 0 | R89: =MIN(F89+L89,N(Debts!D11)) -> 0 | S89: =MIN(G89+M89,N(Debts!D12)) -> 0 | T89: =Debts!$B$14 -> 286 | U89: =MAX(0,T89-SUM(N89:S89)) -> 286 | V89: =_xlfn.MINIFS($B$3:$G$3,B89:G89,">0.005") -> 0 | W89: =IF(B89<=0.005,0,MIN(B89+H89,N89+IF(B$3=$V89,$U89,0))) -> 0 | X89: =IF(C89<=0.005,0,MIN(C89+I89,O89+IF(C$3=$V89,$U89,0))) -> 0 | Y89: =IF(D89<=0.005,0,MIN(D89+J89,P89+IF(D$3=$V89,$U89,0))) -> 0 | Z89: =IF(E89<=0.005,0,MIN(E89+K89,Q89+IF(E$3=$V89,$U89,0))) -> 0 | AA89: =IF(F89<=0.005,0,MIN(F89+L89,R89+IF(F$3=$V89,$U89,0))) -> 0 | AB89: =IF(G89<=0.005,0,MIN(G89+M89,S89+IF(G$3=$V89,$U89,0))) -> 0 | AC89: =MAX(0,B89+H89-W89) -> 0 | AD89: =MAX(0,C89+I89-X89) -> 0 | AE89: =MAX(0,D89+J89-Y89) -> 0 | AF89: =MAX(0,E89+K89-Z89) -> 0 | AG89: =MAX(0,F89+L89-AA89) -> 0 | AH89: =MAX(0,G89+M89-AB89) -> 0 | AI89: =SUM(H89:M89) -> 0 | AJ89: =SUM(AC89:AH89) -> 0
A90: 86 | B90: =AC89 -> 0 | C90: =AD89 -> 0 | D90: =AE89 -> 0 | E90: =AF89 -> 0 | F90: =AG89 -> 0 | G90: =AH89 -> 0 | H90: =B90*N(Debts!C7)/12 -> 0 | I90: =C90*N(Debts!C8)/12 -> 0 | J90: =D90*N(Debts!C9)/12 -> 0 | K90: =E90*N(Debts!C10)/12 -> 0 | L90: =F90*N(Debts!C11)/12 -> 0 | M90: =G90*N(Debts!C12)/12 -> 0 | N90: =MIN(B90+H90,N(Debts!D7)) -> 0 | O90: =MIN(C90+I90,N(Debts!D8)) -> 0 | P90: =MIN(D90+J90,N(Debts!D9)) -> 0 | Q90: =MIN(E90+K90,N(Debts!D10)) -> 0 | R90: =MIN(F90+L90,N(Debts!D11)) -> 0 | S90: =MIN(G90+M90,N(Debts!D12)) -> 0 | T90: =Debts!$B$14 -> 286 | U90: =MAX(0,T90-SUM(N90:S90)) -> 286 | V90: =_xlfn.MINIFS($B$3:$G$3,B90:G90,">0.005") -> 0 | W90: =IF(B90<=0.005,0,MIN(B90+H90,N90+IF(B$3=$V90,$U90,0))) -> 0 | X90: =IF(C90<=0.005,0,MIN(C90+I90,O90+IF(C$3=$V90,$U90,0))) -> 0 | Y90: =IF(D90<=0.005,0,MIN(D90+J90,P90+IF(D$3=$V90,$U90,0))) -> 0 | Z90: =IF(E90<=0.005,0,MIN(E90+K90,Q90+IF(E$3=$V90,$U90,0))) -> 0 | AA90: =IF(F90<=0.005,0,MIN(F90+L90,R90+IF(F$3=$V90,$U90,0))) -> 0 | AB90: =IF(G90<=0.005,0,MIN(G90+M90,S90+IF(G$3=$V90,$U90,0))) -> 0 | AC90: =MAX(0,B90+H90-W90) -> 0 | AD90: =MAX(0,C90+I90-X90) -> 0 | AE90: =MAX(0,D90+J90-Y90) -> 0 | AF90: =MAX(0,E90+K90-Z90) -> 0 | AG90: =MAX(0,F90+L90-AA90) -> 0 | AH90: =MAX(0,G90+M90-AB90) -> 0 | AI90: =SUM(H90:M90) -> 0 | AJ90: =SUM(AC90:AH90) -> 0
A91: 87 | B91: =AC90 -> 0 | C91: =AD90 -> 0 | D91: =AE90 -> 0 | E91: =AF90 -> 0 | F91: =AG90 -> 0 | G91: =AH90 -> 0 | H91: =B91*N(Debts!C7)/12 -> 0 | I91: =C91*N(Debts!C8)/12 -> 0 | J91: =D91*N(Debts!C9)/12 -> 0 | K91: =E91*N(Debts!C10)/12 -> 0 | L91: =F91*N(Debts!C11)/12 -> 0 | M91: =G91*N(Debts!C12)/12 -> 0 | N91: =MIN(B91+H91,N(Debts!D7)) -> 0 | O91: =MIN(C91+I91,N(Debts!D8)) -> 0 | P91: =MIN(D91+J91,N(Debts!D9)) -> 0 | Q91: =MIN(E91+K91,N(Debts!D10)) -> 0 | R91: =MIN(F91+L91,N(Debts!D11)) -> 0 | S91: =MIN(G91+M91,N(Debts!D12)) -> 0 | T91: =Debts!$B$14 -> 286 | U91: =MAX(0,T91-SUM(N91:S91)) -> 286 | V91: =_xlfn.MINIFS($B$3:$G$3,B91:G91,">0.005") -> 0 | W91: =IF(B91<=0.005,0,MIN(B91+H91,N91+IF(B$3=$V91,$U91,0))) -> 0 | X91: =IF(C91<=0.005,0,MIN(C91+I91,O91+IF(C$3=$V91,$U91,0))) -> 0 | Y91: =IF(D91<=0.005,0,MIN(D91+J91,P91+IF(D$3=$V91,$U91,0))) -> 0 | Z91: =IF(E91<=0.005,0,MIN(E91+K91,Q91+IF(E$3=$V91,$U91,0))) -> 0 | AA91: =IF(F91<=0.005,0,MIN(F91+L91,R91+IF(F$3=$V91,$U91,0))) -> 0 | AB91: =IF(G91<=0.005,0,MIN(G91+M91,S91+IF(G$3=$V91,$U91,0))) -> 0 | AC91: =MAX(0,B91+H91-W91) -> 0 | AD91: =MAX(0,C91+I91-X91) -> 0 | AE91: =MAX(0,D91+J91-Y91) -> 0 | AF91: =MAX(0,E91+K91-Z91) -> 0 | AG91: =MAX(0,F91+L91-AA91) -> 0 | AH91: =MAX(0,G91+M91-AB91) -> 0 | AI91: =SUM(H91:M91) -> 0 | AJ91: =SUM(AC91:AH91) -> 0
A92: 88 | B92: =AC91 -> 0 | C92: =AD91 -> 0 | D92: =AE91 -> 0 | E92: =AF91 -> 0 | F92: =AG91 -> 0 | G92: =AH91 -> 0 | H92: =B92*N(Debts!C7)/12 -> 0 | I92: =C92*N(Debts!C8)/12 -> 0 | J92: =D92*N(Debts!C9)/12 -> 0 | K92: =E92*N(Debts!C10)/12 -> 0 | L92: =F92*N(Debts!C11)/12 -> 0 | M92: =G92*N(Debts!C12)/12 -> 0 | N92: =MIN(B92+H92,N(Debts!D7)) -> 0 | O92: =MIN(C92+I92,N(Debts!D8)) -> 0 | P92: =MIN(D92+J92,N(Debts!D9)) -> 0 | Q92: =MIN(E92+K92,N(Debts!D10)) -> 0 | R92: =MIN(F92+L92,N(Debts!D11)) -> 0 | S92: =MIN(G92+M92,N(Debts!D12)) -> 0 | T92: =Debts!$B$14 -> 286 | U92: =MAX(0,T92-SUM(N92:S92)) -> 286 | V92: =_xlfn.MINIFS($B$3:$G$3,B92:G92,">0.005") -> 0 | W92: =IF(B92<=0.005,0,MIN(B92+H92,N92+IF(B$3=$V92,$U92,0))) -> 0 | X92: =IF(C92<=0.005,0,MIN(C92+I92,O92+IF(C$3=$V92,$U92,0))) -> 0 | Y92: =IF(D92<=0.005,0,MIN(D92+J92,P92+IF(D$3=$V92,$U92,0))) -> 0 | Z92: =IF(E92<=0.005,0,MIN(E92+K92,Q92+IF(E$3=$V92,$U92,0))) -> 0 | AA92: =IF(F92<=0.005,0,MIN(F92+L92,R92+IF(F$3=$V92,$U92,0))) -> 0 | AB92: =IF(G92<=0.005,0,MIN(G92+M92,S92+IF(G$3=$V92,$U92,0))) -> 0 | AC92: =MAX(0,B92+H92-W92) -> 0 | AD92: =MAX(0,C92+I92-X92) -> 0 | AE92: =MAX(0,D92+J92-Y92) -> 0 | AF92: =MAX(0,E92+K92-Z92) -> 0 | AG92: =MAX(0,F92+L92-AA92) -> 0 | AH92: =MAX(0,G92+M92-AB92) -> 0 | AI92: =SUM(H92:M92) -> 0 | AJ92: =SUM(AC92:AH92) -> 0
A93: 89 | B93: =AC92 -> 0 | C93: =AD92 -> 0 | D93: =AE92 -> 0 | E93: =AF92 -> 0 | F93: =AG92 -> 0 | G93: =AH92 -> 0 | H93: =B93*N(Debts!C7)/12 -> 0 | I93: =C93*N(Debts!C8)/12 -> 0 | J93: =D93*N(Debts!C9)/12 -> 0 | K93: =E93*N(Debts!C10)/12 -> 0 | L93: =F93*N(Debts!C11)/12 -> 0 | M93: =G93*N(Debts!C12)/12 -> 0 | N93: =MIN(B93+H93,N(Debts!D7)) -> 0 | O93: =MIN(C93+I93,N(Debts!D8)) -> 0 | P93: =MIN(D93+J93,N(Debts!D9)) -> 0 | Q93: =MIN(E93+K93,N(Debts!D10)) -> 0 | R93: =MIN(F93+L93,N(Debts!D11)) -> 0 | S93: =MIN(G93+M93,N(Debts!D12)) -> 0 | T93: =Debts!$B$14 -> 286 | U93: =MAX(0,T93-SUM(N93:S93)) -> 286 | V93: =_xlfn.MINIFS($B$3:$G$3,B93:G93,">0.005") -> 0 | W93: =IF(B93<=0.005,0,MIN(B93+H93,N93+IF(B$3=$V93,$U93,0))) -> 0 | X93: =IF(C93<=0.005,0,MIN(C93+I93,O93+IF(C$3=$V93,$U93,0))) -> 0 | Y93: =IF(D93<=0.005,0,MIN(D93+J93,P93+IF(D$3=$V93,$U93,0))) -> 0 | Z93: =IF(E93<=0.005,0,MIN(E93+K93,Q93+IF(E$3=$V93,$U93,0))) -> 0 | AA93: =IF(F93<=0.005,0,MIN(F93+L93,R93+IF(F$3=$V93,$U93,0))) -> 0 | AB93: =IF(G93<=0.005,0,MIN(G93+M93,S93+IF(G$3=$V93,$U93,0))) -> 0 | AC93: =MAX(0,B93+H93-W93) -> 0 | AD93: =MAX(0,C93+I93-X93) -> 0 | AE93: =MAX(0,D93+J93-Y93) -> 0 | AF93: =MAX(0,E93+K93-Z93) -> 0 | AG93: =MAX(0,F93+L93-AA93) -> 0 | AH93: =MAX(0,G93+M93-AB93) -> 0 | AI93: =SUM(H93:M93) -> 0 | AJ93: =SUM(AC93:AH93) -> 0
A94: 90 | B94: =AC93 -> 0 | C94: =AD93 -> 0 | D94: =AE93 -> 0 | E94: =AF93 -> 0 | F94: =AG93 -> 0 | G94: =AH93 -> 0 | H94: =B94*N(Debts!C7)/12 -> 0 | I94: =C94*N(Debts!C8)/12 -> 0 | J94: =D94*N(Debts!C9)/12 -> 0 | K94: =E94*N(Debts!C10)/12 -> 0 | L94: =F94*N(Debts!C11)/12 -> 0 | M94: =G94*N(Debts!C12)/12 -> 0 | N94: =MIN(B94+H94,N(Debts!D7)) -> 0 | O94: =MIN(C94+I94,N(Debts!D8)) -> 0 | P94: =MIN(D94+J94,N(Debts!D9)) -> 0 | Q94: =MIN(E94+K94,N(Debts!D10)) -> 0 | R94: =MIN(F94+L94,N(Debts!D11)) -> 0 | S94: =MIN(G94+M94,N(Debts!D12)) -> 0 | T94: =Debts!$B$14 -> 286 | U94: =MAX(0,T94-SUM(N94:S94)) -> 286 | V94: =_xlfn.MINIFS($B$3:$G$3,B94:G94,">0.005") -> 0 | W94: =IF(B94<=0.005,0,MIN(B94+H94,N94+IF(B$3=$V94,$U94,0))) -> 0 | X94: =IF(C94<=0.005,0,MIN(C94+I94,O94+IF(C$3=$V94,$U94,0))) -> 0 | Y94: =IF(D94<=0.005,0,MIN(D94+J94,P94+IF(D$3=$V94,$U94,0))) -> 0 | Z94: =IF(E94<=0.005,0,MIN(E94+K94,Q94+IF(E$3=$V94,$U94,0))) -> 0 | AA94: =IF(F94<=0.005,0,MIN(F94+L94,R94+IF(F$3=$V94,$U94,0))) -> 0 | AB94: =IF(G94<=0.005,0,MIN(G94+M94,S94+IF(G$3=$V94,$U94,0))) -> 0 | AC94: =MAX(0,B94+H94-W94) -> 0 | AD94: =MAX(0,C94+I94-X94) -> 0 | AE94: =MAX(0,D94+J94-Y94) -> 0 | AF94: =MAX(0,E94+K94-Z94) -> 0 | AG94: =MAX(0,F94+L94-AA94) -> 0 | AH94: =MAX(0,G94+M94-AB94) -> 0 | AI94: =SUM(H94:M94) -> 0 | AJ94: =SUM(AC94:AH94) -> 0
A95: 91 | B95: =AC94 -> 0 | C95: =AD94 -> 0 | D95: =AE94 -> 0 | E95: =AF94 -> 0 | F95: =AG94 -> 0 | G95: =AH94 -> 0 | H95: =B95*N(Debts!C7)/12 -> 0 | I95: =C95*N(Debts!C8)/12 -> 0 | J95: =D95*N(Debts!C9)/12 -> 0 | K95: =E95*N(Debts!C10)/12 -> 0 | L95: =F95*N(Debts!C11)/12 -> 0 | M95: =G95*N(Debts!C12)/12 -> 0 | N95: =MIN(B95+H95,N(Debts!D7)) -> 0 | O95: =MIN(C95+I95,N(Debts!D8)) -> 0 | P95: =MIN(D95+J95,N(Debts!D9)) -> 0 | Q95: =MIN(E95+K95,N(Debts!D10)) -> 0 | R95: =MIN(F95+L95,N(Debts!D11)) -> 0 | S95: =MIN(G95+M95,N(Debts!D12)) -> 0 | T95: =Debts!$B$14 -> 286 | U95: =MAX(0,T95-SUM(N95:S95)) -> 286 | V95: =_xlfn.MINIFS($B$3:$G$3,B95:G95,">0.005") -> 0 | W95: =IF(B95<=0.005,0,MIN(B95+H95,N95+IF(B$3=$V95,$U95,0))) -> 0 | X95: =IF(C95<=0.005,0,MIN(C95+I95,O95+IF(C$3=$V95,$U95,0))) -> 0 | Y95: =IF(D95<=0.005,0,MIN(D95+J95,P95+IF(D$3=$V95,$U95,0))) -> 0 | Z95: =IF(E95<=0.005,0,MIN(E95+K95,Q95+IF(E$3=$V95,$U95,0))) -> 0 | AA95: =IF(F95<=0.005,0,MIN(F95+L95,R95+IF(F$3=$V95,$U95,0))) -> 0 | AB95: =IF(G95<=0.005,0,MIN(G95+M95,S95+IF(G$3=$V95,$U95,0))) -> 0 | AC95: =MAX(0,B95+H95-W95) -> 0 | AD95: =MAX(0,C95+I95-X95) -> 0 | AE95: =MAX(0,D95+J95-Y95) -> 0 | AF95: =MAX(0,E95+K95-Z95) -> 0 | AG95: =MAX(0,F95+L95-AA95) -> 0 | AH95: =MAX(0,G95+M95-AB95) -> 0 | AI95: =SUM(H95:M95) -> 0 | AJ95: =SUM(AC95:AH95) -> 0
A96: 92 | B96: =AC95 -> 0 | C96: =AD95 -> 0 | D96: =AE95 -> 0 | E96: =AF95 -> 0 | F96: =AG95 -> 0 | G96: =AH95 -> 0 | H96: =B96*N(Debts!C7)/12 -> 0 | I96: =C96*N(Debts!C8)/12 -> 0 | J96: =D96*N(Debts!C9)/12 -> 0 | K96: =E96*N(Debts!C10)/12 -> 0 | L96: =F96*N(Debts!C11)/12 -> 0 | M96: =G96*N(Debts!C12)/12 -> 0 | N96: =MIN(B96+H96,N(Debts!D7)) -> 0 | O96: =MIN(C96+I96,N(Debts!D8)) -> 0 | P96: =MIN(D96+J96,N(Debts!D9)) -> 0 | Q96: =MIN(E96+K96,N(Debts!D10)) -> 0 | R96: =MIN(F96+L96,N(Debts!D11)) -> 0 | S96: =MIN(G96+M96,N(Debts!D12)) -> 0 | T96: =Debts!$B$14 -> 286 | U96: =MAX(0,T96-SUM(N96:S96)) -> 286 | V96: =_xlfn.MINIFS($B$3:$G$3,B96:G96,">0.005") -> 0 | W96: =IF(B96<=0.005,0,MIN(B96+H96,N96+IF(B$3=$V96,$U96,0))) -> 0 | X96: =IF(C96<=0.005,0,MIN(C96+I96,O96+IF(C$3=$V96,$U96,0))) -> 0 | Y96: =IF(D96<=0.005,0,MIN(D96+J96,P96+IF(D$3=$V96,$U96,0))) -> 0 | Z96: =IF(E96<=0.005,0,MIN(E96+K96,Q96+IF(E$3=$V96,$U96,0))) -> 0 | AA96: =IF(F96<=0.005,0,MIN(F96+L96,R96+IF(F$3=$V96,$U96,0))) -> 0 | AB96: =IF(G96<=0.005,0,MIN(G96+M96,S96+IF(G$3=$V96,$U96,0))) -> 0 | AC96: =MAX(0,B96+H96-W96) -> 0 | AD96: =MAX(0,C96+I96-X96) -> 0 | AE96: =MAX(0,D96+J96-Y96) -> 0 | AF96: =MAX(0,E96+K96-Z96) -> 0 | AG96: =MAX(0,F96+L96-AA96) -> 0 | AH96: =MAX(0,G96+M96-AB96) -> 0 | AI96: =SUM(H96:M96) -> 0 | AJ96: =SUM(AC96:AH96) -> 0
A97: 93 | B97: =AC96 -> 0 | C97: =AD96 -> 0 | D97: =AE96 -> 0 | E97: =AF96 -> 0 | F97: =AG96 -> 0 | G97: =AH96 -> 0 | H97: =B97*N(Debts!C7)/12 -> 0 | I97: =C97*N(Debts!C8)/12 -> 0 | J97: =D97*N(Debts!C9)/12 -> 0 | K97: =E97*N(Debts!C10)/12 -> 0 | L97: =F97*N(Debts!C11)/12 -> 0 | M97: =G97*N(Debts!C12)/12 -> 0 | N97: =MIN(B97+H97,N(Debts!D7)) -> 0 | O97: =MIN(C97+I97,N(Debts!D8)) -> 0 | P97: =MIN(D97+J97,N(Debts!D9)) -> 0 | Q97: =MIN(E97+K97,N(Debts!D10)) -> 0 | R97: =MIN(F97+L97,N(Debts!D11)) -> 0 | S97: =MIN(G97+M97,N(Debts!D12)) -> 0 | T97: =Debts!$B$14 -> 286 | U97: =MAX(0,T97-SUM(N97:S97)) -> 286 | V97: =_xlfn.MINIFS($B$3:$G$3,B97:G97,">0.005") -> 0 | W97: =IF(B97<=0.005,0,MIN(B97+H97,N97+IF(B$3=$V97,$U97,0))) -> 0 | X97: =IF(C97<=0.005,0,MIN(C97+I97,O97+IF(C$3=$V97,$U97,0))) -> 0 | Y97: =IF(D97<=0.005,0,MIN(D97+J97,P97+IF(D$3=$V97,$U97,0))) -> 0 | Z97: =IF(E97<=0.005,0,MIN(E97+K97,Q97+IF(E$3=$V97,$U97,0))) -> 0 | AA97: =IF(F97<=0.005,0,MIN(F97+L97,R97+IF(F$3=$V97,$U97,0))) -> 0 | AB97: =IF(G97<=0.005,0,MIN(G97+M97,S97+IF(G$3=$V97,$U97,0))) -> 0 | AC97: =MAX(0,B97+H97-W97) -> 0 | AD97: =MAX(0,C97+I97-X97) -> 0 | AE97: =MAX(0,D97+J97-Y97) -> 0 | AF97: =MAX(0,E97+K97-Z97) -> 0 | AG97: =MAX(0,F97+L97-AA97) -> 0 | AH97: =MAX(0,G97+M97-AB97) -> 0 | AI97: =SUM(H97:M97) -> 0 | AJ97: =SUM(AC97:AH97) -> 0
A98: 94 | B98: =AC97 -> 0 | C98: =AD97 -> 0 | D98: =AE97 -> 0 | E98: =AF97 -> 0 | F98: =AG97 -> 0 | G98: =AH97 -> 0 | H98: =B98*N(Debts!C7)/12 -> 0 | I98: =C98*N(Debts!C8)/12 -> 0 | J98: =D98*N(Debts!C9)/12 -> 0 | K98: =E98*N(Debts!C10)/12 -> 0 | L98: =F98*N(Debts!C11)/12 -> 0 | M98: =G98*N(Debts!C12)/12 -> 0 | N98: =MIN(B98+H98,N(Debts!D7)) -> 0 | O98: =MIN(C98+I98,N(Debts!D8)) -> 0 | P98: =MIN(D98+J98,N(Debts!D9)) -> 0 | Q98: =MIN(E98+K98,N(Debts!D10)) -> 0 | R98: =MIN(F98+L98,N(Debts!D11)) -> 0 | S98: =MIN(G98+M98,N(Debts!D12)) -> 0 | T98: =Debts!$B$14 -> 286 | U98: =MAX(0,T98-SUM(N98:S98)) -> 286 | V98: =_xlfn.MINIFS($B$3:$G$3,B98:G98,">0.005") -> 0 | W98: =IF(B98<=0.005,0,MIN(B98+H98,N98+IF(B$3=$V98,$U98,0))) -> 0 | X98: =IF(C98<=0.005,0,MIN(C98+I98,O98+IF(C$3=$V98,$U98,0))) -> 0 | Y98: =IF(D98<=0.005,0,MIN(D98+J98,P98+IF(D$3=$V98,$U98,0))) -> 0 | Z98: =IF(E98<=0.005,0,MIN(E98+K98,Q98+IF(E$3=$V98,$U98,0))) -> 0 | AA98: =IF(F98<=0.005,0,MIN(F98+L98,R98+IF(F$3=$V98,$U98,0))) -> 0 | AB98: =IF(G98<=0.005,0,MIN(G98+M98,S98+IF(G$3=$V98,$U98,0))) -> 0 | AC98: =MAX(0,B98+H98-W98) -> 0 | AD98: =MAX(0,C98+I98-X98) -> 0 | AE98: =MAX(0,D98+J98-Y98) -> 0 | AF98: =MAX(0,E98+K98-Z98) -> 0 | AG98: =MAX(0,F98+L98-AA98) -> 0 | AH98: =MAX(0,G98+M98-AB98) -> 0 | AI98: =SUM(H98:M98) -> 0 | AJ98: =SUM(AC98:AH98) -> 0
A99: 95 | B99: =AC98 -> 0 | C99: =AD98 -> 0 | D99: =AE98 -> 0 | E99: =AF98 -> 0 | F99: =AG98 -> 0 | G99: =AH98 -> 0 | H99: =B99*N(Debts!C7)/12 -> 0 | I99: =C99*N(Debts!C8)/12 -> 0 | J99: =D99*N(Debts!C9)/12 -> 0 | K99: =E99*N(Debts!C10)/12 -> 0 | L99: =F99*N(Debts!C11)/12 -> 0 | M99: =G99*N(Debts!C12)/12 -> 0 | N99: =MIN(B99+H99,N(Debts!D7)) -> 0 | O99: =MIN(C99+I99,N(Debts!D8)) -> 0 | P99: =MIN(D99+J99,N(Debts!D9)) -> 0 | Q99: =MIN(E99+K99,N(Debts!D10)) -> 0 | R99: =MIN(F99+L99,N(Debts!D11)) -> 0 | S99: =MIN(G99+M99,N(Debts!D12)) -> 0 | T99: =Debts!$B$14 -> 286 | U99: =MAX(0,T99-SUM(N99:S99)) -> 286 | V99: =_xlfn.MINIFS($B$3:$G$3,B99:G99,">0.005") -> 0 | W99: =IF(B99<=0.005,0,MIN(B99+H99,N99+IF(B$3=$V99,$U99,0))) -> 0 | X99: =IF(C99<=0.005,0,MIN(C99+I99,O99+IF(C$3=$V99,$U99,0))) -> 0 | Y99: =IF(D99<=0.005,0,MIN(D99+J99,P99+IF(D$3=$V99,$U99,0))) -> 0 | Z99: =IF(E99<=0.005,0,MIN(E99+K99,Q99+IF(E$3=$V99,$U99,0))) -> 0 | AA99: =IF(F99<=0.005,0,MIN(F99+L99,R99+IF(F$3=$V99,$U99,0))) -> 0 | AB99: =IF(G99<=0.005,0,MIN(G99+M99,S99+IF(G$3=$V99,$U99,0))) -> 0 | AC99: =MAX(0,B99+H99-W99) -> 0 | AD99: =MAX(0,C99+I99-X99) -> 0 | AE99: =MAX(0,D99+J99-Y99) -> 0 | AF99: =MAX(0,E99+K99-Z99) -> 0 | AG99: =MAX(0,F99+L99-AA99) -> 0 | AH99: =MAX(0,G99+M99-AB99) -> 0 | AI99: =SUM(H99:M99) -> 0 | AJ99: =SUM(AC99:AH99) -> 0
A100: 96 | B100: =AC99 -> 0 | C100: =AD99 -> 0 | D100: =AE99 -> 0 | E100: =AF99 -> 0 | F100: =AG99 -> 0 | G100: =AH99 -> 0 | H100: =B100*N(Debts!C7)/12 -> 0 | I100: =C100*N(Debts!C8)/12 -> 0 | J100: =D100*N(Debts!C9)/12 -> 0 | K100: =E100*N(Debts!C10)/12 -> 0 | L100: =F100*N(Debts!C11)/12 -> 0 | M100: =G100*N(Debts!C12)/12 -> 0 | N100: =MIN(B100+H100,N(Debts!D7)) -> 0 | O100: =MIN(C100+I100,N(Debts!D8)) -> 0 | P100: =MIN(D100+J100,N(Debts!D9)) -> 0 | Q100: =MIN(E100+K100,N(Debts!D10)) -> 0 | R100: =MIN(F100+L100,N(Debts!D11)) -> 0 | S100: =MIN(G100+M100,N(Debts!D12)) -> 0 | T100: =Debts!$B$14 -> 286 | U100: =MAX(0,T100-SUM(N100:S100)) -> 286 | V100: =_xlfn.MINIFS($B$3:$G$3,B100:G100,">0.005") -> 0 | W100: =IF(B100<=0.005,0,MIN(B100+H100,N100+IF(B$3=$V100,$U100,0))) -> 0 | X100: =IF(C100<=0.005,0,MIN(C100+I100,O100+IF(C$3=$V100,$U100,0))) -> 0 | Y100: =IF(D100<=0.005,0,MIN(D100+J100,P100+IF(D$3=$V100,$U100,0))) -> 0 | Z100: =IF(E100<=0.005,0,MIN(E100+K100,Q100+IF(E$3=$V100,$U100,0))) -> 0 | AA100: =IF(F100<=0.005,0,MIN(F100+L100,R100+IF(F$3=$V100,$U100,0))) -> 0 | AB100: =IF(G100<=0.005,0,MIN(G100+M100,S100+IF(G$3=$V100,$U100,0))) -> 0 | AC100: =MAX(0,B100+H100-W100) -> 0 | AD100: =MAX(0,C100+I100-X100) -> 0 | AE100: =MAX(0,D100+J100-Y100) -> 0 | AF100: =MAX(0,E100+K100-Z100) -> 0 | AG100: =MAX(0,F100+L100-AA100) -> 0 | AH100: =MAX(0,G100+M100-AB100) -> 0 | AI100: =SUM(H100:M100) -> 0 | AJ100: =SUM(AC100:AH100) -> 0
...
